Workbook
Name Aguacate: Caracteristicas!$A$39
Name AMAZONAS: departamento!$F$3:$F$13
Name ANTIOQUIA: departamento!$G$3:$G$127
Name ARAUCA: departamento!$H$3:$H$9
Name ATLÁNTICO: departamento!$I$3:$I$25
Name BOLÍVAR: departamento!$J$3:$J$48
Name BOYACÁ: departamento!$K$3:$K$125
Name Cacao: Caracteristicas!$B$39
Name Café: Caracteristicas!$C$39
Name CALDAS: departamento!$L$3:$L$29
Name Caña_Azucar: Caracteristicas!$L$39:$L$41
Name CAQUETÁ: departamento!$M$3:$M$18
Name CASANARE: departamento!$N$3:$N$21
Name CAUCA: departamento!$O$3:$O$44
Name CESAR: departamento!$P$3:$P$27
Name CHOCÓ: departamento!$Q$3:$Q$33
Name CÓRDOBA: departamento!$R$3:$R$32
Name CUNDINAMARCA: departamento!$S$3:$S$118
Name Eucalipto: Caracteristicas!$D$39
Name GUAINÍA: departamento!$T$3:$T$10
Name GUAVIARE: departamento!$U$3:$U$6
Name HUILA: departamento!$V$3:$V$39
Name Limón: Caracteristicas!$E$39:$E$41
Name MAGDALENA: departamento!$X$3:$X$32
Name Mandarina: Caracteristicas!$F$39
Name Mango: Caracteristicas!$G$39
Name META: departamento!$Y$3:$Y$31
Name Naranja: Caracteristicas!$K$39:$K$40
Name NARIÑO: departamento!$Z$3:$Z$66
Name NORTE_DE_SANTANDER: departamento!$AA$3:$AA$42
Name Palma_Aceite: Caracteristicas!$H$39:$H$40
Name Plátano: Caracteristicas!$I$39
Name PUTUMAYO: departamento!$AB$3:$AB$15
Name QUINDÍO: departamento!$AC$3:$AC$14
Name RISARALDA: departamento!$AD$3:$AD$16
Name SANTANDER: departamento!$AE$3:$AE$89
Name SUCRE: departamento!$AF$3:$AF$28
Name TOLIMA: departamento!$AG$3:$AG$49
Name VALLE_DEL_CAUCA: departamento!$AH$3:$AH$44
Name VICHADA: departamento!$AJ$3:$AJ$6

Sheet Instrucciones
A1: MANUAL DE USO — AVALÚO DE CULTIVO (Res. 620/2008)
A2: Herramienta para perímetros agrícolas — Cálculo de valor justo del cultivo y banda de negociación
A4: CÓDIGO DE COLORES
A5: Color | B5: Significado | C5: Acción del usuario
A6: AZUL | B6: Valores editables | C6: Cambie el valor según el caso (cultivo, edad, precio, etc.)
A7: NEGRO | B7: Fórmula calculada | C7: No modificar — se actualiza automáticamente
A8: VERDE | B8: Enlace a otra hoja del libro | C8: No modificar — referencia interna
A9: ROJO | B9: Resultado clave del avalúo | C9: Lectura — valor que arroja la herramienta
A10: AMARILLO | B10: Celda clave que requiere atención | C10: Revisar antes de tomar el valor
A12: ESTRUCTURA DEL LIBRO — ¿QUÉ HACE CADA HOJA?
A13: # | B13: Hoja | C13: Función | D13: Tipo
A14: 1 | B14: Formulario | C14: Punto de entrada — cultivo, edad, departamento, municipio, precio de venta, área | D14: ENTRADA
A15: 2 | B15: PERITO | C15: Datos del perito y entidad emisora del avalúo | D15: ENTRADA
A16: 3 | B16: Entradas_Tasas | C16: Selección del método de tasa de descuento (DTF+Prima, CAPM, Finagro, WACC) | D16: ENTRADA
A17: 4 | B17: Entradas_calculos | C17: Variables clave consolidadas: edad, precio, tasa, costos por año de etapa improductiva | D17: CÁLCULO
A18: 5 | B18: Calculos_generales | C18: Análisis financiero consolidado en la misma hoja: TIR del proyecto (Q3), Relación Costo/Beneficio (Q4) y Punto de equilibrio (Q5) | D18: ANÁLISIS
A19: 6 | B19: Amortización | C19: Tabla de amortización de la inversión inicial | D19: CÁLCULO
A20: 7 | B20: calculo_etapa_vegetativa | C20: Costos capitalizados de la siembra hasta la edad actual del cultivo | D20: CÁLCULO
A21: 8 | B21: Calculo_etapa_productiva | C21: Flujos de caja proyectados año por año (rendimiento, ingreso, costo, flujo neto) | D21: CÁLCULO
A22: 9 | B22: escenario de negociación | C22: TABLERO PRINCIPAL — valor del cultivo, banda de negociación y argumentos | D22: RESULTADO
A23: 10 | B23: Resumen_Departamento | C23: Resumen agregado por departamento | D23: RESULTADO
A24: 11 | B24: PreciosRef. por Mercado / Tabla_Costos_Insumos / departamento / Base_datActividades_priorFIN / Caracteristicas / Caracteristicas_agronomicas / Rendimientos estandar_ / Tiempos de cosecha_ / mecanización_ pendiente / Jornalesdeppto / Limites_agroecologicos | C24: Bases de datos de referencia (precios, jornales, rendimientos, características) | D24: DATOS
A26: FLUJO DE TRABAJO — PASO A PASO
A27: Paso | B27: Acción | C27: Dónde | D27: Resultado
A28: 1 | B28: Diligenciar datos del cultivo: especie, edad actual, departamento, municipio, precio venta y área | C28: Formulario | D28: Parámetros base cargados
A29: 2 | B29: en este espacio es cuando el perito tenga una densidad diferente a la densidad usada lo cual trae como consecuencia que se deba hacer calculo de jornales a partir de los tiempos y movimientos encontrados en la Base_datActividades_priorFIN columna R | C29: PERITO | D29: Identificación del avalúo
A30: 3 | B30: Seleccionar método de tasa de descuento escribiendo el nombre exacto (DTF + Prima de Riesgo, CAPM, Finagro o WACC) en la celda C57 | C30: Entradas_Tasas → C57 | D30: Tasa activa definida
A31: 4 | B31: Revisar cálculos automáticos (no editar) | C31: Calculo_etapa_productiva, calculo_etapa_vegetativa, Calculos_generales, Amortización | D31: Flujos y costos calculados
A32: 5 | B32: Consultar el VALOR DEL CULTIVO RECOMENDADO en el bloque resumen | C32: escenario de negociación → C28 | D32: Precio sugerido $/ha
A33: 6 | B33: Comparar contra TECHO, PISO, REFERENCIA Finagro y oferta agresiva | C33: escenario de negociación → C26:E30 | D33: Banda de negociación
A34: 7 | B34: Argumentar con base en los textos técnicos del tablero | C34: escenario de negociación → C33:E34 | D34: Argumentos negociadores
A36: CONCEPTOS CLAVE
A37: Concepto | B37: Definición
A38: VPN remanente | B38: Valor presente neto de los flujos futuros desde la edad actual hasta el fin de la vida útil del cultivo
A39: Costo de reposición | B39: Lo que costaría hoy reconstruir el cultivo desde cero hasta la edad actual (capitalizado a la tasa de descuento)
A40: TECHO | B40: Precio máximo del vendedor (escenario favorable: tasa Res. 620 base)
A41: PISO | B41: Precio mínimo del vendedor: lo que costó construir el cultivo + lucro cesante
A42: OFERTA RECOMENDADA | B42: Precio justo a tasa privada (18%) — lo que arroja el aplicativo como valor recomendado del cultivo
A43: OFERTA AGRESIVA | B43: Precio de apertura del comprador (tasa 20%) — punto de partida táctico
A44: TIR sembrador | B44: Rentabilidad del proyecto si lo lleva hasta el final de la vida útil
A45: TIR comprador | B45: Rentabilidad para alguien que compra el cultivo a una edad intermedia y lo cosecha hasta el final
A47: NOTAS LEGALES Y TÉCNICAS
A48: • Marco normativo: Resolución 620 de 2008 — método de avaluo de cultivos.
A49: • Las tasas se actualizan desde la hoja Entradas_Tasas — verifique que el método seleccionado corresponda al caso.
A50: • El precio de venta (COP/kg) se carga desde el Formulario — use precio de referencia del mercado. No utilice picos de valor
A51: • Para cultivos jóvenes (edad < productiva), domina el costo de reposición.
A52: • Para cultivos maduros, domina el VPN remanente.

Sheet Formulario
A1: SUBDIRECCIÓN AVALÚOS | K1: Versión 0.3
A2: AVALÚOS COMERCIALES CULTIVOS AGRICOLAS
A3: FORMULARIO RECOLECCIÓN DATOS CULTIVOS
A5: 1. DATOS GENERALES
A7: Departamento | B7: CAUCA | E7: Municipio | F7: AMALFI | I7: Vereda | M7: VERIFICACIÓN COBERTURA CULTIVO × DEPARTAMENTO
M8: Insumos esperados: | P8: =COUNTIFS(Base_datActividades_priorFIN!A17:A1215,A22,Base_datActividades_priorFIN!B17:B1215,B22,Base_datActividades_priorFIN!K17:K1215,"<>") -> 54
M9: Insumos con precio: | P9: =COUNTIFS(Base_datActividades_priorFIN!A17:A1215,A22,Base_datActividades_priorFIN!B17:B1215,B22,Base_datActividades_priorFIN!K17:K1215,"<>",Base_datActividades_priorFIN!N17:N1215,">0") -> 54
M10: % Cobertura: | P10: =IFERROR(P9/P8,0) -> 1
A11: 2. CARACTERISTICAS AGROLOGICAS | M11: Estado: | N11: =IF(P8=0,"⚠ Cultivo sin datos",IF(P10>=0.999,"✓ COBERTURA COMPLETA",IF(P10>=0.8,"⚠ Cobertura parcial",IF(P10>0,"✗ Cobertura insuficiente","✗ Sin cobertura en este depto")))) -> ✓ COBERTURA COMPLETA
M12: Detalle: | N12: =IF(P8=0,"Verifica cultivo+variedad en A22:B22",IF(P10>=0.999,"Todos los "&P8&" insumos tienen precio en "&B7,IF(P9>0,"Faltan "&(P8-P9)&" de "&P8&" insumos con precio en "&B7,"Ningún insumo tiene precio en "&B7))) -> Todos los 54 insumos tienen precio en CAUCA
A13: Coordenadas | F13: Clima
A14: Latitud | B14: =VLOOKUP(F7,departamento!$B$2:$E$1123,4,0) -> 6,909655 | C14: Longitud | D14: =VLOOKUP(F7,departamento!$B$2:$E$1123,3,0) -> -75,077501 | F14: Tipo | G14: Calido | H14: Rango Temperatura (°C) | I14: =VLOOKUP(G14,Tabla18[],3,0) -> T°>24 | J14: Rango Altitud (msnm) | K14: =VLOOKUP(G14,Tabla18[],2,0) -> 0-1000
A16: APTITUD (consulta upra sipra) | F16: Otras
F17: Pendiente (%) | G17: 25 | H17: Clase Agrologica | I17: I | J17: Altitud (msnm)
A19: 3. DATOS GENERALES DEL CULTIVO
A21: CULTIVO | B21: VARIEDAD | C21: TIPO CULTIVO | D21: SISTEMA PRODUCTIVO | E21: EDAD (AÑOS) | F21: CONDICION FITOSANITARIA | G21: DISTANCIA PLANTA (m) | H21: DISTANCIA SURCO (m) | I21: DENSIDAD DE SIEMBRA (plantas/ha) | J21: AREA DE CULTIVO (ha) | K21: RENDIMIENTO PRODUCTO EN FRESCO (kg/ha)
A22: Plátano | B22: Domínico hartón | C22: Permanente | D22: Convencional | E22: 6 | F22: BUENO | G22: {=IFERROR(_xlfn.LET(_xlpm.dato, _xlfn.XLOOKUP(1,(PERITO!A2:A20=A22)*(PERITO!B2:B20=B22),PERITO!C2:C20),IF(_xlpm.dato<>"",_xlpm.dato,_xlfn.XLOOKUP(1,(Caracteristicas_agronomicas!A2:A20=A22)*(Caracteristicas_agronomicas!B2:B20=B22),Caracteristicas_agronomicas!H2:H20))),_xlfn.XLOOKUP(1,(Caracteristicas_agronomicas!A2:A20=A22)*(Caracteristicas_agronomicas!B2:B20=B22),Caracteristicas_agronomicas!H2:H20))} -> 3 | H22: {=IFERROR(_xlfn.LET(_xlpm.dato, _xlfn.XLOOKUP(1,(PERITO!A2:A20=A22)*(PERITO!B2:B20=B22),PERITO!D2:D20),IF(_xlpm.dato<>"", _xlpm.dato,_xlfn.XLOOKUP(1,(Caracteristicas_agronomicas!A2:A20=A22)*(Caracteristicas_agronomicas!B2:B20=B22),Caracteristicas_agronomicas!I2:I20))),_xlfn.XLOOKUP(1,(Caracteristicas_agronomicas!A2:A20=A22)*(Caracteristicas_agronomicas!B2:B20=B22),Caracteristicas_agronomicas!I2:I20))} -> 2.5 | I22: {=IFERROR(IF(INDEX(PERITO!E:E,MATCH(1,(PERITO!A:A=A22)*(PERITO!B:B=B22),0))<>"",INDEX(PERITO!E:E,MATCH(1,(PERITO!A:A=A22)*(PERITO!B:B=B22),0)),ROUND(IF(H23="tres bolillo",10000/(G22*H22*0.866),IF(H23="cuadro",10000/(G22*H22),"")),0)),ROUND(IF(H23="tres bolillo",10000/(G22*H22*0.866),IF(H23="cuadro",10000/(G22*H22),"")),0))} -> 1540 | J22: 1
A23: Condición hídrica del predio | B23: Con disponibilidad de agua permanente | C23: Regimen de lluvias | D23: Bimodal | E23: Precipitacion anual (mm/año) | F23: 1200 | G23: MARCO DE PLANTACIÓN | H23: tres bolillo | I23: COSTO DE ARRIENDO Ha/AÑO | J23: 500000 | K23: Costo del jornal
A24: Porcentaje Fitosanitario | B24: {=IFERROR(_xlfn.SWITCH(UPPER(TRIM(F22)),"BUENO",0.95,"BUENA",0.95,"ACEPTABLE",0.7,"REGULAR",0.475,"MALO",0.2,"MALA",0.2,""),"")} -> 0.95 | C24: Valor del suelo/ ha | D24: 30000000
A26: 4. COSTOS DE PRODUCCIÓN ($/ha)
A28: Cultivo variedad | B28: =CONCATENATE(A22," ",B22) -> Plátano Domínico hartón | E28: Año | F28: Establecimiento | H28: Ciclo de vida (años) | I28: =_xlfn.XLOOKUP(B28,Caracteristicas_agronomicas!$C$2:$C$17,Caracteristicas_agronomicas!$E$2:$E$17,0) -> 5 | J28: Precio comercializacón (Kg) | K28: 4000
H29: Vida remanente | I29: =I28-E22 -> -1
A31: RUBRO | C31: SUBRUBRO | E31: ACTIVIDAD | G31: SERVICIO O INSUMO | L31: VALOR TOTAL
A32: Código | B32: Nombre | C32: Código | D32: Nombre | E32: Código | F32: Nombre | G32: Tipo | H32: Nombre | I32: Presentación | J32: Cant | K32: Precio Unitario
A33: {=_xlfn._xlws.FILTER(Base_datActividades_priorFIN!D17:O1145, (Base_datActividades_priorFIN!P17:P1145=Formulario!B28) * (Base_datActividades_priorFIN!C17:C1145=Formulario!F28), "no corresponde")} -> 1. | B33: Labores | C33: 1.3. | D33: Preparacion de Tierras | E33: 1.3.10. | F33: Trazado y Hoyado | G33: Varios | H33: Mano de Obra | I33: Jornal | J33: 26 | K33: 46666.667 | L33: 1213333.3
A34: 1. | B34: Labores | C34: 1.3. | D34: Preparacion de Tierras | E34: 1.3.12. | F34: Otras | G34: Varios | H34: Mano de Obra | I34: Jornal | J34: 3 | K34: 46666.667 | L34: 140000
A35: 1. | B35: Labores | C35: 1.4. | D35: Siembra y Sostenimiento | E35: 1.4.6. | F35: Plateo | G35: Varios | H35: Mano de Obra | I35: Jornal | J35: 17 | K35: 46666.667 | L35: 793333.33
A36: 1. | B36: Labores | C36: 1.4. | D36: Siembra y Sostenimiento | E36: 1.4.7. | F36: Resiembra | G36: Varios | H36: Mano de Obra | I36: Jornal | J36: 21 | K36: 46666.667 | L36: 980000
A37: 1. | B37: Labores | C37: 1.4. | D37: Siembra y Sostenimiento | E37: 1.4.8. | F37: Siembra Abonamiento y Tapada | G37: Varios | H37: Mano de Obra | I37: Jornal | J37: 21 | K37: 46666.667 | L37: 980000
A38: 1. | B38: Labores | C38: 1.5. | D38: Labores Culturales | E38: 1.5.6. | F38: Deshije y Destronque | G38: Varios | H38: Mano de Obra | I38: Jornal | J38: 17 | K38: 46666.667 | L38: 793333.33
A39: 1. | B39: Labores | C39: 1.6. | D39: Control Sanitario | E39: 1.6.1. | F39: Aplicación de Fungicidas | G39: Varios | H39: Mano de Obra | I39: Jornal | J39: 19 | K39: 46666.667 | L39: 886666.67
A40: 1. | B40: Labores | C40: 1.6. | D40: Control Sanitario | E40: 1.6.2. | F40: Aplicación de Insecticidas | G40: Varios | H40: Mano de Obra | I40: Jornal | J40: 19 | K40: 46666.667 | L40: 886666.67
A41: 1. | B41: Labores | C41: 1.7. | D41: Control de Malezas | E41: 1.7.1. | F41: Aplicación de Herbicidas Preemergentes | G41: Varios | H41: Mano de Obra | I41: Jornal | J41: 10 | K41: 46666.667 | L41: 466666.67
A42: 1. | B42: Labores | C42: 1.8. | D42: Fertilizacion | E42: 1.8.2. | F42: Fertilizante Simple | G42: Varios | H42: Mano de Obra | I42: Jornal | J42: 13 | K42: 46666.667 | L42: 606666.67
A43: 2. | B43: Insumos | C43: 2.1. | D43: Material Vegetal | E43: 2.1.1. | F43: Semillas o Plantulas | G43: Material_de_propagación | H43: Plátano domínico hartón colino | I43: unidad | J43: 1540 | K43: 3000 | L43: 4620000
A44: 2. | B44: Insumos | C44: 2.2. | D44: Fertilizacion | E44: 2.2.1. | F44: Simples | G44: Fertilizantes_enmiendas_y_acondicionadores_de_suelo | H44: Cloruro de Potasio 0-0-60 | I44: 50 kilogramos | J44: 11 | K44: 110000 | L44: 1210000
A45: 2. | B45: Insumos | C45: 2.2. | D45: Fertilizacion | E45: 2.2.2. | F45: compuestos | G45: Fertilizantes_enmiendas_y_acondicionadores_de_suelo | H45: Fosfato Diamónico (DAP) 18-46-0 | I45: 50 kilogramos | J45: 2 | K45: 198055.68 | L45: 396111.37
... A58: 3. | B58: Otros Costos | C58: 3.3. | D58: Arrendamiento | E58: 3.3.1. | F58: Canon | G58: Arrendamiento_de_tierras | H58: Hectárea anual. | I58: unidad | J58: 1 | K58: 500000 | L58: 500000
K65: TOTAL | L65: =SUM(L33:L64) -> 21007737
A71: Cultivo variedad | B71: =$B$28 -> Plátano Domínico hartón | E71: Año | F71: Improductivo
A74: RUBRO | C74: SUBRUBRO | E74: ACTIVIDAD | G74: SERVICIO O INSUMO | L74: VALOR TOTAL
A75: Código | B75: Nombre | C75: Código | D75: Nombre | E75: Código | F75: Nombre | G75: Tipo | H75: Nombre | I75: Presentación | J75: Cant | K75: Precio Unitario
A76: {=_xlfn._xlws.FILTER(Base_datActividades_priorFIN!D17:O1145, (Base_datActividades_priorFIN!P17:P1145=B71) * (Base_datActividades_priorFIN!C17:C1145=F71), "no corresponde")} -> no corresponde
K104: TOTAL | L104: =SUM(L76:L100) -> 0 | U104: =42/2 -> 21 | V104: =365/U104 -> 17.380952
A108: Cultivo variedad | B108: =$B$28 -> Plátano Domínico hartón | E108: Año | F108: Mantenimiento
A111: RUBRO | C111: SUBRUBRO | E111: ACTIVIDAD | G111: SERVICIO O INSUMO | L111: VALOR TOTAL
A112: Código | B112: Nombre | C112: Código | D112: Nombre | E112: Código | F112: Nombre | G112: Tipo | H112: Nombre | I112: Presentación | J112: Cant | K112: Precio Unitario
A113: {=_xlfn._xlws.FILTER(Base_datActividades_priorFIN!D17:O1145, (Base_datActividades_priorFIN!P17:P1145=B108) * (Base_datActividades_priorFIN!C17:C1145=F108), "no corresponde")} -> 1. | B113: Labores | C113: 1.4. | D113: Siembra y Sostenimiento | E113: 1.4.2. | F113: Apuntalada o Amarre Aéreo | G113: Varios | H113: Mano de Obra | I113: Jornal | J113: 6 | K113: 46666.667 | L113: 280000
A114: 1. | B114: Labores | C114: 1.4. | D114: Siembra y Sostenimiento | E114: 1.4.6. | F114: Plateo | G114: Varios | H114: Mano de Obra | I114: Jornal | J114: 17 | K114: 46666.667 | L114: 793333.33
A115: 1. | B115: Labores | C115: 1.5. | D115: Labores Culturales | E115: 1.5.6. | F115: Deshije y Destronque | G115: Varios | H115: Mano de Obra | I115: Jornal | J115: 17 | K115: 46666.667 | L115: 793333.33
A116: 1. | B116: Labores | C116: 1.6. | D116: Control Sanitario | E116: 1.6.1. | F116: Aplicación de Fungicidas | G116: Varios | H116: Mano de Obra | I116: Jornal | J116: 19 | K116: 46666.667 | L116: 886666.67
A117: 1. | B117: Labores | C117: 1.6. | D117: Control Sanitario | E117: 1.6.2. | F117: Aplicación de Insecticidas | G117: Varios | H117: Mano de Obra | I117: Jornal | J117: 19 | K117: 46666.667 | L117: 886666.67
A118: 1. | B118: Labores | C118: 1.7. | D118: Control de Malezas | E118: 1.7.3. | F118: Desyerbas - Postemergente | G118: Varios | H118: Mano de Obra | I118: Jornal | J118: 10 | K118: 46666.667 | L118: 466666.67
A119: 1. | B119: Labores | C119: 1.8. | D119: Fertilizacion | E119: 1.8.2. | F119: Fertilizante Simple | G119: Varios | H119: Mano de Obra | I119: Jornal | J119: 13 | K119: 46666.667 | L119: 606666.67
A120: 1. | B120: Labores | C120: 1.9. | D120: Cosecha y Beneficio | E120: 1.9.6. | F120: Pesada Limpieza y Secamiento | G120: Varios | H120: Mano de Obra | I120: Jornal | J120: 6 | K120: 46666.667 | L120: 280000
A121: 1. | B121: Labores | C121: 1.9. | D121: Cosecha y Beneficio | E121: 1.9.7. | F121: Recolección | G121: Varios | H121: Mano de Obra | I121: Jornal | J121: 19 | K121: 46666.667 | L121: 886666.67
A122: 2. | B122: Insumos | C122: 2.2. | D122: Fertilizacion | E122: 2.2.1. | F122: Simples | G122: Fertilizantes_enmiendas_y_acondicionadores_de_suelo | H122: Urea 46% | I122: 50 kilogramos | J122: 21 | K122: 125849.24 | L122: 2642834.1
A123: 2. | B123: Insumos | C123: 2.2. | D123: Fertilizacion | E123: 2.2.2. | F123: compuestos | G123: Fertilizantes_enmiendas_y_acondicionadores_de_suelo | H123: Fosfato Diamónico (DAP) 18-46-0 | I123: 50 kilogramos | J123: 4 | K123: 198055.68 | L123: 792222.73
A124: 2. | B124: Insumos | C124: 2.2. | D124: Fertilizacion | E124: 2.2.4. | F124: Correctivos | G124: Fertilizantes_enmiendas_y_acondicionadores_de_suelo | H124: Cal dolomita | I124: 50 kilogramos | J124: 14 | K124: 17212.5 | L124: 240975
A125: 2. | B125: Insumos | C125: 2.2. | D125: Fertilizacion | E125: 2.2.6. | F125: Foliares | G125: Fertilizantes_enmiendas_y_acondicionadores_de_suelo | H125: Klip - K Calcio-Boro | I125: 1 litro | J125: 18 | K125: 26208.33 | L125: 471749.94
... A136: 3. | B136: Otros Costos | C136: 3.3. | D136: Arrendamiento | E136: 3.3.1. | F136: Canon | G136: Arrendamiento_de_tierras | H136: Hectárea anual. | I136: unidad | J136: 1 | K136: 500000 | L136: 500000
K146: TOTAL | L146: =SUM(L113:L142) -> 16737024
A149: Cultivo variedad | B149: =$B$28 -> Plátano Domínico hartón | E149: Año | F149: Salvamento
A152: RUBRO | C152: SUBRUBRO | E152: ACTIVIDAD | G152: SERVICIO O INSUMO | L152: VALOR TOTAL
A153: Código | B153: Nombre | C153: Código | D153: Nombre | E153: Código | F153: Nombre | G153: Tipo | H153: Nombre | I153: Presentación | J153: Cant | K153: Precio Unitario
A154: {=_xlfn._xlws.FILTER(Base_datActividades_priorFIN!D58:O1215, (Base_datActividades_priorFIN!P58:P1215=B149) * (Base_datActividades_priorFIN!C58:C1215=F149), "no corresponde")} -> 1. | B154: Labores | C154: 1.3. | D154: Preparacion de Tierras | E154: 1.3.6. | F154: Limpia Manual | G154: Varios | H154: Mano de Obra | I154: Jornal | J154: 13 | K154: 46666.667 | L154: 606666.67
A155: 1. | B155: Labores | C155: 1.3. | D155: Preparacion de Tierras | E155: 1.3.11. | F155: Tumba - Socola - Repique | G155: Varios | H155: Mano de Obra | I155: Jornal | J155: 7 | K155: 46666.667 | L155: 326666.67
A156: 1. | B156: Labores | C156: 1.3. | D156: Preparacion de Tierras | E156: 1.3.12. | F156: Otras | G156: Varios | H156: Mano de Obra | I156: Jornal | J156: 7 | K156: 46666.667 | L156: 326666.67
A157: 3. | B157: Otros Costos | C157: 3.1. | D157: Administracion | E157: 3.1.1. | F157: Administración | G157: Otros costos directos | H157: Administración del cultivo | I157: unidad | J157: 1 | K157: 100800 | L157: 100800
K163: Total | L163: =SUM(L154:L162) -> 1360800

Sheet PERITO
A1: Culitvo | B1: Variedad | C1: DISTANCIA_SURCOS | D1: DISTANCIA_PLANTAS | E1: DENSIDAD_SIEMBRA
A2: Aguacate | B2: Hass
A3: Cacao | B3: Criollo
A4: Café | B4: Castillo
A5: Caña Azucar | B5: Criolla
A6: Caña Azucar | B6: POJ 2878
A7: Caña Azucar | B7: CC 93-7711 Pierna Bella
A8: Limón | B8: Tahití
A9: Limón | B9: Común
A10: Limón | B10: Mandarino
A11: Mandarina | B11: Común
A12: Mango | B12: Tommy
A13: Naranja | B13: Valencia
... A17: Plátano | B17: Domínico hartón

Sheet Entradas_Tasas
B1: CONSTRUCCIÓN DE TASA DE DESCUENTO — Resolución 620 de 2008
B2: Azul = celda editable | D2: Negro = calculado automáticamente | F2: Verde = valor de otra hoja
B4: DATOS MACROECONÓMICOS (actualizar cuando cambien las fuentes)
B5: Variable | C5: Valor E.A. | D5: Fuente | E5: Fecha consulta
B6: Tasa política monetaria BanRep | C6: 0.1125 | D6: Banco de la República | E6: 31-mar-2026
B7: DTF 90 días | C7: 0.0982 | D7: Banco de la República | E7: 30-mar al 5-abr-2026
B8: IBR (referencia) | C8: 0.105 | D8: Banco de la República | E8: Abril 2026
B9: TES 10 años (tasa libre de riesgo) | C9: 0.132 | D9: Min. Hacienda / BVC | E9: Inicio 2026
B10: IPC cierre 2025 (base legal 2026) | C10: 0.051 | D10: DANE | E10: 8-ene-2026
B11: IPC febrero 2026 (dato oficial) | C11: 0.0529 | D11: DANE | E11: Feb-2026
B12: IPC marzo 2026 (proyectado) | C12: 0.0545 | D12: BanRep / Davivienda | E12: Abr-2026
B13: Tasa de usura | C13: 0.28 | D13: Superfinanciera | E13: Abr-2026
B14: IPC a usar para deflactación (el perito elige) | C14: 0.0529 | D14: Ref: IPC cierre 2025=5.10% | IPC feb-2026=5.29% | Proyectado mar-2026=5.45%
B16: MÉTODO 1 — DTF + Prima de Riesgo Agropecuario
B17: Variable | C17: Valor | D17: Nota
B18: DTF 90 días E.A. | C18: =C7 -> 0.0982 | D18: Trae del panel Entradas actual — actualizar DTF en esa hoja
B19: Prima de riesgo agropecuario | C19: 0.1 | D19: Editable — rango sugerido: 8% a 12% según riesgo del cultivo
B20: Tasa nominal = DTF + Prima | C20: =C18+C19 -> 0.1982 | D20: Calculado automáticamente
B21: ✔ TASA REAL = (1+nom)/(1+IPC)−1 | C21: =(1+C20)/(1+C14)-1 -> 0.13799981 | D21: RESULTADO — usar en VNA si elige este método
B23: MÉTODO 2 — CAPM (Capital Asset Pricing Model)
B24: Variable | C24: Valor | D24: Nota
B25: Tasa libre de riesgo Rf (TES 10 años) | C25: 0.132 | D25: Fuente: Min. Hacienda / BVC — actualizar mensualmente
B26: Beta sectorial agrícola (β) | C26: 0.75 | D26: Editable — rango agro Colombia: 0.60–0.90
B27: Prima de mercado (Rm − Rf) | C27: 0.075 | D27: Editable — histórico Colombia: 6%–9%. Default: 7.5%
B28: Tasa CAPM nominal = Rf + β×(Rm−Rf) | C28: =C25+(C26*C27) -> 0.18825 | D28: Calculado automáticamente
B29: ✔ TASA REAL = (1+nom)/(1+IPC)−1 | C29: =(1+C28)/(1+C14)-1 -> 0.12854972 | D29: RESULTADO — usar en VNA si elige este método
B31: MÉTODO 3 — Tasa Finagro como Referencia
B32: Variable | C32: Valor | D32: Nota
B33: IBR E.A. | C33: 0.07 | D33: Promedio historico de los ultimos 10 años
B34: Tipo de productor | C34: pequeño | D34: Opciones: Pequeño / Mediano / Grande
B35: Puntos adicionales sobre IBR | C35: 0.072 | D35: Pequeño: +4.50% | Mediano: +7.20% | Grande: +7.75% (Banco Agrario mar-2026)
B36: Tasa Finagro nominal ≈ IBR + Puntos | C36: =C33+C35 -> 0.142 | D36: Aproximación E.A. — verificar en www.bancoagrario.gov.co
B37: ✔ TASA REAL = (1+nom)/(1+IPC)−1 | C37: =(1+C36)/(1+C14)-1 -> 0.084623421 | D37: RESULTADO — usar en VNA si elige este método
B39: MÉTODO 4 — WACC (Costo Promedio Ponderado de Capital)
B40: ¿El proyecto tiene deuda? | C40: si | D40: Escriba SI o NO — si es NO el WACC equivale al CAPM real del Bloque 3
B41: Variable | C41: Valor | D41: Nota
B42: % Financiado con deuda | C42: 0.7 | D42: Solo si C40=SI — ingresar entre 0 y 1 (ej: 0.40 = 40%)
B43: Tasa de la deuda E.A. (escribir libremente) | C43: 0.17 | D43: Escriba la tasa conseguida — Finagro, banco comercial u otra
B44: % Capital propio = 1 − % Deuda | C44: =1-C42 -> 0.3 | D44: Calculado automáticamente
B45: Costo capital propio (CAPM nominal) | C45: =C28 -> 0.18825 | D45: Toma el CAPM del Bloque 3
B46: WACC nominal = %D×Td + %Kp×CAPM | C46: =C42*C43+C44*C45 -> 0.175475 | D46: Sin escudo fiscal — tasa bruta de deuda
B47: ✔ TASA REAL = (1+WACC)/(1+IPC)−1 | C47: =(1+C46)/(1+C14)-1 -> 0.11641656 | D47: RESULTADO — si % Deuda=0% este valor es igual al CAPM real
B50: COMPARATIVO DE TASAS REALES Y SELECTOR
B51: Método | C51: Tasa Real Res.620 | D51: Interpretación | G51: ¿Usar?
B52: DTF + Prima de Riesgo | C52: =C21 -> 0.13799981 | D52: Conservador. | G52: ☐
B53: CAPM | C53: =C29 -> 0.12854972 | D53: Técnico. Requiere justificar el beta sectorial. | G53: ☐
B54: Finagro | C54: =C37 -> 0.084623421 | D54: Referencia mínima del mercado agropecuario con recursos de fomento. | G54: ☐
B55: WACC | C55: =C47 -> 0.11641656 | D55: Aplicable cuando el proyecto tiene deuda. Si no hay deuda = CAPM. | G55: ☐
B57: → MÉTODO ELEGIDO (escriba el nombre exacto de la tabla) | C57: Finagro | E57: → TASA ACTIVA | F57: =IF(C57="DTF + Prima de Riesgo",C52,IF(C57="CAPM",C53,IF(C57="Finagro",C54,IF(C57="WACC",C55,0)))) -> 0.084623421
B58: FUENTES OFICIALES
B59: Banco de la República: www.banrep.gov.co → Estadísticas → Tasas de interés (DTF, IBR, TES)
B60: DANE: www.dane.gov.co → IPC mensual — publicación el 5° día hábil de cada mes
B61: Banco Agrario / FINAGRO: www.bancoagrario.gov.co → Tasas de colocación semanales
B62: Superfinanciera: www.superfinanciera.gov.co → Tasa de usura mensual

Sheet Entradas_calculos
A1: =Formulario!B28 -> Plátano Domínico hartón | E1: Curva de Producción (kg por ha) | J1: Entradas
A2: Etapa | B2: Edad | C2: Costo/ha | E2: Edad | F2: Producción/ha (kg) | J2: Edad inicial | K2: =Formulario!$E$22 -> 6
A3: {=IFERROR(INDEX('Rendimientos estandar_'!$C$2:$C$268,MATCH(1,(SUBSTITUTE(TRIM('Rendimientos estandar_'!$B$2:$B$268)," "," ")=SUBSTITUTE(TRIM(SUBSTITUTE(Formulario!$B$28,"_"," "))," "," "))*('Rendimientos estandar_'!$A$2:$A$268=B3),0)),"")} -> Establecimiento | B3: 1 | C3: {=IF(A3="","",_xlfn.IFS(A3="Establecimiento",Formulario!$L$65,A3="Improductivo",Formulario!$L$104,A3="Mantenimiento",Formulario!$L$146)+IF(AND(A3="Mantenimiento",A4<>"Mantenimiento"),Formulario!$L$163,0))} -> 21007737 | E3: 1 | F3: {=IFERROR(INDEX('Rendimientos estandar_'!$H$2:$H$268,MATCH(1,(SUBSTITUTE(TRIM('Rendimientos estandar_'!$B$2:$B$268)," "," ")=SUBSTITUTE(TRIM(SUBSTITUTE($A$1,"_"," "))," "," "))*('Rendimientos estandar_'!$A$2:$A$268=E3),0)),"")} -> 10450 | G3: Rendimiento ajustado = base × factor fitosanitario (Formulario!B24) | J3: Precio venta (COP/kg) | K3: =Formulario!$K$28 -> 4000
A4: {=IFERROR(INDEX('Rendimientos estandar_'!$C$2:$C$268,MATCH(1,(SUBSTITUTE(TRIM('Rendimientos estandar_'!$B$2:$B$268)," "," ")=SUBSTITUTE(TRIM(SUBSTITUTE(Formulario!$B$28,"_"," "))," "," "))*('Rendimientos estandar_'!$A$2:$A$268=B4),0)),"")} -> Mantenimiento | B4: 2 | C4: {=IF(A4="","",_xlfn.IFS(A4="Establecimiento",Formulario!$L$65,A4="Improductivo",Formulario!$L$104,A4="Mantenimiento",Formulario!$L$146)+IF(AND(A4="Mantenimiento",A5<>"Mantenimiento"),Formulario!$L$163,0))} -> 16737024 | E4: 2 | F4: {=IFERROR(INDEX('Rendimientos estandar_'!$H$2:$H$268,MATCH(1,(SUBSTITUTE(TRIM('Rendimientos estandar_'!$B$2:$B$268)," "," ")=SUBSTITUTE(TRIM(SUBSTITUTE($A$1,"_"," "))," "," "))*('Rendimientos estandar_'!$A$2:$A$268=E4),0)),"")} -> 17100 | J4: Interés (tasa) | K4: =Entradas_Tasas!$F$57 -> 0.084623421
A5: {=IFERROR(INDEX('Rendimientos estandar_'!$C$2:$C$268,MATCH(1,(SUBSTITUTE(TRIM('Rendimientos estandar_'!$B$2:$B$268)," "," ")=SUBSTITUTE(TRIM(SUBSTITUTE(Formulario!$B$28,"_"," "))," "," "))*('Rendimientos estandar_'!$A$2:$A$268=B5),0)),"")} -> Mantenimiento | B5: 3 | C5: {=IF(A5="","",_xlfn.IFS(A5="Establecimiento",Formulario!$L$65,A5="Improductivo",Formulario!$L$104,A5="Mantenimiento",Formulario!$L$146)+IF(AND(A5="Mantenimiento",A6<>"Mantenimiento"),Formulario!$L$163,0))} -> 16737024 | E5: 3 | F5: {=IFERROR(INDEX('Rendimientos estandar_'!$H$2:$H$268,MATCH(1,(SUBSTITUTE(TRIM('Rendimientos estandar_'!$B$2:$B$268)," "," ")=SUBSTITUTE(TRIM(SUBSTITUTE($A$1,"_"," "))," "," "))*('Rendimientos estandar_'!$A$2:$A$268=E5),0)),"")} -> 16245
A6: {=IFERROR(INDEX('Rendimientos estandar_'!$C$2:$C$268,MATCH(1,(SUBSTITUTE(TRIM('Rendimientos estandar_'!$B$2:$B$268)," "," ")=SUBSTITUTE(TRIM(SUBSTITUTE(Formulario!$B$28,"_"," "))," "," "))*('Rendimientos estandar_'!$A$2:$A$268=B6),0)),"")} -> Mantenimiento | B6: 4 | C6: {=IF(A6="","",_xlfn.IFS(A6="Establecimiento",Formulario!$L$65,A6="Improductivo",Formulario!$L$104,A6="Mantenimiento",Formulario!$L$146)+IF(AND(A6="Mantenimiento",A7<>"Mantenimiento"),Formulario!$L$163,0))} -> 16737024 | E6: 4 | F6: {=IFERROR(INDEX('Rendimientos estandar_'!$H$2:$H$268,MATCH(1,(SUBSTITUTE(TRIM('Rendimientos estandar_'!$B$2:$B$268)," "," ")=SUBSTITUTE(TRIM(SUBSTITUTE($A$1,"_"," "))," "," "))*('Rendimientos estandar_'!$A$2:$A$268=E6),0)),"")} -> 15390
A7: {=IFERROR(INDEX('Rendimientos estandar_'!$C$2:$C$268,MATCH(1,(SUBSTITUTE(TRIM('Rendimientos estandar_'!$B$2:$B$268)," "," ")=SUBSTITUTE(TRIM(SUBSTITUTE(Formulario!$B$28,"_"," "))," "," "))*('Rendimientos estandar_'!$A$2:$A$268=B7),0)),"")} -> Mantenimiento | B7: 5 | C7: {=IF(A7="","",_xlfn.IFS(A7="Establecimiento",Formulario!$L$65,A7="Improductivo",Formulario!$L$104,A7="Mantenimiento",Formulario!$L$146)+IF(AND(A7="Mantenimiento",A8<>"Mantenimiento"),Formulario!$L$163,0))} -> 16737024 | E7: 5 | F7: {=IFERROR(INDEX('Rendimientos estandar_'!$H$2:$H$268,MATCH(1,(SUBSTITUTE(TRIM('Rendimientos estandar_'!$B$2:$B$268)," "," ")=SUBSTITUTE(TRIM(SUBSTITUTE($A$1,"_"," "))," "," "))*('Rendimientos estandar_'!$A$2:$A$268=E7),0)),"")} -> 14535
A8: {=IFERROR(INDEX('Rendimientos estandar_'!$C$2:$C$268,MATCH(1,(SUBSTITUTE(TRIM('Rendimientos estandar_'!$B$2:$B$268)," "," ")=SUBSTITUTE(TRIM(SUBSTITUTE(Formulario!$B$28,"_"," "))," "," "))*('Rendimientos estandar_'!$A$2:$A$268=B8),0)),"")} -> Mantenimiento | B8: 6 | C8: {=IF(A8="","",_xlfn.IFS(A8="Establecimiento",Formulario!$L$65,A8="Improductivo",Formulario!$L$104,A8="Mantenimiento",Formulario!$L$146)+IF(AND(A8="Mantenimiento",A9<>"Mantenimiento"),Formulario!$L$163,0))} -> 18097824 | E8: 6 | F8: {=IFERROR(INDEX('Rendimientos estandar_'!$H$2:$H$268,MATCH(1,(SUBSTITUTE(TRIM('Rendimientos estandar_'!$B$2:$B$268)," "," ")=SUBSTITUTE(TRIM(SUBSTITUTE($A$1,"_"," "))," "," "))*('Rendimientos estandar_'!$A$2:$A$268=E8),0)),"")} -> 13680
A9: {=IFERROR(INDEX('Rendimientos estandar_'!$C$2:$C$268,MATCH(1,(SUBSTITUTE(TRIM('Rendimientos estandar_'!$B$2:$B$268)," "," ")=SUBSTITUTE(TRIM(SUBSTITUTE(Formulario!$B$28,"_"," "))," "," "))*('Rendimientos estandar_'!$A$2:$A$268=B9),0)),"")} | B9: 7 | C9: {=IF(A9="","",_xlfn.IFS(A9="Establecimiento",Formulario!$L$65,A9="Improductivo",Formulario!$L$104,A9="Mantenimiento",Formulario!$L$146)+IF(AND(A9="Mantenimiento",A10<>"Mantenimiento"),Formulario!$L$163,0))} | E9: 7 | F9: {=IFERROR(INDEX('Rendimientos estandar_'!$H$2:$H$268,MATCH(1,(SUBSTITUTE(TRIM('Rendimientos estandar_'!$B$2:$B$268)," "," ")=SUBSTITUTE(TRIM(SUBSTITUTE($A$1,"_"," "))," "," "))*('Rendimientos estandar_'!$A$2:$A$268=E9),0)),"")}
A10: {=IFERROR(INDEX('Rendimientos estandar_'!$C$2:$C$268,MATCH(1,(SUBSTITUTE(TRIM('Rendimientos estandar_'!$B$2:$B$268)," "," ")=SUBSTITUTE(TRIM(SUBSTITUTE(Formulario!$B$28,"_"," "))," "," "))*('Rendimientos estandar_'!$A$2:$A$268=B10),0)),"")} | B10: 8 | C10: {=IF(A10="","",_xlfn.IFS(A10="Establecimiento",Formulario!$L$65,A10="Improductivo",Formulario!$L$104,A10="Mantenimiento",Formulario!$L$146)+IF(AND(A10="Mantenimiento",A11<>"Mantenimiento"),Formulario!$L$163,0))} | E10: 8 | F10: {=IFERROR(INDEX('Rendimientos estandar_'!$H$2:$H$268,MATCH(1,(SUBSTITUTE(TRIM('Rendimientos estandar_'!$B$2:$B$268)," "," ")=SUBSTITUTE(TRIM(SUBSTITUTE($A$1,"_"," "))," "," "))*('Rendimientos estandar_'!$A$2:$A$268=E10),0)),"")}
A11: {=IFERROR(INDEX('Rendimientos estandar_'!$C$2:$C$268,MATCH(1,(SUBSTITUTE(TRIM('Rendimientos estandar_'!$B$2:$B$268)," "," ")=SUBSTITUTE(TRIM(SUBSTITUTE(Formulario!$B$28,"_"," "))," "," "))*('Rendimientos estandar_'!$A$2:$A$268=B11),0)),"")} | B11: 9 | C11: {=IF(A11="","",_xlfn.IFS(A11="Establecimiento",Formulario!$L$65,A11="Improductivo",Formulario!$L$104,A11="Mantenimiento",Formulario!$L$146)+IF(AND(A11="Mantenimiento",A12<>"Mantenimiento"),Formulario!$L$163,0))} | E11: 9 | F11: {=IFERROR(INDEX('Rendimientos estandar_'!$H$2:$H$268,MATCH(1,(SUBSTITUTE(TRIM('Rendimientos estandar_'!$B$2:$B$268)," "," ")=SUBSTITUTE(TRIM(SUBSTITUTE($A$1,"_"," "))," "," "))*('Rendimientos estandar_'!$A$2:$A$268=E11),0)),"")}
A12: {=IFERROR(INDEX('Rendimientos estandar_'!$C$2:$C$268,MATCH(1,(SUBSTITUTE(TRIM('Rendimientos estandar_'!$B$2:$B$268)," "," ")=SUBSTITUTE(TRIM(SUBSTITUTE(Formulario!$B$28,"_"," "))," "," "))*('Rendimientos estandar_'!$A$2:$A$268=B12),0)),"")} | B12: 10 | C12: {=IF(A12="","",_xlfn.IFS(A12="Establecimiento",Formulario!$L$65,A12="Improductivo",Formulario!$L$104,A12="Mantenimiento",Formulario!$L$146)+IF(AND(A12="Mantenimiento",A13<>"Mantenimiento"),Formulario!$L$163,0))} | E12: 10 | F12: {=IFERROR(INDEX('Rendimientos estandar_'!$H$2:$H$268,MATCH(1,(SUBSTITUTE(TRIM('Rendimientos estandar_'!$B$2:$B$268)," "," ")=SUBSTITUTE(TRIM(SUBSTITUTE($A$1,"_"," "))," "," "))*('Rendimientos estandar_'!$A$2:$A$268=E12),0)),"")}
A13: {=IFERROR(INDEX('Rendimientos estandar_'!$C$2:$C$268,MATCH(1,(SUBSTITUTE(TRIM('Rendimientos estandar_'!$B$2:$B$268)," "," ")=SUBSTITUTE(TRIM(SUBSTITUTE(Formulario!$B$28,"_"," "))," "," "))*('Rendimientos estandar_'!$A$2:$A$268=B13),0)),"")} | B13: 11 | C13: {=IF(A13="","",_xlfn.IFS(A13="Establecimiento",Formulario!$L$65,A13="Improductivo",Formulario!$L$104,A13="Mantenimiento",Formulario!$L$146)+IF(AND(A13="Mantenimiento",A14<>"Mantenimiento"),Formulario!$L$163,0))} | E13: 11 | F13: {=IFERROR(INDEX('Rendimientos estandar_'!$H$2:$H$268,MATCH(1,(SUBSTITUTE(TRIM('Rendimientos estandar_'!$B$2:$B$268)," "," ")=SUBSTITUTE(TRIM(SUBSTITUTE($A$1,"_"," "))," "," "))*('Rendimientos estandar_'!$A$2:$A$268=E13),0)),"")}
A14: {=IFERROR(INDEX('Rendimientos estandar_'!$C$2:$C$268,MATCH(1,(SUBSTITUTE(TRIM('Rendimientos estandar_'!$B$2:$B$268)," "," ")=SUBSTITUTE(TRIM(SUBSTITUTE(Formulario!$B$28,"_"," "))," "," "))*('Rendimientos estandar_'!$A$2:$A$268=B14),0)),"")} | B14: 12 | C14: {=IF(A14="","",_xlfn.IFS(A14="Establecimiento",Formulario!$L$65,A14="Improductivo",Formulario!$L$104,A14="Mantenimiento",Formulario!$L$146)+IF(AND(A14="Mantenimiento",A15<>"Mantenimiento"),Formulario!$L$163,0))} | E14: 12 | F14: {=IFERROR(INDEX('Rendimientos estandar_'!$H$2:$H$268,MATCH(1,(SUBSTITUTE(TRIM('Rendimientos estandar_'!$B$2:$B$268)," "," ")=SUBSTITUTE(TRIM(SUBSTITUTE($A$1,"_"," "))," "," "))*('Rendimientos estandar_'!$A$2:$A$268=E14),0)),"")}
A15: {=IFERROR(INDEX('Rendimientos estandar_'!$C$2:$C$268,MATCH(1,(SUBSTITUTE(TRIM('Rendimientos estandar_'!$B$2:$B$268)," "," ")=SUBSTITUTE(TRIM(SUBSTITUTE(Formulario!$B$28,"_"," "))," "," "))*('Rendimientos estandar_'!$A$2:$A$268=B15),0)),"")} | B15: 13 | C15: {=IF(A15="","",_xlfn.IFS(A15="Establecimiento",Formulario!$L$65,A15="Improductivo",Formulario!$L$104,A15="Mantenimiento",Formulario!$L$146)+IF(AND(A15="Mantenimiento",A16<>"Mantenimiento"),Formulario!$L$163,0))} | E15: 13 | F15: {=IFERROR(INDEX('Rendimientos estandar_'!$H$2:$H$268,MATCH(1,(SUBSTITUTE(TRIM('Rendimientos estandar_'!$B$2:$B$268)," "," ")=SUBSTITUTE(TRIM(SUBSTITUTE($A$1,"_"," "))," "," "))*('Rendimientos estandar_'!$A$2:$A$268=E15),0)),"")}
A16: {=IFERROR(INDEX('Rendimientos estandar_'!$C$2:$C$268,MATCH(1,(SUBSTITUTE(TRIM('Rendimientos estandar_'!$B$2:$B$268)," "," ")=SUBSTITUTE(TRIM(SUBSTITUTE(Formulario!$B$28,"_"," "))," "," "))*('Rendimientos estandar_'!$A$2:$A$268=B16),0)),"")} | B16: 14 | C16: {=IF(A16="","",_xlfn.IFS(A16="Establecimiento",Formulario!$L$65,A16="Improductivo",Formulario!$L$104,A16="Mantenimiento",Formulario!$L$146)+IF(AND(A16="Mantenimiento",A17<>"Mantenimiento"),Formulario!$L$163,0))} | E16: 14 | F16: {=IFERROR(INDEX('Rendimientos estandar_'!$H$2:$H$268,MATCH(1,(SUBSTITUTE(TRIM('Rendimientos estandar_'!$B$2:$B$268)," "," ")=SUBSTITUTE(TRIM(SUBSTITUTE($A$1,"_"," "))," "," "))*('Rendimientos estandar_'!$A$2:$A$268=E16),0)),"")}
... A31: {=IFERROR(INDEX('Rendimientos estandar_'!$C$2:$C$268,MATCH(1,(SUBSTITUTE(TRIM('Rendimientos estandar_'!$B$2:$B$268)," "," ")=SUBSTITUTE(TRIM(SUBSTITUTE(Formulario!$B$28,"_"," "))," "," "))*('Rendimientos estandar_'!$A$2:$A$268=B31),0)),"")} | B31: 29 | C31: {=IF(A31="","",_xlfn.IFS(A31="Establecimiento",Formulario!$L$65,A31="Improductivo",Formulario!$L$104,A31="Mantenimiento",Formulario!$L$146)+IF(AND(A31="Mantenimiento",A32<>"Mantenimiento"),Formulario!$L$163,0))} | E31: 29 | F31: {=IFERROR(INDEX('Rendimientos estandar_'!$H$2:$H$268,MATCH(1,(SUBSTITUTE(TRIM('Rendimientos estandar_'!$B$2:$B$268)," "," ")=SUBSTITUTE(TRIM(SUBSTITUTE($A$1,"_"," "))," "," "))*('Rendimientos estandar_'!$A$2:$A$268=E31),0)),"")}
A32: {=IFERROR(INDEX('Rendimientos estandar_'!$C$2:$C$268,MATCH(1,(SUBSTITUTE(TRIM('Rendimientos estandar_'!$B$2:$B$268)," "," ")=SUBSTITUTE(TRIM(SUBSTITUTE(Formulario!$B$28,"_"," "))," "," "))*('Rendimientos estandar_'!$A$2:$A$268=B32),0)),"")} | B32: 30 | C32: {=IF(A32="",0,_xlfn.IFS(A32="Establecimiento",Formulario!$L$65,A32="Improductivo",Formulario!$L$104,A32="Mantenimiento",Formulario!$L$146)+IF(A32="Mantenimiento",Formulario!$L$163,0))} -> 0 | E32: 30 | F32: {=IFERROR(INDEX('Rendimientos estandar_'!$H$2:$H$268,MATCH(1,(SUBSTITUTE(TRIM('Rendimientos estandar_'!$B$2:$B$268)," "," ")=SUBSTITUTE(TRIM(SUBSTITUTE($A$1,"_"," "))," "," "))*('Rendimientos estandar_'!$A$2:$A$268=E32),0)),"")}

Sheet Calculos_generales
A1: Edad | B1: Prod/ha (kg) | C1: Precio | D1: Ingreso (Prod*Precio) | E1: Costo/ha | F1: Costo Financiero | G1: Flujo Neto | H1: n (años) | I1: Interés | J1: Factor Descuento | K1: VP del Flujo | L1: VPN Remanente | M1: VPN traído al momento 0
A2: 1 | B2: =IFERROR(VLOOKUP(A2,Entradas_calculos!$E$3:$F$32,2,FALSE),0) -> 10450 | C2: =Entradas_calculos!$K$3 -> 4000 | D2: =IFERROR(B2*C2,0) -> 41800000 | E2: =IFERROR(VLOOKUP(A2,Entradas_calculos!$B$3:$C$32,2,FALSE),0) -> 21007737 | F2: =+IF(AND(A2<=Amortización!$B$3,A2-Amortización!$B$4>0),IFERROR(VLOOKUP(A2,Amortización!$A$8:$B$32,2,FALSE),0),0) -> 0 | G2: =IFERROR(D2-E2-F2,0) -> 20792263 | H2: =A2 -> 1 | I2: =Entradas_calculos!$K$4 -> 0.084623421 | J2: =(1+I2)^A2 -> 1.0846234 | K2: =IF(J2="",0,G2/J2) -> 19170030 | L2: =+NPV(Entradas_calculos!$K$4,G2:G31) -> 1.8336e+08 | P2: Total VP | Q2: =SUM(K2:K31) -> 1.8336e+08
A3: 2 | B3: =IFERROR(VLOOKUP(A3,Entradas_calculos!$E$3:$F$32,2,FALSE),0) -> 17100 | C3: =Entradas_calculos!$K$3 -> 4000 | D3: =IFERROR(B3*C3,0) -> 68400000 | E3: =IFERROR(VLOOKUP(A3,Entradas_calculos!$B$3:$C$32,2,FALSE),0) -> 16737024 | F3: =+IF(AND(A3<=Amortización!$B$3,A3-Amortización!$B$4>0),IFERROR(VLOOKUP(A3,Amortización!$A$8:$B$32,2,FALSE),0),0) -> 0 | G3: =IFERROR(D3-E3-F3,0) -> 51662976 | H3: =A3 -> 2 | I3: =Entradas_calculos!$K$4 -> 0.084623421 | J3: =(1+I3)^A3 -> 1.176408 | K3: =IF(J3="",0,G3/J3) -> 43915868 | L3: =+NPV(Entradas_calculos!$K$4,G3:G31) -> 1.7808428e+08 | P3: TIR | Q3: =IRR(G2:G31,0.1) -> #NUM!
A4: 3 | B4: =IFERROR(VLOOKUP(A4,Entradas_calculos!$E$3:$F$32,2,FALSE),0) -> 16245 | C4: =Entradas_calculos!$K$3 -> 4000 | D4: =IFERROR(B4*C4,0) -> 64980000 | E4: =IFERROR(VLOOKUP(A4,Entradas_calculos!$B$3:$C$32,2,FALSE),0) -> 16737024 | F4: =+IF(AND(A4<=Amortización!$B$3,A4-Amortización!$B$4>0),IFERROR(VLOOKUP(A4,Amortización!$A$8:$B$32,2,FALSE),0),0) -> 0 | G4: =IFERROR(D4-E4-F4,0) -> 48242976 | H4: =A4 -> 3 | I4: =Entradas_calculos!$K$4 -> 0.084623421 | J4: =(1+I4)^A4 -> 1.2759596 | K4: =IF(J4="",0,G4/J4) -> 37809171 | L4: =+NPV(Entradas_calculos!$K$4,G4:G31) -> 1.4149141e+08 | M4: =IF(H4="","",L4/((1+Entradas_calculos!$K$4)^H4)) -> 1.1089019e+08 | P4: Relacion C/B | Q4: {=IFERROR(NPV(Entradas_calculos!$K$4,D2:D30)/NPV(Entradas_calculos!$K$4,E2:E30+F2:F30),"-")} -> -
A5: 4 | B5: =IFERROR(VLOOKUP(A5,Entradas_calculos!$E$3:$F$32,2,FALSE),0) -> 15390 | C5: =Entradas_calculos!$K$3 -> 4000 | D5: =IFERROR(B5*C5,0) -> 61560000 | E5: =IFERROR(VLOOKUP(A5,Entradas_calculos!$B$3:$C$32,2,FALSE),0) -> 16737024 | F5: =+IF(AND(A5<=Amortización!$B$3,A5-Amortización!$B$4>0),IFERROR(VLOOKUP(A5,Amortización!$A$8:$B$32,2,FALSE),0),0) -> 0 | G5: =IFERROR(D5-E5-F5,0) -> 44822976 | H5: =A5 -> 4 | I5: =Entradas_calculos!$K$4 -> 0.084623421 | J5: =(1+I5)^A5 -> 1.3839357 | K5: =IF(J5="",0,G5/J5) -> 32388048 | L5: =+NPV(Entradas_calculos!$K$4,G5:G31) -> 1.0522192e+08 | M5: =IF(H5="","",L5/((1+Entradas_calculos!$K$4)^H5)) -> 76030930 | P5: punto equilibrio | Q5: {=IFERROR(_xlfn.LET(_xlpm.idx,MATCH(TRUE,MMULT(--(ROW(G2:G30)>=TRANSPOSE(ROW(G2:G30))),G2:G30)>=0,0),_xlpm.prev,SUM(OFFSET(G2,0,0,_xlpm.idx-1,1)),_xlpm.flujoAct,INDEX(G2:G30,_xlpm.idx),(_xlpm.idx-1)+(-_xlpm.prev/_xlpm.flujoAct)),"No alcanza")} -> No alcanza
A6: 5 | B6: =IFERROR(VLOOKUP(A6,Entradas_calculos!$E$3:$F$32,2,FALSE),0) -> 14535 | C6: =Entradas_calculos!$K$3 -> 4000 | D6: =IFERROR(B6*C6,0) -> 58140000 | E6: =IFERROR(VLOOKUP(A6,Entradas_calculos!$B$3:$C$32,2,FALSE),0) -> 16737024 | F6: =+IF(AND(A6<=Amortización!$B$3,A6-Amortización!$B$4>0),IFERROR(VLOOKUP(A6,Amortización!$A$8:$B$32,2,FALSE),0),0) -> 0 | G6: =IFERROR(D6-E6-F6,0) -> 41402976 | H6: =A6 -> 5 | I6: =Entradas_calculos!$K$4 -> 0.084623421 | J6: =(1+I6)^A6 -> 1.5010491 | K6: =IF(J6="",0,G6/J6) -> 27582693 | L6: =+NPV(Entradas_calculos!$K$4,G6:G31) -> 69303181 | M6: =IF(H6="","",L6/((1+Entradas_calculos!$K$4)^H6)) -> 46169830
A7: 6 | B7: =IFERROR(VLOOKUP(A7,Entradas_calculos!$E$3:$F$32,2,FALSE),0) -> 13680 | C7: =Entradas_calculos!$K$3 -> 4000 | D7: =IFERROR(B7*C7,0) -> 54720000 | E7: =IFERROR(VLOOKUP(A7,Entradas_calculos!$B$3:$C$32,2,FALSE),0) -> 18097824 | F7: =+IF(AND(A7<=Amortización!$B$3,A7-Amortización!$B$4>0),IFERROR(VLOOKUP(A7,Amortización!$A$8:$B$32,2,FALSE),0),0) -> 0 | G7: =IFERROR(D7-E7-F7,0) -> 36622176 | H7: =A7 -> 6 | I7: =Entradas_calculos!$K$4 -> 0.084623421 | J7: =(1+I7)^A7 -> 1.628073 | K7: =IF(J7="",0,G7/J7) -> 22494186 | L7: =+NPV(Entradas_calculos!$K$4,G7:G31) -> 33764877 | M7: =IF(H7="","",L7/((1+Entradas_calculos!$K$4)^H7)) -> 20739167
A8: 7 | B8: =IFERROR(VLOOKUP(A8,Entradas_calculos!$E$3:$F$32,2,FALSE),0) | C8: =Entradas_calculos!$K$3 -> 4000 | D8: =IFERROR(B8*C8,0) -> 0 | E8: =IFERROR(VLOOKUP(A8,Entradas_calculos!$B$3:$C$32,2,FALSE),0) | F8: =+IF(AND(A8<=Amortización!$B$3,A8-Amortización!$B$4>0),IFERROR(VLOOKUP(A8,Amortización!$A$8:$B$32,2,FALSE),0),0) -> 0 | G8: =IFERROR(D8-E8-F8,0) -> 0 | H8: =A8 -> 7 | I8: =Entradas_calculos!$K$4 -> 0.084623421 | J8: =(1+I8)^A8 -> 1.7658461 | K8: =IF(J8="",0,G8/J8) -> 0 | L8: =+NPV(Entradas_calculos!$K$4,G8:G31) -> 0 | M8: =IF(H8="","",L8/((1+Entradas_calculos!$K$4)^H8)) -> 0
A9: 8 | B9: =IFERROR(VLOOKUP(A9,Entradas_calculos!$E$3:$F$32,2,FALSE),0) | C9: =Entradas_calculos!$K$3 -> 4000 | D9: =IFERROR(B9*C9,0) -> 0 | E9: =IFERROR(VLOOKUP(A9,Entradas_calculos!$B$3:$C$32,2,FALSE),0) | F9: =+IF(AND(A9<=Amortización!$B$3,A9-Amortización!$B$4>0),IFERROR(VLOOKUP(A9,Amortización!$A$8:$B$32,2,FALSE),0),0) -> 0 | G9: =IFERROR(D9-E9-F9,0) -> 0 | H9: =A9 -> 8 | I9: =Entradas_calculos!$K$4 -> 0.084623421 | J9: =(1+I9)^A9 -> 1.915278 | K9: =IF(J9="",0,G9/J9) -> 0 | L9: =+NPV(Entradas_calculos!$K$4,Calculos_generales!G9:G31) -> 0 | M9: =IF(H9="","",L9/((1+Entradas_calculos!$K$4)^H9)) -> 0
A10: 9 | B10: =IFERROR(VLOOKUP(A10,Entradas_calculos!$E$3:$F$32,2,FALSE),0) | C10: =Entradas_calculos!$K$3 -> 4000 | D10: =IFERROR(B10*C10,0) -> 0 | E10: =IFERROR(VLOOKUP(A10,Entradas_calculos!$B$3:$C$32,2,FALSE),0) | F10: =+IF(AND(A10<=Amortización!$B$3,A10-Amortización!$B$4>0),IFERROR(VLOOKUP(A10,Amortización!$A$8:$B$32,2,FALSE),0),0) -> 0 | G10: =IFERROR(D10-E10-F10,0) -> 0 | H10: =A10 -> 9 | I10: =Entradas_calculos!$K$4 -> 0.084623421 | J10: =(1+I10)^A10 -> 2.0773554 | K10: =IF(J10="",0,G10/J10) -> 0 | L10: =+NPV(Entradas_calculos!$K$4,Calculos_generales!G10:G32) -> 0 | M10: =IF(H10="","",L10/((1+Entradas_calculos!$K$4)^H10)) -> 0
A11: 10 | B11: =IFERROR(VLOOKUP(A11,Entradas_calculos!$E$3:$F$32,2,FALSE),0) | C11: =Entradas_calculos!$K$3 -> 4000 | D11: =IFERROR(B11*C11,0) -> 0 | E11: =IFERROR(VLOOKUP(A11,Entradas_calculos!$B$3:$C$32,2,FALSE),0) | F11: =+IF(AND(A11<=Amortización!$B$3,A11-Amortización!$B$4>0),IFERROR(VLOOKUP(A11,Amortización!$A$8:$B$32,2,FALSE),0),0) -> 0 | G11: =IFERROR(D11-E11-F11,0) -> 0 | H11: =A11 -> 10 | I11: =Entradas_calculos!$K$4 -> 0.084623421 | J11: =(1+I11)^A11 -> 2.2531483 | K11: =IF(J11="",0,G11/J11) -> 0 | L11: =+NPV(Entradas_calculos!$K$4,G11:G31) -> 0 | M11: =+L11/((1+Entradas_calculos!$K$4)^Calculos_generales!H11) -> 0
A12: 11 | B12: =IFERROR(VLOOKUP(A12,Entradas_calculos!$E$3:$F$32,2,FALSE),0) | C12: =Entradas_calculos!$K$3 -> 4000 | D12: =IFERROR(B12*C12,0) -> 0 | E12: =IFERROR(VLOOKUP(A12,Entradas_calculos!$B$3:$C$32,2,FALSE),0) | F12: =+IF(AND(A12<=Amortización!$B$3,A12-Amortización!$B$4>0),IFERROR(VLOOKUP(A12,Amortización!$A$8:$B$32,2,FALSE),0),0) -> 0 | G12: =IFERROR(D12-E12-F12,0) -> 0 | H12: =A12 -> 11 | I12: =Entradas_calculos!$K$4 -> 0.084623421 | J12: =(1+I12)^A12 -> 2.4438174 | K12: =IF(J12="",0,G12/J12) -> 0 | L12: =+NPV(Entradas_calculos!$K$4,Calculos_generales!G12:G34) -> 0 | M12: =+L12/((1+Entradas_calculos!$K$4)^Calculos_generales!H12) -> 0
A13: 12 | B13: =IFERROR(VLOOKUP(A13,Entradas_calculos!$E$3:$F$32,2,FALSE),0) | C13: =Entradas_calculos!$K$3 -> 4000 | D13: =IFERROR(B13*C13,0) -> 0 | E13: =IFERROR(VLOOKUP(A13,Entradas_calculos!$B$3:$C$32,2,FALSE),0) | F13: =+IF(AND(A13<=Amortización!$B$3,A13-Amortización!$B$4>0),IFERROR(VLOOKUP(A13,Amortización!$A$8:$B$32,2,FALSE),0),0) -> 0 | G13: =IFERROR(D13-E13-F13,0) -> 0 | H13: =A13 -> 12 | I13: =Entradas_calculos!$K$4 -> 0.084623421 | J13: =(1+I13)^A13 -> 2.6506216 | K13: =IF(J13="",0,G13/J13) -> 0 | L13: =+NPV(Entradas_calculos!$K$4,Calculos_generales!G13:G35) -> 0 | M13: =+L13/((1+Entradas_calculos!$K$4)^Calculos_generales!H13) -> 0
A14: 13 | B14: =IFERROR(VLOOKUP(A14,Entradas_calculos!$E$3:$F$32,2,FALSE),0) | C14: =Entradas_calculos!$K$3 -> 4000 | D14: =IFERROR(B14*C14,0) -> 0 | E14: =IFERROR(VLOOKUP(A14,Entradas_calculos!$B$3:$C$32,2,FALSE),0) | F14: =+IF(AND(A14<=Amortización!$B$3,A14-Amortización!$B$4>0),IFERROR(VLOOKUP(A14,Amortización!$A$8:$B$32,2,FALSE),0),0) -> 0 | G14: =IFERROR(D14-E14-F14,0) -> 0 | H14: =A14 -> 13 | I14: =Entradas_calculos!$K$4 -> 0.084623421 | J14: =(1+I14)^A14 -> 2.8749263 | K14: =IF(J14="",0,G14/J14) -> 0 | L14: =+NPV(Entradas_calculos!$K$4,Calculos_generales!G14:G36) -> 0 | M14: =+L14/((1+Entradas_calculos!$K$4)^Calculos_generales!H14) -> 0
A15: 14 | B15: =IFERROR(VLOOKUP(A15,Entradas_calculos!$E$3:$F$32,2,FALSE),0) | C15: =Entradas_calculos!$K$3 -> 4000 | D15: =IFERROR(B15*C15,0) -> 0 | E15: =IFERROR(VLOOKUP(A15,Entradas_calculos!$B$3:$C$32,2,FALSE),0) | F15: =+IF(AND(A15<=Amortización!$B$3,A15-Amortización!$B$4>0),IFERROR(VLOOKUP(A15,Amortización!$A$8:$B$32,2,FALSE),0),0) -> 0 | G15: =IFERROR(D15-E15-F15,0) -> 0 | H15: =A15 -> 14 | I15: =Entradas_calculos!$K$4 -> 0.084623421 | J15: =(1+I15)^A15 -> 3.1182124 | K15: =IF(J15="",0,G15/J15) -> 0 | L15: =+NPV(Entradas_calculos!$K$4,Calculos_generales!G15:G37) -> 0 | M15: =+L15/((1+Entradas_calculos!$K$4)^Calculos_generales!H15) -> 0
A16: 15 | B16: =IFERROR(VLOOKUP(A16,Entradas_calculos!$E$3:$F$32,2,FALSE),0) | C16: =Entradas_calculos!$K$3 -> 4000 | D16: =IFERROR(B16*C16,0) -> 0 | E16: =IFERROR(VLOOKUP(A16,Entradas_calculos!$B$3:$C$32,2,FALSE),0) | F16: =+IF(AND(A16<=Amortización!$B$3,A16-Amortización!$B$4>0),IFERROR(VLOOKUP(A16,Amortización!$A$8:$B$32,2,FALSE),0),0) -> 0 | G16: =IFERROR(D16-E16-F16,0) -> 0 | H16: =A16 -> 15 | I16: =Entradas_calculos!$K$4 -> 0.084623421 | J16: =(1+I16)^A16 -> 3.3820862 | K16: =IF(J16="",0,G16/J16) -> 0 | L16: =+NPV(Entradas_calculos!$K$4,Calculos_generales!G16:G38) -> 0 | M16: =+L16/((1+Entradas_calculos!$K$4)^Calculos_generales!H16) -> 0
A17: 16 | B17: =IFERROR(VLOOKUP(A17,Entradas_calculos!$E$3:$F$32,2,FALSE),0) | C17: =Entradas_calculos!$K$3 -> 4000 | D17: =IFERROR(B17*C17,0) -> 0 | E17: =IFERROR(VLOOKUP(A17,Entradas_calculos!$B$3:$C$32,2,FALSE),0) | F17: =+IF(AND(A17<=Amortización!$B$3,A17-Amortización!$B$4>0),IFERROR(VLOOKUP(A17,Amortización!$A$8:$B$32,2,FALSE),0),0) -> 0 | G17: =IFERROR(D17-E17-F17,0) -> 0 | H17: =A17 -> 16 | I17: =Entradas_calculos!$K$4 -> 0.084623421 | J17: =(1+I17)^A17 -> 3.6682899 | K17: =IF(J17="",0,G17/J17) -> 0 | L17: =+NPV(Entradas_calculos!$K$4,Calculos_generales!G17:G39) -> 0 | M17: =+L17/((1+Entradas_calculos!$K$4)^Calculos_generales!H17) -> 0
A18: 17 | B18: =IFERROR(VLOOKUP(A18,Entradas_calculos!$E$3:$F$32,2,FALSE),0) | C18: =Entradas_calculos!$K$3 -> 4000 | D18: =IFERROR(B18*C18,0) -> 0 | E18: =IFERROR(VLOOKUP(A18,Entradas_calculos!$B$3:$C$32,2,FALSE),0) | F18: =+IF(AND(A18<=Amortización!$B$3,A18-Amortización!$B$4>0),IFERROR(VLOOKUP(A18,Amortización!$A$8:$B$32,2,FALSE),0),0) -> 0 | G18: =IFERROR(D18-E18-F18,0) -> 0 | H18: =A18 -> 17 | I18: =Entradas_calculos!$K$4 -> 0.084623421 | J18: =(1+I18)^A18 -> 3.9787132 | K18: =IF(J18="",0,G18/J18) -> 0 | L18: =+NPV(Entradas_calculos!$K$4,Calculos_generales!G18:G40) -> 0 | M18: =+L18/((1+Entradas_calculos!$K$4)^Calculos_generales!H18) -> 0
A19: 18 | B19: =IFERROR(VLOOKUP(A19,Entradas_calculos!$E$3:$F$32,2,FALSE),0) | C19: =Entradas_calculos!$K$3 -> 4000 | D19: =IFERROR(B19*C19,0) -> 0 | E19: =IFERROR(VLOOKUP(A19,Entradas_calculos!$B$3:$C$32,2,FALSE),0) | F19: =+IF(AND(A19<=Amortización!$B$3,A19-Amortización!$B$4>0),IFERROR(VLOOKUP(A19,Amortización!$A$8:$B$32,2,FALSE),0),0) -> 0 | G19: =IFERROR(D19-E19-F19,0) -> 0 | H19: =A19 -> 18 | I19: =Entradas_calculos!$K$4 -> 0.084623421 | J19: =(1+I19)^A19 -> 4.3154055 | K19: =IF(J19="",0,G19/J19) -> 0 | L19: =+NPV(Entradas_calculos!$K$4,Calculos_generales!G19:G41) -> 0 | M19: =+L19/((1+Entradas_calculos!$K$4)^Calculos_generales!H19) -> 0
A20: 19 | B20: =IFERROR(VLOOKUP(A20,Entradas_calculos!$E$3:$F$32,2,FALSE),0) | C20: =Entradas_calculos!$K$3 -> 4000 | D20: =IFERROR(B20*C20,0) -> 0 | E20: =IFERROR(VLOOKUP(A20,Entradas_calculos!$B$3:$C$32,2,FALSE),0) | F20: =+IF(AND(A20<=Amortización!$B$3,A20-Amortización!$B$4>0),IFERROR(VLOOKUP(A20,Amortización!$A$8:$B$32,2,FALSE),0),0) -> 0 | G20: =IFERROR(D20-E20-F20,0) -> 0 | H20: =A20 -> 19 | I20: =Entradas_calculos!$K$4 -> 0.084623421 | J20: =(1+I20)^A20 -> 4.6805898 | K20: =IF(J20="",0,G20/J20) -> 0 | L20: =+NPV(Entradas_calculos!$K$4,Calculos_generales!G20:G42) -> 0 | M20: =+L20/((1+Entradas_calculos!$K$4)^Calculos_generales!H20) -> 0
A21: 20 | B21: =IFERROR(VLOOKUP(A21,Entradas_calculos!$E$3:$F$32,2,FALSE),0) | C21: =Entradas_calculos!$K$3 -> 4000 | D21: =IFERROR(B21*C21,0) -> 0 | E21: =IFERROR(VLOOKUP(A21,Entradas_calculos!$B$3:$C$32,2,FALSE),0) | F21: =+IF(AND(A21<=Amortización!$B$3,A21-Amortización!$B$4>0),IFERROR(VLOOKUP(A21,Amortización!$A$8:$B$32,2,FALSE),0),0) -> 0 | G21: =IFERROR(D21-E21-F21,0) -> 0 | H21: =A21 -> 20 | I21: =Entradas_calculos!$K$4 -> 0.084623421 | J21: =(1+I21)^A21 -> 5.0766774 | K21: =IF(J21="",0,G21/J21) -> 0 | L21: =+NPV(Entradas_calculos!$K$4,Calculos_generales!G21:G43) -> 0 | M21: =+L21/((1+Entradas_calculos!$K$4)^Calculos_generales!H21) -> 0
A22: 21 | B22: =IFERROR(VLOOKUP(A22,Entradas_calculos!$E$3:$F$32,2,FALSE),0) | C22: =Entradas_calculos!$K$3 -> 4000 | D22: =IFERROR(B22*C22,0) -> 0 | E22: =IFERROR(VLOOKUP(A22,Entradas_calculos!$B$3:$C$32,2,FALSE),0) | F22: =+IF(AND(A22<=Amortización!$B$3,A22-Amortización!$B$4>0),IFERROR(VLOOKUP(A22,Amortización!$A$8:$B$32,2,FALSE),0),0) -> 0 | G22: =IFERROR(D22-E22-F22,0) -> 0 | H22: =A22 -> 21 | I22: =Entradas_calculos!$K$4 -> 0.084623421 | J22: =(1+I22)^A22 -> 5.5062832 | K22: =IF(J22="",0,G22/J22) -> 0 | L22: =+NPV(Entradas_calculos!$K$4,Calculos_generales!G22:G44) -> 0 | M22: =+L22/((1+Entradas_calculos!$K$4)^Calculos_generales!H22) -> 0
A23: 22 | B23: =IFERROR(VLOOKUP(A23,Entradas_calculos!$E$3:$F$32,2,FALSE),0) | C23: =Entradas_calculos!$K$3 -> 4000 | D23: =IFERROR(B23*C23,0) -> 0 | E23: =IFERROR(VLOOKUP(A23,Entradas_calculos!$B$3:$C$32,2,FALSE),0) | F23: =+IF(AND(A23<=Amortización!$B$3,A23-Amortización!$B$4>0),IFERROR(VLOOKUP(A23,Amortización!$A$8:$B$32,2,FALSE),0),0) -> 0 | G23: =IFERROR(D23-E23-F23,0) -> 0 | H23: =A23 -> 22 | I23: =Entradas_calculos!$K$4 -> 0.084623421 | J23: =(1+I23)^A23 -> 5.9722437 | K23: =IF(J23="",0,G23/J23) -> 0 | L23: =+NPV(Entradas_calculos!$K$4,Calculos_generales!G23:G45) -> 0 | M23: =+L23/((1+Entradas_calculos!$K$4)^Calculos_generales!H23) -> 0
... A26: 25 | B26: =IFERROR(VLOOKUP(A26,Entradas_calculos!$E$3:$F$32,2,FALSE),0) | C26: =Entradas_calculos!$K$3 -> 4000 | D26: =IFERROR(B26*C26,0) -> 0 | E26: =IFERROR(VLOOKUP(A26,Entradas_calculos!$B$3:$C$32,2,FALSE),0) | F26: =+IF(AND(A26<=Amortización!$B$3,A26-Amortización!$B$4>0),IFERROR(VLOOKUP(A26,Amortización!$A$8:$B$32,2,FALSE),0),0) -> 0 | G26: =IFERROR(D26-E26-F26,0) -> 0 | H26: =A26 -> 25 | I26: =Entradas_calculos!$K$4 -> 0.084623421 | J26: =(1+I26)^A26 -> 7.6203419 | K26: =IF(J26="",0,G26/J26) -> 0 | L26: =+NPV(Entradas_calculos!$K$4,Calculos_generales!G26:G48) -> 0 | M26: =+L26/((1+Entradas_calculos!$K$4)^Calculos_generales!H26) -> 0
A27: 26 | B27: =IFERROR(VLOOKUP(A27,Entradas_calculos!$E$3:$F$32,2,FALSE),0) | C27: =Entradas_calculos!$K$3 -> 4000 | D27: =IFERROR(B27*C27,0) -> 0 | E27: =IFERROR(VLOOKUP(A27,Entradas_calculos!$B$3:$C$32,2,FALSE),0) | F27: =+IF(AND(A27<=Amortización!$B$3,A27-Amortización!$B$4>0),IFERROR(VLOOKUP(A27,Amortización!$A$8:$B$32,2,FALSE),0),0) -> 0 | G27: =IFERROR(D27-E27-F27,0) -> 0 | H27: =A27 -> 26 | I27: =Entradas_calculos!$K$4 -> 0.084623421 | J27: =(1+I27)^A27 -> 8.2652013 | K27: =IF(J27="",0,G27/J27) -> 0 | L27: =+NPV(Entradas_calculos!$K$4,Calculos_generales!G27:G49) -> 0
A28: 27 | B28: =IFERROR(VLOOKUP(A28,Entradas_calculos!$E$3:$F$32,2,FALSE),0) | C28: =Entradas_calculos!$K$3 -> 4000 | D28: =IFERROR(B28*C28,0) -> 0 | E28: =IFERROR(VLOOKUP(A28,Entradas_calculos!$B$3:$C$32,2,FALSE),0) | F28: =+IF(AND(A28<=Amortización!$B$3,A28-Amortización!$B$4>0),IFERROR(VLOOKUP(A28,Amortización!$A$8:$B$32,2,FALSE),0),0) -> 0 | G28: =IFERROR(D28-E28-F28,0) -> 0 | H28: =A28 -> 27 | I28: =Entradas_calculos!$K$4 -> 0.084623421 | J28: =(1+I28)^A28 -> 8.9646309 | K28: =IF(J28="",0,G28/J28) -> 0 | L28: =+NPV(Entradas_calculos!$K$4,Calculos_generales!G28:G50) -> 0
A29: 28 | B29: =IFERROR(VLOOKUP(A29,Entradas_calculos!$E$3:$F$32,2,FALSE),0) | C29: =Entradas_calculos!$K$3 -> 4000 | D29: =IFERROR(B29*C29,0) -> 0 | E29: =IFERROR(VLOOKUP(A29,Entradas_calculos!$B$3:$C$32,2,FALSE),0) | F29: =+IF(AND(A29<=Amortización!$B$3,A29-Amortización!$B$4>0),IFERROR(VLOOKUP(A29,Amortización!$A$8:$B$32,2,FALSE),0),0) -> 0 | G29: =IFERROR(D29-E29-F29,0) -> 0 | H29: =A29 -> 28 | I29: =Entradas_calculos!$K$4 -> 0.084623421 | J29: =(1+I29)^A29 -> 9.7232486 | K29: =IF(J29="",0,G29/J29) -> 0 | L29: =+NPV(Entradas_calculos!$K$4,Calculos_generales!G29:G51) -> 0
A30: 29 | B30: =IFERROR(VLOOKUP(A30,Entradas_calculos!$E$3:$F$32,2,FALSE),0) | C30: =Entradas_calculos!$K$3 -> 4000 | D30: =IFERROR(B30*C30,0) -> 0 | E30: =IFERROR(VLOOKUP(A30,Entradas_calculos!$B$3:$C$32,2,FALSE),0) | F30: =+IF(AND(A30<=Amortización!$B$3,A30-Amortización!$B$4>0),IFERROR(VLOOKUP(A30,Amortización!$A$8:$B$32,2,FALSE),0),0) -> 0 | G30: =IFERROR(D30-E30-F30,0) -> 0 | H30: =A30 -> 29 | I30: =Entradas_calculos!$K$4 -> 0.084623421 | J30: =(1+I30)^A30 -> 10.546063 | K30: =IF(J30="",0,G30/J30) -> 0 | L30: =+NPV(Entradas_calculos!$K$4,Calculos_generales!G30:G52) -> 0
A31: 30 | B31: =IFERROR(VLOOKUP(A31,Entradas_calculos!$E$3:$F$32,2,FALSE),0) | C31: =Entradas_calculos!$K$3 -> 4000 | D31: =IFERROR(B31*C31,0) -> 0 | E31: =IFERROR(VLOOKUP(A31,Entradas_calculos!$B$3:$C$32,2,FALSE),0) -> 0 | F31: =+IF(AND(A31<=Amortización!$B$3,A31-Amortización!$B$4>0),IFERROR(VLOOKUP(A31,Amortización!$A$8:$B$32,2,FALSE),0),0) -> 0 | G31: =IFERROR(D31-E31-F31,0) -> 0 | H31: =A31 -> 30 | I31: =Entradas_calculos!$K$4 -> 0.084623421 | J31: =(1+I31)^A31 -> 11.438507 | K31: =IF(J31="",0,G31/J31) -> 0 | L31: =+NPV(Entradas_calculos!$K$4,Calculos_generales!G31:G53) -> 0

Sheet Amortización
A1: Inversión Inicial | B1: =Entradas_calculos!N4 -> 0
A2: Tasa EA (i + IBR) | B2: =Entradas_calculos!N5 -> 0
A3: Periodo (años) | B3: =Entradas_calculos!N6 -> 0
A4: Periodo gracia | B4: =Entradas_calculos!N7 -> 0
A5: ¿Hay préstamo? | B5: =Entradas_calculos!N2 -> 0
A6: Período | B6: Cuota | C6: Amortización | D6: Interés | E6: Saldo deuda
A7: 0 | B7: =IF($B$5="Sí",IFERROR(PMT($B$2,$B$3-$B$4,-($B$1*(1+$B$2)^$B$4)),0),0) -> 0 | E7: =IF($B$5="Sí",$B$1*(1+$B$2)^$B$4,0) -> 0
A8: 1 | B8: =IF($B$5="Sí",IF(A8>$B$3,0,B7),0) -> 0 | C8: =IF($B$5="Sí",IF(A8<=$B$4,0,B8-D8),0) -> 0 | D8: =IF($B$5="Sí",E7*$B$2,0) -> 0 | E8: =IF($B$5="Sí",MAX(E7-C8,0),0) -> 0
A9: 2 | B9: =IF($B$5="Sí",IF(A9>$B$3,0,B8),0) -> 0 | C9: =IF($B$5="Sí",IF(A9<=$B$4,0,B9-D9),0) -> 0 | D9: =IF($B$5="Sí",E8*$B$2,0) -> 0 | E9: =IF($B$5="Sí",MAX(E8-C9,0),0) -> 0
A10: 3 | B10: =IF($B$5="Sí",IF(A10>$B$3,0,B9),0) -> 0 | C10: =IF($B$5="Sí",IF(A10<=$B$4,0,B10-D10),0) -> 0 | D10: =IF($B$5="Sí",E9*$B$2,0) -> 0 | E10: =IF($B$5="Sí",MAX(E9-C10,0),0) -> 0
A11: 4 | B11: =IF($B$5="Sí",IF(A11>$B$3,0,B10),0) -> 0 | C11: =IF($B$5="Sí",IF(A11<=$B$4,0,B11-D11),0) -> 0 | D11: =IF($B$5="Sí",E10*$B$2,0) -> 0 | E11: =IF($B$5="Sí",MAX(E10-C11,0),0) -> 0
A12: 5 | B12: =IF($B$5="Sí",IF(A12>$B$3,0,B11),0) -> 0 | C12: =IF($B$5="Sí",IF(A12<=$B$4,0,B12-D12),0) -> 0 | D12: =IF($B$5="Sí",E11*$B$2,0) -> 0 | E12: =IF($B$5="Sí",MAX(E11-C12,0),0) -> 0
A13: 6 | B13: =IF($B$5="Sí",IF(A13>$B$3,0,B12),0) -> 0 | C13: =IF($B$5="Sí",IF(A13<=$B$4,0,B13-D13),0) -> 0 | D13: =IF($B$5="Sí",E12*$B$2,0) -> 0 | E13: =IF($B$5="Sí",MAX(E12-C13,0),0) -> 0
A14: 7 | B14: =IF($B$5="Sí",IF(A14>$B$3,0,B13),0) -> 0 | C14: =IF($B$5="Sí",IF(A14<=$B$4,0,B14-D14),0) -> 0 | D14: =IF($B$5="Sí",E13*$B$2,0) -> 0 | E14: =IF($B$5="Sí",MAX(E13-C14,0),0) -> 0
A15: 8 | B15: =IF($B$5="Sí",IF(A15>$B$3,0,B14),0) -> 0 | C15: =IF($B$5="Sí",IF(A15<=$B$4,0,B15-D15),0) -> 0 | D15: =IF($B$5="Sí",E14*$B$2,0) -> 0 | E15: =IF($B$5="Sí",MAX(E14-C15,0),0) -> 0
A16: 9 | B16: =IF($B$5="Sí",IF(A16>$B$3,0,B15),0) -> 0 | C16: =IF($B$5="Sí",IF(A16<=$B$4,0,B16-D16),0) -> 0 | D16: =IF($B$5="Sí",E15*$B$2,0) -> 0 | E16: =IF($B$5="Sí",MAX(E15-C16,0),0) -> 0
A17: 10 | B17: =IF($B$5="Sí",IF(A17>$B$3,0,B16),0) -> 0 | C17: =IF($B$5="Sí",IF(A17<=$B$4,0,B17-D17),0) -> 0 | D17: =IF($B$5="Sí",E16*$B$2,0) -> 0 | E17: =IF($B$5="Sí",MAX(E16-C17,0),0) -> 0
A18: 11 | B18: =IF($B$5="Sí",IF(A18>$B$3,0,B17),0) -> 0 | C18: =IF($B$5="Sí",IF(A18<=$B$4,0,B18-D18),0) -> 0 | D18: =IF($B$5="Sí",E17*$B$2,0) -> 0 | E18: =IF($B$5="Sí",MAX(E17-C18,0),0) -> 0
A19: 12 | B19: =IF($B$5="Sí",IF(A19>$B$3,0,B18),0) -> 0 | C19: =IF($B$5="Sí",IF(A19<=$B$4,0,B19-D19),0) -> 0 | D19: =IF($B$5="Sí",E18*$B$2,0) -> 0 | E19: =IF($B$5="Sí",MAX(E18-C19,0),0) -> 0
... A32: 25 | B32: =IF($B$5="Sí",IF(A32>$B$3,0,B31),0) -> 0 | C32: =IF($B$5="Sí",IF(A32<=$B$4,0,B32-D32),0) -> 0 | D32: =IF($B$5="Sí",E31*$B$2,0) -> 0 | E32: =IF($B$5="Sí",MAX(E31-C32,0),0) -> 0

Sheet calculo_etapa_vegetativa
A1: Costos de siembra por hectárea etapa improductiva
A2: Año | B2: Costo en pesos constantes/ha | C2: Costo Financiero | D2: valor inversion | E2: Período (n) | F2: Valor futuro (VF) | H2: tasa de descuento
A3: 1 | B3: =IFERROR(VLOOKUP(A3,Entradas_calculos!$B$2:$C$32,2,FALSE),0) -> 21007737 | D3: =(B3+C3) -> 21007737 | E3: =IF(A3>Entradas_calculos!$K$2,"",Entradas_calculos!$K$2-A3) -> 5 | F3: =IFERROR(D3*(1+$H$3)^E3,0) -> 31533644 | H3: =Entradas_Tasas!$F$57 -> 0.084623421
A4: 2 | B4: =IFERROR(VLOOKUP(A4,Entradas_calculos!$B$2:$C$32,2,FALSE),0) -> 16737024 | D4: =(B4+C4) -> 16737024 | E4: =IF(A4>Entradas_calculos!$K$2,"",Entradas_calculos!$K$2-A4) -> 4 | F4: =IFERROR(D4*(1+$H$3)^E4,0) -> 23162964
A5: 3 | B5: =IFERROR(VLOOKUP(A5,Entradas_calculos!$B$2:$C$32,2,FALSE),0) -> 16737024 | D5: =(B5+C5) -> 16737024 | E5: =IF(A5>Entradas_calculos!$K$2,"",Entradas_calculos!$K$2-A5) -> 3 | F5: =IFERROR(D5*(1+$H$3)^E5,0) -> 21355766
A6: 4 | B6: =IFERROR(VLOOKUP(A6,Entradas_calculos!$B$2:$C$32,2,FALSE),0) -> 16737024 | D6: =IFERROR(B6+C6,0) -> 16737024 | E6: =IF(A6>Entradas_calculos!$K$2,"",Entradas_calculos!$K$2-A6) -> 2 | F6: =IFERROR(D6*(1+$H$3)^E6,0) -> 19689568
A7: 5 | B7: =IFERROR(VLOOKUP(A7,Entradas_calculos!$B$2:$C$32,2,FALSE),0) -> 16737024 | D7: =IFERROR(B7+C7,0) -> 16737024 | E7: =IF(A7>Entradas_calculos!$K$2,"",Entradas_calculos!$K$2-A7) -> 1 | F7: =IFERROR(D7*(1+$H$3)^E7,0) -> 18153368
A8: 6 | B8: =IFERROR(VLOOKUP(A8,Entradas_calculos!$B$2:$C$32,2,FALSE),0) -> 18097824 | D8: =IFERROR(B8+C8,0) -> 18097824 | E8: =IF(A8>Entradas_calculos!$K$2,"",Entradas_calculos!$K$2-A8) -> 0 | F8: =IFERROR(D8*(1+$H$3)^E8,0) -> 18097824
A9: 7 | B9: =IFERROR(VLOOKUP(A9,Entradas_calculos!$B$2:$C$32,2,FALSE),0) | D9: =IFERROR(B9+C9,0) -> 0 | E9: =IF(A9>Entradas_calculos!$K$2,"",Entradas_calculos!$K$2-A9) | F9: =IFERROR(D9*(1+$H$3)^E9,0) -> 0
A10: 8 | B10: =IFERROR(VLOOKUP(A10,Entradas_calculos!$B$2:$C$32,2,FALSE),0) | D10: =IFERROR(B10+C10,0) -> 0 | E10: =IF(A10>Entradas_calculos!$K$2,"",Entradas_calculos!$K$2-A10) | F10: =IFERROR(D10*(1+$H$3)^E10,0) -> 0
A11: 9 | B11: =IFERROR(VLOOKUP(A11,Entradas_calculos!$B$2:$C$32,2,FALSE),0) | D11: =IFERROR(B11+C11,0) -> 0 | E11: =IF(A11>Entradas_calculos!$K$2,"",Entradas_calculos!$K$2-A11) | F11: =IFERROR(D11*(1+$H$3)^E11,0) -> 0
A12: 10 | B12: =IFERROR(VLOOKUP(A12,Entradas_calculos!$B$2:$C$32,2,FALSE),0) | D12: =IFERROR(B12+C12,0) -> 0 | E12: =IF(A12>Entradas_calculos!$K$2,"",Entradas_calculos!$K$2-A12) | F12: =IFERROR(D12*(1+$H$3)^E12,0) -> 0
A13: 11 | B13: =IFERROR(VLOOKUP(A13,Entradas_calculos!$B$2:$C$32,2,FALSE),0) | D13: =IFERROR(B13+C13,0) -> 0 | E13: =IF(A13>Entradas_calculos!$K$2,"",Entradas_calculos!$K$2-A13) | F13: =IFERROR(D13*(1+$H$3)^E13,0) -> 0
A14: 12 | B14: =IFERROR(VLOOKUP(A14,Entradas_calculos!$B$2:$C$32,2,FALSE),0) | D14: =IFERROR(B14+C14,0) -> 0 | E14: =IF(A14>Entradas_calculos!$K$2,"",Entradas_calculos!$K$2-A14) | F14: =IFERROR(D14*(1+$H$3)^E14,0) -> 0
A15: 13 | B15: =IFERROR(VLOOKUP(A15,Entradas_calculos!$B$2:$C$32,2,FALSE),0) | D15: =IFERROR(B15+C15,0) -> 0 | E15: =IF(A15>Entradas_calculos!$K$2,"",Entradas_calculos!$K$2-A15) | F15: =IFERROR(D15*(1+$H$3)^E15,0) -> 0
A16: 14 | B16: =IFERROR(VLOOKUP(A16,Entradas_calculos!$B$2:$C$32,2,FALSE),0) | D16: =IFERROR(B16+C16,0) -> 0 | E16: =IF(A16>Entradas_calculos!$K$2,"",Entradas_calculos!$K$2-A16) | F16: =IFERROR(D16*(1+$H$3)^E16,0) -> 0
A17: 15 | B17: =IFERROR(VLOOKUP(A17,Entradas_calculos!$B$2:$C$32,2,FALSE),0) | D17: =IFERROR(B17+C17,0) -> 0 | E17: =IF(A17>Entradas_calculos!$K$2,"",Entradas_calculos!$K$2-A17) | F17: =IFERROR(D17*(1+$H$3)^E17,0) -> 0
... A32: 30 | B32: =IFERROR(VLOOKUP(A32,Entradas_calculos!$B$2:$C$32,2,FALSE),0) -> 0 | D32: =IFERROR(B32+C32,0) -> 0 | E32: =IF(A32>Entradas_calculos!$K$2,"",Entradas_calculos!$K$2-A32) | F32: =IFERROR(D32*(1+$H$3)^E32,0) -> 0
D33: {=SUMPRODUCT(ISNUMBER(E3:E32)*D3:D32)} -> 1.0605365e+08 | F33: =SUM(F3:F32) -> 1.3199313e+08 | G33: =F33-D33 -> 25939479
G34: =G33/F33 -> 0.19652143

Sheet Calculo_etapa_productiva
A1: Edad | B1: Prod/ha (kg) | C1: Precio | D1: Ingreso (Prod*Precio) | E1: Costo/ha | F1: Costo Financiero | G1: Flujo Neto | H1: n (años) | I1: Interés | J1: Factor Descuento | K1: VP del Flujo | L1: VPN Remanente | M1: VPN traído al momento 0
A2: 1 | B2: =IFERROR(VLOOKUP(A2,Entradas_calculos!$E$3:$F$32,2,FALSE),0) -> 10450 | C2: =Entradas_calculos!$K$3 -> 4000 | D2: =IFERROR(B2*C2,0) -> 41800000 | E2: =IFERROR(VLOOKUP(A2,Entradas_calculos!$B$3:$C$32,2,FALSE),0) -> 21007737 | F2: =+IF(AND(A2<=Amortización!$B$3,A2-Amortización!$B$4>0),IFERROR(VLOOKUP(A2,Amortización!$A$8:$B$32,2,FALSE),0),0) -> 0 | G2: =IFERROR(D2-E2-F2,0) -> 20792263 | H2: =IF(A2<Entradas_calculos!$K$2,"",A2-Entradas_calculos!$K$2+1) | I2: =Entradas_calculos!$K$4 -> 0.084623421 | J2: =IF(H2="","",(1+I2)^H2) | K2: =IF(J2="",0,G2/J2) -> 0 | L2: =+NPV(Entradas_calculos!$K$4,G2:G31) -> 1.8336e+08
A3: 2 | B3: =IFERROR(VLOOKUP(A3,Entradas_calculos!$E$3:$F$32,2,FALSE),0) -> 17100 | C3: =Entradas_calculos!$K$3 -> 4000 | D3: =IFERROR(B3*C3,0) -> 68400000 | E3: =IFERROR(VLOOKUP(A3,Entradas_calculos!$B$3:$C$32,2,FALSE),0) -> 16737024 | F3: =+IF(AND(A3<=Amortización!$B$3,A3-Amortización!$B$4>0),IFERROR(VLOOKUP(A3,Amortización!$A$8:$B$32,2,FALSE),0),0) -> 0 | G3: =IFERROR(D3-E3-F3,0) -> 51662976 | H3: =IF(A3<Entradas_calculos!$K$2,"",A3-Entradas_calculos!$K$2+1) | I3: =Entradas_calculos!$K$4 -> 0.084623421 | J3: =IF(H3="","",(1+I3)^H3) | K3: =IF(J3="",0,G3/J3) -> 0 | L3: =+NPV(Entradas_calculos!$K$4,G3:G31) -> 1.7808428e+08
A4: 3 | B4: =IFERROR(VLOOKUP(A4,Entradas_calculos!$E$3:$F$32,2,FALSE),0) -> 16245 | C4: =Entradas_calculos!$K$3 -> 4000 | D4: =IFERROR(B4*C4,0) -> 64980000 | E4: =IFERROR(VLOOKUP(A4,Entradas_calculos!$B$3:$C$32,2,FALSE),0) -> 16737024 | F4: =+IF(AND(A4<=Amortización!$B$3,A4-Amortización!$B$4>0),IFERROR(VLOOKUP(A4,Amortización!$A$8:$B$32,2,FALSE),0),0) -> 0 | G4: =IFERROR(D4-E4-F4,0) -> 48242976 | H4: =IF(A4<Entradas_calculos!$K$2,"",A4-Entradas_calculos!$K$2+1) | I4: =Entradas_calculos!$K$4 -> 0.084623421 | J4: =IF(H4="","",(1+I4)^H4) | K4: =IF(J4="",0,G4/J4) -> 0 | L4: =+NPV(Entradas_calculos!$K$4,G4:G31) -> 1.4149141e+08 | M4: =IF(H4="","",L4/((1+Entradas_calculos!$K$4)^H4))
A5: 4 | B5: =IFERROR(VLOOKUP(A5,Entradas_calculos!$E$3:$F$32,2,FALSE),0) -> 15390 | C5: =Entradas_calculos!$K$3 -> 4000 | D5: =IFERROR(B5*C5,0) -> 61560000 | E5: =IFERROR(VLOOKUP(A5,Entradas_calculos!$B$3:$C$32,2,FALSE),0) -> 16737024 | F5: =+IF(AND(A5<=Amortización!$B$3,A5-Amortización!$B$4>0),IFERROR(VLOOKUP(A5,Amortización!$A$8:$B$32,2,FALSE),0),0) -> 0 | G5: =IFERROR(D5-E5-F5,0) -> 44822976 | H5: =IF(A5<Entradas_calculos!$K$2,"",A5-Entradas_calculos!$K$2+1) | I5: =Entradas_calculos!$K$4 -> 0.084623421 | J5: =IF(H5="","",(1+I5)^H5) | K5: =IF(J5="",0,G5/J5) -> 0 | L5: =+NPV(Entradas_calculos!$K$4,G5:G31) -> 1.0522192e+08 | M5: =IF(H5="","",L5/((1+Entradas_calculos!$K$4)^H5))
A6: 5 | B6: =IFERROR(VLOOKUP(A6,Entradas_calculos!$E$3:$F$32,2,FALSE),0) -> 14535 | C6: =Entradas_calculos!$K$3 -> 4000 | D6: =IFERROR(B6*C6,0) -> 58140000 | E6: =IFERROR(VLOOKUP(A6,Entradas_calculos!$B$3:$C$32,2,FALSE),0) -> 16737024 | F6: =+IF(AND(A6<=Amortización!$B$3,A6-Amortización!$B$4>0),IFERROR(VLOOKUP(A6,Amortización!$A$8:$B$32,2,FALSE),0),0) -> 0 | G6: =IFERROR(D6-E6-F6,0) -> 41402976 | H6: =IF(A6<Entradas_calculos!$K$2,"",A6-Entradas_calculos!$K$2+1) | I6: =Entradas_calculos!$K$4 -> 0.084623421 | J6: =IF(H6="","",(1+I6)^H6) | K6: =IF(J6="",0,G6/J6) -> 0 | L6: =+NPV(Entradas_calculos!$K$4,G6:G31) -> 69303181 | M6: =IF(H6="","",L6/((1+Entradas_calculos!$K$4)^H6))
A7: 6 | B7: =IFERROR(VLOOKUP(A7,Entradas_calculos!$E$3:$F$32,2,FALSE),0) -> 13680 | C7: =Entradas_calculos!$K$3 -> 4000 | D7: =IFERROR(B7*C7,0) -> 54720000 | E7: =IFERROR(VLOOKUP(A7,Entradas_calculos!$B$3:$C$32,2,FALSE),0) -> 18097824 | F7: =+IF(AND(A7<=Amortización!$B$3,A7-Amortización!$B$4>0),IFERROR(VLOOKUP(A7,Amortización!$A$8:$B$32,2,FALSE),0),0) -> 0 | G7: =IFERROR(D7-E7-F7,0) -> 36622176 | H7: =IF(A7<Entradas_calculos!$K$2,"",A7-Entradas_calculos!$K$2+1) -> 1 | I7: =Entradas_calculos!$K$4 -> 0.084623421 | J7: =IF(H7="","",(1+I7)^H7) -> 1.0846234 | K7: =IF(J7="",0,G7/J7) -> 33764877 | L7: =+NPV(Entradas_calculos!$K$4,G7:G31) -> 33764877 | M7: =IF(H7="","",L7/((1+Entradas_calculos!$K$4)^H7)) -> 31130507
A8: 7 | B8: =IFERROR(VLOOKUP(A8,Entradas_calculos!$E$3:$F$32,2,FALSE),0) | C8: =Entradas_calculos!$K$3 -> 4000 | D8: =IFERROR(B8*C8,0) -> 0 | E8: =IFERROR(VLOOKUP(A8,Entradas_calculos!$B$3:$C$32,2,FALSE),0) | F8: =+IF(AND(A8<=Amortización!$B$3,A8-Amortización!$B$4>0),IFERROR(VLOOKUP(A8,Amortización!$A$8:$B$32,2,FALSE),0),0) -> 0 | G8: =IFERROR(D8-E8-F8,0) -> 0 | H8: =IF(A8<Entradas_calculos!$K$2,"",A8-Entradas_calculos!$K$2+1) -> 2 | I8: =Entradas_calculos!$K$4 -> 0.084623421 | J8: =IF(H8="","",(1+I8)^H8) -> 1.176408 | K8: =IF(J8="",0,G8/J8) -> 0 | L8: =+NPV(Entradas_calculos!$K$4,G8:G31) -> 0 | M8: =IF(H8="","",L8/((1+Entradas_calculos!$K$4)^H8)) -> 0
A9: 8 | B9: =IFERROR(VLOOKUP(A9,Entradas_calculos!$E$3:$F$32,2,FALSE),0) | C9: =Entradas_calculos!$K$3 -> 4000 | D9: =IFERROR(B9*C9,0) -> 0 | E9: =IFERROR(VLOOKUP(A9,Entradas_calculos!$B$3:$C$32,2,FALSE),0) | F9: =+IF(AND(A9<=Amortización!$B$3,A9-Amortización!$B$4>0),IFERROR(VLOOKUP(A9,Amortización!$A$8:$B$32,2,FALSE),0),0) -> 0 | G9: =IFERROR(D9-E9-F9,0) -> 0 | H9: =IF(A9<Entradas_calculos!$K$2,"",A9-Entradas_calculos!$K$2+1) -> 3 | I9: =Entradas_calculos!$K$4 -> 0.084623421 | J9: =IF(H9="","",(1+I9)^H9) -> 1.2759596 | K9: =IF(J9="",0,G9/J9) -> 0 | L9: =+NPV(Entradas_calculos!$K$4,Calculo_etapa_productiva!G9:G31) -> 0 | M9: =IF(H9="","",L9/((1+Entradas_calculos!$K$4)^H9)) -> 0
A10: 9 | B10: =IFERROR(VLOOKUP(A10,Entradas_calculos!$E$3:$F$32,2,FALSE),0) | C10: =Entradas_calculos!$K$3 -> 4000 | D10: =IFERROR(B10*C10,0) -> 0 | E10: =IFERROR(VLOOKUP(A10,Entradas_calculos!$B$3:$C$32,2,FALSE),0) | F10: =+IF(AND(A10<=Amortización!$B$3,A10-Amortización!$B$4>0),IFERROR(VLOOKUP(A10,Amortización!$A$8:$B$32,2,FALSE),0),0) -> 0 | G10: =IFERROR(D10-E10-F10,0) -> 0 | H10: =IF(A10<Entradas_calculos!$K$2,"",A10-Entradas_calculos!$K$2+1) -> 4 | I10: =Entradas_calculos!$K$4 -> 0.084623421 | J10: =IF(H10="","",(1+I10)^H10) -> 1.3839357 | K10: =IF(J10="",0,G10/J10) -> 0 | L10: =+NPV(Entradas_calculos!$K$4,Calculo_etapa_productiva!G10:G32) -> 0 | M10: =IF(H10="","",L10/((1+Entradas_calculos!$K$4)^H10)) -> 0
A11: 10 | B11: =IFERROR(VLOOKUP(A11,Entradas_calculos!$E$3:$F$32,2,FALSE),0) | C11: =Entradas_calculos!$K$3 -> 4000 | D11: =IFERROR(B11*C11,0) -> 0 | E11: =IFERROR(VLOOKUP(A11,Entradas_calculos!$B$3:$C$32,2,FALSE),0) | F11: =+IF(AND(A11<=Amortización!$B$3,A11-Amortización!$B$4>0),IFERROR(VLOOKUP(A11,Amortización!$A$8:$B$32,2,FALSE),0),0) -> 0 | G11: =IFERROR(D11-E11-F11,0) -> 0 | H11: =IF(A11<Entradas_calculos!$K$2,"",A11-Entradas_calculos!$K$2+1) -> 5 | I11: =Entradas_calculos!$K$4 -> 0.084623421 | J11: =IF(H11="","",(1+I11)^H11) -> 1.5010491 | K11: =IF(J11="",0,G11/J11) -> 0 | L11: =+NPV(Entradas_calculos!$K$4,G11:G31) -> 0 | M11: =+L11/((1+Entradas_calculos!$K$4)^Calculo_etapa_productiva!H11) -> 0
A12: 11 | B12: =IFERROR(VLOOKUP(A12,Entradas_calculos!$E$3:$F$32,2,FALSE),0) | C12: =Entradas_calculos!$K$3 -> 4000 | D12: =IFERROR(B12*C12,0) -> 0 | E12: =IFERROR(VLOOKUP(A12,Entradas_calculos!$B$3:$C$32,2,FALSE),0) | F12: =+IF(AND(A12<=Amortización!$B$3,A12-Amortización!$B$4>0),IFERROR(VLOOKUP(A12,Amortización!$A$8:$B$32,2,FALSE),0),0) -> 0 | G12: =IFERROR(D12-E12-F12,0) -> 0 | H12: =IF(A12<Entradas_calculos!$K$2,"",A12-Entradas_calculos!$K$2+1) -> 6 | I12: =Entradas_calculos!$K$4 -> 0.084623421 | J12: =IF(H12="","",(1+I12)^H12) -> 1.628073 | K12: =IF(J12="",0,G12/J12) -> 0 | L12: =+NPV(Entradas_calculos!$K$4,Calculo_etapa_productiva!G12:G34) -> 0 | M12: =+L12/((1+Entradas_calculos!$K$4)^Calculo_etapa_productiva!H12) -> 0
A13: 12 | B13: =IFERROR(VLOOKUP(A13,Entradas_calculos!$E$3:$F$32,2,FALSE),0) | C13: =Entradas_calculos!$K$3 -> 4000 | D13: =IFERROR(B13*C13,0) -> 0 | E13: =IFERROR(VLOOKUP(A13,Entradas_calculos!$B$3:$C$32,2,FALSE),0) | F13: =+IF(AND(A13<=Amortización!$B$3,A13-Amortización!$B$4>0),IFERROR(VLOOKUP(A13,Amortización!$A$8:$B$32,2,FALSE),0),0) -> 0 | G13: =IFERROR(D13-E13-F13,0) -> 0 | H13: =IF(A13<Entradas_calculos!$K$2,"",A13-Entradas_calculos!$K$2+1) -> 7 | I13: =Entradas_calculos!$K$4 -> 0.084623421 | J13: =IF(H13="","",(1+I13)^H13) -> 1.7658461 | K13: =IF(J13="",0,G13/J13) -> 0 | L13: =+NPV(Entradas_calculos!$K$4,Calculo_etapa_productiva!G13:G35) -> 0 | M13: =+L13/((1+Entradas_calculos!$K$4)^Calculo_etapa_productiva!H13) -> 0
A14: 13 | B14: =IFERROR(VLOOKUP(A14,Entradas_calculos!$E$3:$F$32,2,FALSE),0) | C14: =Entradas_calculos!$K$3 -> 4000 | D14: =IFERROR(B14*C14,0) -> 0 | E14: =IFERROR(VLOOKUP(A14,Entradas_calculos!$B$3:$C$32,2,FALSE),0) | F14: =+IF(AND(A14<=Amortización!$B$3,A14-Amortización!$B$4>0),IFERROR(VLOOKUP(A14,Amortización!$A$8:$B$32,2,FALSE),0),0) -> 0 | G14: =IFERROR(D14-E14-F14,0) -> 0 | H14: =IF(A14<Entradas_calculos!$K$2,"",A14-Entradas_calculos!$K$2+1) -> 8 | I14: =Entradas_calculos!$K$4 -> 0.084623421 | J14: =IF(H14="","",(1+I14)^H14) -> 1.915278 | K14: =IF(J14="",0,G14/J14) -> 0 | L14: =+NPV(Entradas_calculos!$K$4,Calculo_etapa_productiva!G14:G36) -> 0 | M14: =+L14/((1+Entradas_calculos!$K$4)^Calculo_etapa_productiva!H14) -> 0
A15: 14 | B15: =IFERROR(VLOOKUP(A15,Entradas_calculos!$E$3:$F$32,2,FALSE),0) | C15: =Entradas_calculos!$K$3 -> 4000 | D15: =IFERROR(B15*C15,0) -> 0 | E15: =IFERROR(VLOOKUP(A15,Entradas_calculos!$B$3:$C$32,2,FALSE),0) | F15: =+IF(AND(A15<=Amortización!$B$3,A15-Amortización!$B$4>0),IFERROR(VLOOKUP(A15,Amortización!$A$8:$B$32,2,FALSE),0),0) -> 0 | G15: =IFERROR(D15-E15-F15,0) -> 0 | H15: =IF(A15<Entradas_calculos!$K$2,"",A15-Entradas_calculos!$K$2+1) -> 9 | I15: =Entradas_calculos!$K$4 -> 0.084623421 | J15: =IF(H15="","",(1+I15)^H15) -> 2.0773554 | K15: =IF(J15="",0,G15/J15) -> 0 | L15: =+NPV(Entradas_calculos!$K$4,Calculo_etapa_productiva!G15:G37) -> 0 | M15: =+L15/((1+Entradas_calculos!$K$4)^Calculo_etapa_productiva!H15) -> 0
A16: 15 | B16: =IFERROR(VLOOKUP(A16,Entradas_calculos!$E$3:$F$32,2,FALSE),0) | C16: =Entradas_calculos!$K$3 -> 4000 | D16: =IFERROR(B16*C16,0) -> 0 | E16: =IFERROR(VLOOKUP(A16,Entradas_calculos!$B$3:$C$32,2,FALSE),0) | F16: =+IF(AND(A16<=Amortización!$B$3,A16-Amortización!$B$4>0),IFERROR(VLOOKUP(A16,Amortización!$A$8:$B$32,2,FALSE),0),0) -> 0 | G16: =IFERROR(D16-E16-F16,0) -> 0 | H16: =IF(A16<Entradas_calculos!$K$2,"",A16-Entradas_calculos!$K$2+1) -> 10 | I16: =Entradas_calculos!$K$4 -> 0.084623421 | J16: =IF(H16="","",(1+I16)^H16) -> 2.2531483 | K16: =IF(J16="",0,G16/J16) -> 0 | L16: =+NPV(Entradas_calculos!$K$4,Calculo_etapa_productiva!G16:G38) -> 0 | M16: =+L16/((1+Entradas_calculos!$K$4)^Calculo_etapa_productiva!H16) -> 0
A17: 16 | B17: =IFERROR(VLOOKUP(A17,Entradas_calculos!$E$3:$F$32,2,FALSE),0) | C17: =Entradas_calculos!$K$3 -> 4000 | D17: =IFERROR(B17*C17,0) -> 0 | E17: =IFERROR(VLOOKUP(A17,Entradas_calculos!$B$3:$C$32,2,FALSE),0) | F17: =+IF(AND(A17<=Amortización!$B$3,A17-Amortización!$B$4>0),IFERROR(VLOOKUP(A17,Amortización!$A$8:$B$32,2,FALSE),0),0) -> 0 | G17: =IFERROR(D17-E17-F17,0) -> 0 | H17: =IF(A17<Entradas_calculos!$K$2,"",A17-Entradas_calculos!$K$2+1) -> 11 | I17: =Entradas_calculos!$K$4 -> 0.084623421 | J17: =IF(H17="","",(1+I17)^H17) -> 2.4438174 | K17: =IF(J17="",0,G17/J17) -> 0 | L17: =+NPV(Entradas_calculos!$K$4,Calculo_etapa_productiva!G17:G39) -> 0 | M17: =+L17/((1+Entradas_calculos!$K$4)^Calculo_etapa_productiva!H17) -> 0
A18: 17 | B18: =IFERROR(VLOOKUP(A18,Entradas_calculos!$E$3:$F$32,2,FALSE),0) | C18: =Entradas_calculos!$K$3 -> 4000 | D18: =IFERROR(B18*C18,0) -> 0 | E18: =IFERROR(VLOOKUP(A18,Entradas_calculos!$B$3:$C$32,2,FALSE),0) | F18: =+IF(AND(A18<=Amortización!$B$3,A18-Amortización!$B$4>0),IFERROR(VLOOKUP(A18,Amortización!$A$8:$B$32,2,FALSE),0),0) -> 0 | G18: =IFERROR(D18-E18-F18,0) -> 0 | H18: =IF(A18<Entradas_calculos!$K$2,"",A18-Entradas_calculos!$K$2+1) -> 12 | I18: =Entradas_calculos!$K$4 -> 0.084623421 | J18: =IF(H18="","",(1+I18)^H18) -> 2.6506216 | K18: =IF(J18="",0,G18/J18) -> 0 | L18: =+NPV(Entradas_calculos!$K$4,Calculo_etapa_productiva!G18:G40) -> 0 | M18: =+L18/((1+Entradas_calculos!$K$4)^Calculo_etapa_productiva!H18) -> 0
A19: 18 | B19: =IFERROR(VLOOKUP(A19,Entradas_calculos!$E$3:$F$32,2,FALSE),0) | C19: =Entradas_calculos!$K$3 -> 4000 | D19: =IFERROR(B19*C19,0) -> 0 | E19: =IFERROR(VLOOKUP(A19,Entradas_calculos!$B$3:$C$32,2,FALSE),0) | F19: =+IF(AND(A19<=Amortización!$B$3,A19-Amortización!$B$4>0),IFERROR(VLOOKUP(A19,Amortización!$A$8:$B$32,2,FALSE),0),0) -> 0 | G19: =IFERROR(D19-E19-F19,0) -> 0 | H19: =IF(A19<Entradas_calculos!$K$2,"",A19-Entradas_calculos!$K$2+1) -> 13 | I19: =Entradas_calculos!$K$4 -> 0.084623421 | J19: =IF(H19="","",(1+I19)^H19) -> 2.8749263 | K19: =IF(J19="",0,G19/J19) -> 0 | L19: =+NPV(Entradas_calculos!$K$4,Calculo_etapa_productiva!G19:G41) -> 0 | M19: =+L19/((1+Entradas_calculos!$K$4)^Calculo_etapa_productiva!H19) -> 0
A20: 19 | B20: =IFERROR(VLOOKUP(A20,Entradas_calculos!$E$3:$F$32,2,FALSE),0) | C20: =Entradas_calculos!$K$3 -> 4000 | D20: =IFERROR(B20*C20,0) -> 0 | E20: =IFERROR(VLOOKUP(A20,Entradas_calculos!$B$3:$C$32,2,FALSE),0) | F20: =+IF(AND(A20<=Amortización!$B$3,A20-Amortización!$B$4>0),IFERROR(VLOOKUP(A20,Amortización!$A$8:$B$32,2,FALSE),0),0) -> 0 | G20: =IFERROR(D20-E20-F20,0) -> 0 | H20: =IF(A20<Entradas_calculos!$K$2,"",A20-Entradas_calculos!$K$2+1) -> 14 | I20: =Entradas_calculos!$K$4 -> 0.084623421 | J20: =IF(H20="","",(1+I20)^H20) -> 3.1182124 | K20: =IF(J20="",0,G20/J20) -> 0 | L20: =+NPV(Entradas_calculos!$K$4,Calculo_etapa_productiva!G20:G42) -> 0 | M20: =+L20/((1+Entradas_calculos!$K$4)^Calculo_etapa_productiva!H20) -> 0
A21: 20 | B21: =IFERROR(VLOOKUP(A21,Entradas_calculos!$E$3:$F$32,2,FALSE),0) | C21: =Entradas_calculos!$K$3 -> 4000 | D21: =IFERROR(B21*C21,0) -> 0 | E21: =IFERROR(VLOOKUP(A21,Entradas_calculos!$B$3:$C$32,2,FALSE),0) | F21: =+IF(AND(A21<=Amortización!$B$3,A21-Amortización!$B$4>0),IFERROR(VLOOKUP(A21,Amortización!$A$8:$B$32,2,FALSE),0),0) -> 0 | G21: =IFERROR(D21-E21-F21,0) -> 0 | H21: =IF(A21<Entradas_calculos!$K$2,"",A21-Entradas_calculos!$K$2+1) -> 15 | I21: =Entradas_calculos!$K$4 -> 0.084623421 | J21: =IF(H21="","",(1+I21)^H21) -> 3.3820862 | K21: =IF(J21="",0,G21/J21) -> 0 | L21: =+NPV(Entradas_calculos!$K$4,Calculo_etapa_productiva!G21:G43) -> 0 | M21: =+L21/((1+Entradas_calculos!$K$4)^Calculo_etapa_productiva!H21) -> 0
A22: 21 | B22: =IFERROR(VLOOKUP(A22,Entradas_calculos!$E$3:$F$32,2,FALSE),0) | C22: =Entradas_calculos!$K$3 -> 4000 | D22: =IFERROR(B22*C22,0) -> 0 | E22: =IFERROR(VLOOKUP(A22,Entradas_calculos!$B$3:$C$32,2,FALSE),0) | F22: =+IF(AND(A22<=Amortización!$B$3,A22-Amortización!$B$4>0),IFERROR(VLOOKUP(A22,Amortización!$A$8:$B$32,2,FALSE),0),0) -> 0 | G22: =IFERROR(D22-E22-F22,0) -> 0 | H22: =IF(A22<Entradas_calculos!$K$2,"",A22-Entradas_calculos!$K$2+1) -> 16 | I22: =Entradas_calculos!$K$4 -> 0.084623421 | J22: =IF(H22="","",(1+I22)^H22) -> 3.6682899 | K22: =IF(J22="",0,G22/J22) -> 0 | L22: =+NPV(Entradas_calculos!$K$4,Calculo_etapa_productiva!G22:G44) -> 0 | M22: =+L22/((1+Entradas_calculos!$K$4)^Calculo_etapa_productiva!H22) -> 0
A23: 22 | B23: =IFERROR(VLOOKUP(A23,Entradas_calculos!$E$3:$F$32,2,FALSE),0) | C23: =Entradas_calculos!$K$3 -> 4000 | D23: =IFERROR(B23*C23,0) -> 0 | E23: =IFERROR(VLOOKUP(A23,Entradas_calculos!$B$3:$C$32,2,FALSE),0) | F23: =+IF(AND(A23<=Amortización!$B$3,A23-Amortización!$B$4>0),IFERROR(VLOOKUP(A23,Amortización!$A$8:$B$32,2,FALSE),0),0) -> 0 | G23: =IFERROR(D23-E23-F23,0) -> 0 | H23: =IF(A23<Entradas_calculos!$K$2,"",A23-Entradas_calculos!$K$2+1) -> 17 | I23: =Entradas_calculos!$K$4 -> 0.084623421 | J23: =IF(H23="","",(1+I23)^H23) -> 3.9787132 | K23: =IF(J23="",0,G23/J23) -> 0 | L23: =+NPV(Entradas_calculos!$K$4,Calculo_etapa_productiva!G23:G45) -> 0 | M23: =+L23/((1+Entradas_calculos!$K$4)^Calculo_etapa_productiva!H23) -> 0
... A26: 25 | B26: =IFERROR(VLOOKUP(A26,Entradas_calculos!$E$3:$F$32,2,FALSE),0) | C26: =Entradas_calculos!$K$3 -> 4000 | D26: =IFERROR(B26*C26,0) -> 0 | E26: =IFERROR(VLOOKUP(A26,Entradas_calculos!$B$3:$C$32,2,FALSE),0) | F26: =+IF(AND(A26<=Amortización!$B$3,A26-Amortización!$B$4>0),IFERROR(VLOOKUP(A26,Amortización!$A$8:$B$32,2,FALSE),0),0) -> 0 | G26: =IFERROR(D26-E26-F26,0) -> 0 | H26: =IF(A26<Entradas_calculos!$K$2,"",A26-Entradas_calculos!$K$2+1) -> 20 | I26: =Entradas_calculos!$K$4 -> 0.084623421 | J26: =IF(H26="","",(1+I26)^H26) -> 5.0766774 | K26: =IF(J26="",0,G26/J26) -> 0 | L26: =+NPV(Entradas_calculos!$K$4,Calculo_etapa_productiva!G26:G48) -> 0 | M26: =+L26/((1+Entradas_calculos!$K$4)^Calculo_etapa_productiva!H26) -> 0
A27: 26 | B27: =IFERROR(VLOOKUP(A27,Entradas_calculos!$E$3:$F$32,2,FALSE),0) | C27: =Entradas_calculos!$K$3 -> 4000 | D27: =IFERROR(B27*C27,0) -> 0 | E27: =IFERROR(VLOOKUP(A27,Entradas_calculos!$B$3:$C$32,2,FALSE),0) | F27: =+IF(AND(A27<=Amortización!$B$3,A27-Amortización!$B$4>0),IFERROR(VLOOKUP(A27,Amortización!$A$8:$B$32,2,FALSE),0),0) -> 0 | G27: =IFERROR(D27-E27-F27,0) -> 0 | H27: =IF(A27<Entradas_calculos!$K$2,"",A27-Entradas_calculos!$K$2+1) -> 21 | I27: =Entradas_calculos!$K$4 -> 0.084623421 | J27: =IF(H27="","",(1+I27)^H27) -> 5.5062832 | K27: =IF(J27="",0,G27/J27) -> 0 | L27: =+NPV(Entradas_calculos!$K$4,Calculo_etapa_productiva!G27:G49) -> 0
A28: 27 | B28: =IFERROR(VLOOKUP(A28,Entradas_calculos!$E$3:$F$32,2,FALSE),0) | C28: =Entradas_calculos!$K$3 -> 4000 | D28: =IFERROR(B28*C28,0) -> 0 | E28: =IFERROR(VLOOKUP(A28,Entradas_calculos!$B$3:$C$32,2,FALSE),0) | F28: =+IF(AND(A28<=Amortización!$B$3,A28-Amortización!$B$4>0),IFERROR(VLOOKUP(A28,Amortización!$A$8:$B$32,2,FALSE),0),0) -> 0 | G28: =IFERROR(D28-E28-F28,0) -> 0 | H28: =IF(A28<Entradas_calculos!$K$2,"",A28-Entradas_calculos!$K$2+1) -> 22 | I28: =Entradas_calculos!$K$4 -> 0.084623421 | J28: =IF(H28="","",(1+I28)^H28) -> 5.9722437 | K28: =IF(J28="",0,G28/J28) -> 0 | L28: =+NPV(Entradas_calculos!$K$4,Calculo_etapa_productiva!G28:G50) -> 0
A29: 28 | B29: =IFERROR(VLOOKUP(A29,Entradas_calculos!$E$3:$F$32,2,FALSE),0) | C29: =Entradas_calculos!$K$3 -> 4000 | D29: =IFERROR(B29*C29,0) -> 0 | E29: =IFERROR(VLOOKUP(A29,Entradas_calculos!$B$3:$C$32,2,FALSE),0) | F29: =+IF(AND(A29<=Amortización!$B$3,A29-Amortización!$B$4>0),IFERROR(VLOOKUP(A29,Amortización!$A$8:$B$32,2,FALSE),0),0) -> 0 | G29: =IFERROR(D29-E29-F29,0) -> 0 | H29: =IF(A29<Entradas_calculos!$K$2,"",A29-Entradas_calculos!$K$2+1) -> 23 | I29: =Entradas_calculos!$K$4 -> 0.084623421 | J29: =IF(H29="","",(1+I29)^H29) -> 6.4776354 | K29: =IF(J29="",0,G29/J29) -> 0 | L29: =+NPV(Entradas_calculos!$K$4,Calculo_etapa_productiva!G29:G51) -> 0
A30: 29 | B30: =IFERROR(VLOOKUP(A30,Entradas_calculos!$E$3:$F$32,2,FALSE),0) | C30: =Entradas_calculos!$K$3 -> 4000 | D30: =IFERROR(B30*C30,0) -> 0 | E30: =IFERROR(VLOOKUP(A30,Entradas_calculos!$B$3:$C$32,2,FALSE),0) | F30: =+IF(AND(A30<=Amortización!$B$3,A30-Amortización!$B$4>0),IFERROR(VLOOKUP(A30,Amortización!$A$8:$B$32,2,FALSE),0),0) -> 0 | G30: =IFERROR(D30-E30-F30,0) -> 0 | H30: =IF(A30<Entradas_calculos!$K$2,"",A30-Entradas_calculos!$K$2+1) -> 24 | I30: =Entradas_calculos!$K$4 -> 0.084623421 | J30: =IF(H30="","",(1+I30)^H30) -> 7.0257951 | K30: =IF(J30="",0,G30/J30) -> 0 | L30: =+NPV(Entradas_calculos!$K$4,Calculo_etapa_productiva!G30:G52) -> 0
A31: 30 | B31: =IFERROR(VLOOKUP(A31,Entradas_calculos!$E$3:$F$32,2,FALSE),0) | C31: =Entradas_calculos!$K$3 -> 4000 | D31: =IFERROR(B31*C31,0) -> 0 | E31: =IFERROR(VLOOKUP(A31,Entradas_calculos!$B$3:$C$32,2,FALSE),0) -> 0 | F31: =+IF(AND(A31<=Amortización!$B$3,A31-Amortización!$B$4>0),IFERROR(VLOOKUP(A31,Amortización!$A$8:$B$32,2,FALSE),0),0) -> 0 | G31: =IFERROR(D31-E31-F31,0) -> 0 | H31: =IF(A31<Entradas_calculos!$K$2,"",A31-Entradas_calculos!$K$2+1) -> 25 | I31: =Entradas_calculos!$K$4 -> 0.084623421 | J31: =IF(H31="","",(1+I31)^H31) -> 7.6203419 | K31: =IF(J31="",0,G31/J31) -> 0 | L31: =+NPV(Entradas_calculos!$K$4,Calculo_etapa_productiva!G31:G53) -> 0
J34: Total VP | K34: =SUM(K2:K31) -> 33764877

Sheet escenario de negociación
A1: HERRAMIENTA DE NEGOCIACIÓN — AVALÚO DE CULTIVO (Res. 620/2008)
A2: Azul = editable | C2: Negro = calculado | E2: Verde = desde otra hoja | G2: Rojo = resultado final
A4: PARÁMETROS DEL AVALÚO (se actualizan automáticamente desde el Formulario)
A5: Parámetro | C5: Valor | E5: Parámetro | G5: Valor
A6: Cultivo | C6: =Entradas_calculos!A1 -> Plátano Domínico hartón | E6: Precio de venta (COP/kg) | G6: =Entradas_calculos!K3 -> 4000
A7: Edad actual (años) | C7: =Entradas_calculos!K2 -> 6 | E7: Tasa activa (método elegido) | G7: =Entradas_calculos!K4 -> 0.084623421
A8: Método tasa activa | C8: =Entradas_Tasas!C57 -> Finagro | E8: VPN remanente (tasa activa) | G8: =INDEX(Calculo_etapa_productiva!$L$2:$L$31,Entradas_calculos!$K$2) -> 33764877
A10: VNA FUTURO — Producción remanente a distintas tasas de descuento
A11: Tasa | C11: Descripción | F11: VNA ($/ha) | G11: Diferencia vs. Vendedor
A12: =Entradas_Tasas!C52 -> 0.13799981 | C12: DTF + Prima — Escenario base vendedor (Res. 620) | F12: =IFERROR(NPV(Entradas_Tasas!C52,OFFSET(Calculo_etapa_productiva!G1,Entradas_calculos!$K$2-1,0,32-Entradas_calculos!$K$2,1)),0) -> 64660957 | G12: —
A13: =Entradas_Tasas!C53 -> 0.12854972 | C13: CAPM — Técnico | F13: =IFERROR(NPV(Entradas_Tasas!C53,OFFSET(Calculo_etapa_productiva!G1,Entradas_calculos!$K$2-1,0,32-Entradas_calculos!$K$2,1)),0) -> 65441185 | G13: =F13-F12 -> 780228
A14: =Entradas_Tasas!C54 -> 0.084623421 | C14: Finagro — Referencia mínima agropecuaria | F14: =IFERROR(NPV(Entradas_Tasas!C54,OFFSET(Calculo_etapa_productiva!G1,Entradas_calculos!$K$2-1,0,32-Entradas_calculos!$K$2,1)),0) -> 69303181 | G14: =F14-F12 -> 4642224.7
A15: =Entradas_Tasas!C55 -> 0.11641656 | C15: WACC — Si hay deuda en el proyecto | F15: =IFERROR(NPV(Entradas_Tasas!C55,OFFSET(Calculo_etapa_productiva!G1,Entradas_calculos!$K$2-1,0,32-Entradas_calculos!$K$2,1)),0) -> 66468292 | G15: =F15-F12 -> 1807335.7
A16: =Entradas_Tasas!F57 -> 0.084623421 | C16: Tasa activa seleccionada (método elegido) | F16: =IFERROR(NPV(Entradas_Tasas!F57,OFFSET(Calculo_etapa_productiva!G1,Entradas_calculos!$K$2-1,0,32-Entradas_calculos!$K$2,1)),0) -> 69303181 | G16: =F16-F12 -> 4642224.7
A17: 0.18 | C17: Tasa comprador exigida (18%) | F17: =IFERROR(NPV(0.18,OFFSET(Calculo_etapa_productiva!G1,Entradas_calculos!$K$2-1,0,32-Entradas_calculos!$K$2,1)),0) -> 61388745 | G17: =F17-F12 -> -3272211.4
A18: 0.2 | C18: Tasa comprador agresiva (20%) | F18: =IFERROR(NPV(0.2,OFFSET(Calculo_etapa_productiva!G1,Entradas_calculos!$K$2-1,0,32-Entradas_calculos!$K$2,1)),0) -> 59934547 | G18: =F18-F12 -> -4726409.1
A20: COSTO DE REPOSICIÓN CAPITALIZADO — ¿Cuánto le costó construir este cultivo en la etapa vegetativa?
A21: Concepto | D21: Valor ($/ha) | F21: Interpretación
A22: Posición neta capitalizada (flujos años 1 a edad actual) | D22: =calculo_etapa_vegetativa!F33 -> 1.3199313e+08 | F22: POSITIVO = el vendedor ya recuperó su inversión + intereses. Cualquier precio es utilidad adicional para él.
A24: Rangos de negociación
A25: Escenario | C25: Valor ($/ha) | D25: Tasa Base | E25: Argumento de negociación
A26: TECHO — Precio vendedor | C26: =F12 -> 64660957 | D26: =Entradas_Tasas!C52 -> 0.13799981 | E26: Escenario ideal vendedor. Solo si condición fitosanitaria perfecta y precio sostenido.
A27: REFERENCIA — Finagro | C27: =F14 -> 69303181 | D27: =Entradas_Tasas!C54 -> 0.084623421 | E27: Valor técnico con tasa de fomento. Punto de equilibrio en negociación formal ante perito.
A28: OFERTA RECOMENDADA | C28: =F17 -> 61388745 | D28: 0.18 | E28: Oferta justa. Comprador exige rentabilidad privada. Argumentar riesgo climático y precio volátil.
A29: OFERTA AGRESIVA (apertura) | C29: =F18 -> 59934547 | D29: 0.2 | E29: Primera oferta. Argumentar: riesgo futuro, costo de erradicación, precio variable del mercado.
A30: PISO — Costo reposición | C30: =D22 -> 1.3199313e+08 | D30: — | E30: No vender por menos. Es lo que costó construir el cultivo con intereses capitalizados.
A32: ARGUMENTOS NEGOCIADORES
A33: ARGUMENTO TÉCNICO: | C33: ="Con tasa bancaria privada (18-20%) el VNA cae a "&TEXT(C28,"$#;##0")&"-"&TEXT(C29,"$#;##0")&". El precio debe reflejar el costo real del capital privado (Res. 620/2008)." -> Con tasa bancaria privada (18-20%) el VNA cae a $61388745-$59934547. El precio debe reflejar el costo real del capital privado (Res. 620/2008).
A34: CONEXIÓN AUTOMÁTICA: | C34: "Este tablero se actualiza solo: cambie el cultivo o edad en el Formulario, o el método de tasa en Entradas_Tasas, y todos los valores se recalculan."

Sheet Precio_Final_Cultivo
A1: PRECIO FINAL DEL CULTIVO — 3 ESCENARIOS (Valor por hectárea y por planta)
A2: Azul = input editable | Negro = fórmula | Verde = enlace a otra hoja | Amarillo = celda clave
A4: 1. PARÁMETROS DEL CULTIVO
A5: Parámetro | B5: Valor | C5: Nota
A6: Cultivo | B6: =Entradas_calculos!A1 -> Plátano Domínico hartón
A7: Edad actual (años) | B7: =Entradas_calculos!K2 -> 6
A8: Densidad de siembra (plantas/ha) | B8: =IFERROR(INDEX(Caracteristicas_agronomicas!J:J,MATCH(Entradas_calculos!$A$1,Caracteristicas_agronomicas!C:C,0)),IFERROR(INDEX(Caracteristicas_agronomicas!J:J,MATCH("*"&LEFT(Entradas_calculos!$A$1,FIND(" ",Entradas_calculos!$A$1&" ")-1)&"*",Caracteristicas_agronomicas!C:C,0)),0)) -> 1316
A9: Precio venta producto (COP/kg) | B9: =Entradas_calculos!K3 -> 4000
A10: Tasa de descuento base (Finagro) | B10: =Entradas_Tasas!C54 -> 0.084623421
A11: Condición fitosanitaria → Factor castigo rendimiento | B11: =IFERROR(TRIM(Formulario!F22) & " (factor = " & TEXT(Formulario!B24,"0,00") & ")",Formulario!F22) -> BUENO (factor = 0,95) | C11: Bueno=0,95 / Aceptable=0,70/Regular=0,475/Malo=0,20
A12: 2. VALOR POR ETAPA (por hectárea y por planta)
A13: Etapa | B13: Valor por hectárea ($/ha) | C13: Valor por planta ($/planta) | D13: Descripción
A14: Etapa VEGETATIVA (costo de reposición capitalizado) | B14: =calculo_etapa_vegetativa!F33 -> 1.3199313e+08 | C14: =IFERROR(B14/$B$8,0) -> 100298.73 | D14: Suma de inversiones año 1 → edad actual, llevadas a valor futuro (intereses capitalizados).
A15: Etapa PRODUCTIVA (VPN remanente — tasa Finagro) | B15: =SUM(Calculo_etapa_productiva!K2:K31) -> 33764877 | C15: =IFERROR(B15/$B$8,0) -> 25657.201 | D15: Valor presente de los flujos netos futuros (ingresos – costos) desde la edad actual hasta el fin del ciclo.

Sheet Grafico_Flujos
A1: FLUJOS DE CAJA REMANENTES etapa productiva
A2: Cultivo: | B2: =Precio_Final_Cultivo!B6 -> Plátano Domínico hartón
A3: Edad actual (años): | B3: =Entradas_calculos!K2 -> 6
A4: Tasa de descuento: | B4: =Entradas_calculos!K4 -> 0.084623421
A6: Año remanente | B6: Flujo Neto ($/ha) | C6: Flujo Descontado ($/ha) | D6: RENTAS/AÑO | E6: METODO 1 VALOR DEL CULTIVO | F6: % de participacion del VP
A7: 1 | B7: =IFERROR(IF(Calculo_etapa_productiva!H5="","",Calculo_etapa_productiva!G5),"") | C7: =IFERROR(IF(Calculo_etapa_productiva!H5="","",Calculo_etapa_productiva!K5),"") | D7: =SUM(C7:C23) -> 33764877 | E7: =D7/A23 -> 1986169.2 | F7: =E7*100/D7 -> 5.8823529
A8: 2 | B8: =IFERROR(IF(Calculo_etapa_productiva!H6="","",Calculo_etapa_productiva!G6),"") | C8: =IFERROR(IF(Calculo_etapa_productiva!H6="","",Calculo_etapa_productiva!K6),"") | D8: =SUM(C8:C23) -> 33764877 | E8: =D8/A22 -> 2110304.8 | F8: =E8*100/D8 -> 6.25
A9: 3 | B9: =IFERROR(IF(Calculo_etapa_productiva!H7="","",Calculo_etapa_productiva!G7),"") -> 36622176 | C9: =IFERROR(IF(Calculo_etapa_productiva!H7="","",Calculo_etapa_productiva!K7),"") -> 33764877 | D9: =SUM(C9:C23) -> 33764877 | E9: =D9/A21 -> 2250991.8 | F9: =E9*100/D9 -> 6.6666667
A10: 4 | B10: =IFERROR(IF(Calculo_etapa_productiva!H8="","",Calculo_etapa_productiva!G8),"") -> 0 | C10: =IFERROR(IF(Calculo_etapa_productiva!H8="","",Calculo_etapa_productiva!K8),"") -> 0 | D10: =SUM(C10:C23) -> 0 | E10: =D10/A20 -> 0 | F10: =E10*100/D10 -> #DIV/0!
A11: 5 | B11: =IFERROR(IF(Calculo_etapa_productiva!H9="","",Calculo_etapa_productiva!G9),"") -> 0 | C11: =IFERROR(IF(Calculo_etapa_productiva!H9="","",Calculo_etapa_productiva!K9),"") -> 0 | D11: =SUM(C11:C23) -> 0 | E11: =D11/A19 -> 0 | F11: =E11*100/D11 -> #DIV/0!
A12: 6 | B12: =IFERROR(IF(Calculo_etapa_productiva!H10="","",Calculo_etapa_productiva!G10),"") -> 0 | C12: =IFERROR(IF(Calculo_etapa_productiva!H10="","",Calculo_etapa_productiva!K10),"") -> 0 | D12: =SUM(C12:C23) -> 0 | E12: =D12/A18 -> 0 | F12: =E12*100/D12 -> #DIV/0!
A13: 7 | B13: =IFERROR(IF(Calculo_etapa_productiva!H11="","",Calculo_etapa_productiva!G11),"") -> 0 | C13: =IFERROR(IF(Calculo_etapa_productiva!H11="","",Calculo_etapa_productiva!K11),"") -> 0 | D13: =SUM(C13:C23) -> 0 | E13: =D13/A17 -> 0 | F13: =E13*100/D13 -> #DIV/0!
A14: 8 | B14: =IFERROR(IF(Calculo_etapa_productiva!H12="","",Calculo_etapa_productiva!G12),"") -> 0 | C14: =IFERROR(IF(Calculo_etapa_productiva!H12="","",Calculo_etapa_productiva!K12),"") -> 0 | D14: =SUM(C14:C23) -> 0 | E14: =D14/A16 -> 0 | F14: =E14*100/D14 -> #DIV/0!
A15: 9 | B15: =IFERROR(IF(Calculo_etapa_productiva!H13="","",Calculo_etapa_productiva!G13),"") -> 0 | C15: =IFERROR(IF(Calculo_etapa_productiva!H13="","",Calculo_etapa_productiva!K13),"") -> 0 | D15: =SUM(C15:C23) -> 0 | E15: =D15/A15 -> 0 | F15: =E15*100/D15 -> #DIV/0!
A16: 10 | B16: =IFERROR(IF(Calculo_etapa_productiva!H14="","",Calculo_etapa_productiva!G14),"") -> 0 | C16: =IFERROR(IF(Calculo_etapa_productiva!H14="","",Calculo_etapa_productiva!K14),"") -> 0 | D16: =SUM(C16:C23) -> 0 | E16: =D16/A14 -> 0 | F16: =E16*100/D16 -> #DIV/0!
A17: 11 | B17: =IFERROR(IF(Calculo_etapa_productiva!H15="","",Calculo_etapa_productiva!G15),"") -> 0 | C17: =IFERROR(IF(Calculo_etapa_productiva!H15="","",Calculo_etapa_productiva!K15),"") -> 0 | D17: =SUM(C17:C23) -> 0 | E17: =D17/A13 -> 0 | F17: =E17*100/D17 -> #DIV/0!
A18: 12 | B18: =IFERROR(IF(Calculo_etapa_productiva!H16="","",Calculo_etapa_productiva!G16),"") -> 0 | C18: =IFERROR(IF(Calculo_etapa_productiva!H16="","",Calculo_etapa_productiva!K16),"") -> 0 | D18: =SUM(C18:C23) -> 0 | E18: =D18/A12 -> 0 | F18: =E18*100/D18 -> #DIV/0!
A19: 13 | B19: =IFERROR(IF(Calculo_etapa_productiva!H17="","",Calculo_etapa_productiva!G17),"") -> 0 | C19: =IFERROR(IF(Calculo_etapa_productiva!H17="","",Calculo_etapa_productiva!K17),"") -> 0 | D19: =SUM(C19:C23) -> 0 | E19: =D19/A11 -> 0 | F19: =E19*100/D19 -> #DIV/0!
A20: 14 | B20: =IFERROR(IF(Calculo_etapa_productiva!H18="","",Calculo_etapa_productiva!G18),"") -> 0 | C20: =IFERROR(IF(Calculo_etapa_productiva!H18="","",Calculo_etapa_productiva!K18),"") -> 0 | D20: =SUM(C20:C23) -> 0 | E20: =D20/A10 -> 0 | F20: =E20*100/D20 -> #DIV/0!
A21: 15 | B21: =IFERROR(IF(Calculo_etapa_productiva!H19="","",Calculo_etapa_productiva!G19),"") -> 0 | C21: =IFERROR(IF(Calculo_etapa_productiva!H19="","",Calculo_etapa_productiva!K19),"") -> 0 | D21: =SUM(C21:C23) -> 0 | E21: =D21/A9 -> 0 | F21: =E21*100/D21 -> #DIV/0!
A22: 16 | B22: =IFERROR(IF(Calculo_etapa_productiva!H20="","",Calculo_etapa_productiva!G20),"") -> 0 | C22: =IFERROR(IF(Calculo_etapa_productiva!H20="","",Calculo_etapa_productiva!K20),"") -> 0 | D22: =SUM(C22:C23) -> 0 | E22: =D22/A8 -> 0 | F22: =E22*100/D22 -> #DIV/0!
A23: 17 | B23: =IFERROR(IF(Calculo_etapa_productiva!H21="","",Calculo_etapa_productiva!G21),"") -> 0 | C23: =IFERROR(IF(Calculo_etapa_productiva!H21="","",Calculo_etapa_productiva!K21),"") -> 0 | D23: =SUM(C23:C23) -> 0 | E23: =D23/A7 -> 0 | F23: =E23*100/D23 -> #DIV/0!
B24: =IFERROR(IF(Calculo_etapa_productiva!H22="","",Calculo_etapa_productiva!G22),"") -> 0 | C24: =IFERROR(IF(Calculo_etapa_productiva!H22="","",Calculo_etapa_productiva!K22),"") -> 0
B25: =IFERROR(IF(Calculo_etapa_productiva!H23="","",Calculo_etapa_productiva!G23),"") -> 0 | C25: =IFERROR(IF(Calculo_etapa_productiva!H23="","",Calculo_etapa_productiva!K23),"") -> 0
B26: =IFERROR(IF(Calculo_etapa_productiva!H24="","",Calculo_etapa_productiva!G24),"") -> 0 | C26: =IFERROR(IF(Calculo_etapa_productiva!H24="","",Calculo_etapa_productiva!K24),"") -> 0
B27: =IFERROR(IF(Calculo_etapa_productiva!H25="","",Calculo_etapa_productiva!G25),"") -> 0 | C27: =IFERROR(IF(Calculo_etapa_productiva!H25="","",Calculo_etapa_productiva!K25),"") -> 0
B28: =IFERROR(IF(Calculo_etapa_productiva!H26="","",Calculo_etapa_productiva!G26),"") -> 0 | C28: =IFERROR(IF(Calculo_etapa_productiva!H26="","",Calculo_etapa_productiva!K26),"") -> 0
B29: =IFERROR(IF(Calculo_etapa_productiva!H27="","",Calculo_etapa_productiva!G27),"") -> 0 | C29: =IFERROR(IF(Calculo_etapa_productiva!H27="","",Calculo_etapa_productiva!K27),"") -> 0
B30: =IFERROR(IF(Calculo_etapa_productiva!H28="","",Calculo_etapa_productiva!G28),"") -> 0 | C30: =IFERROR(IF(Calculo_etapa_productiva!H28="","",Calculo_etapa_productiva!K28),"") -> 0
B31: =IFERROR(IF(Calculo_etapa_productiva!H29="","",Calculo_etapa_productiva!G29),"") -> 0 | C31: =IFERROR(IF(Calculo_etapa_productiva!H29="","",Calculo_etapa_productiva!K29),"") -> 0
B32: =IFERROR(IF(Calculo_etapa_productiva!H30="","",Calculo_etapa_productiva!G30),"") -> 0 | C32: =IFERROR(IF(Calculo_etapa_productiva!H30="","",Calculo_etapa_productiva!K30),"") -> 0
B33: =IFERROR(IF(Calculo_etapa_productiva!H31="","",Calculo_etapa_productiva!G31),"") -> 0 | C33: =IFERROR(IF(Calculo_etapa_productiva!H31="","",Calculo_etapa_productiva!K31),"") -> 0
C34: =SUM(C7:C33) -> 33764877
A35: RESUMEN — Valor Presente Distribuido | F35: año 1
A36: Indicador | B36: Valor | C36: Fórmula / Interpretación
A37: Valor Presente Total ($/ha) | B37: =C34 -> 33764877 | C37: Sumatoria de flujos descontados
A38: Años remanentes productivos | B38: =COUNTIF(C7:C33,">0") -> 1 | C38: Número de años con flujo productivo > 0
A39: VP / N años (promedio simple) | B39: =IFERROR(B37/B38,0) -> 33764877 | C39: VP dividido equitativamente entre los años remanentes
A40: Anualidad equivalente (PMT con tasa) | B40: =IFERROR(-PMT(B4,B38,B37),0) -> 36622176 | C40: Flujo anual constante que generaría el mismo VP (descuenta a la tasa)

Sheet PreciosRef. por Mercado
A1: Grupo | B1: Producto | C1: Mercado | D1: N Obs | E1: Precio Ref. ($/kg) | F1: Promedio ($/kg) | G1: Mediana ($/kg) | H1: Mínimo ($/kg) | I1: Máximo ($/kg) | J1: P25 ($/kg) | K1: P75 ($/kg) | L1: Desv. Estándar | M1: CV (%) | N1: Precio de Referencia Ajustado ($/kg) | O1: DIFERENCIA
A2: FRUTAS | B2: Aguacate Hass | C2: Bogotá, D.C., Corabastos | D2: 24 | E2: 7269.5 | F2: 7231.2 | G2: 7269.5 | H2: 5391 | I2: 10096 | J2: 6164.2 | K2: 7743.8 | L2: 1276.8 | M2: 17.7 | N2: =IF(M2<=20,G2,IF(M2<=35,F2,(J2+K2)/2)) -> 7269.5 | O2: =(N2-E2)/E2 -> 0
A3: FRUTAS | B3: Aguacate Hass | C3: Chiquinquirá (Boyacá) | D3: 24 | E3: 5648 | F3: 5676.2 | G3: 5648 | H3: 4352 | I3: 8583 | J3: 4801.8 | K3: 6161.5 | L3: 1101.6 | M3: 19.4 | N3: =IF(M3<=20,G3,IF(M3<=35,F3,(J3+K3)/2)) -> 5648 | O3: =(N3-E3)/E3 -> 0 | Q3: El valor de la columna Precio de Referencia Ajustado representa un precio más confiable del mercado, ya que reduce el efecto de valores atípicos y la volatilidad. Su cálculo se adapta según el coeficiente de variación (CV): cuando el CV ≤ 20% se utiliza la mediana por su estabilidad; cuando el CV está entre 20% y 35% se emplea el promedio; y cuando el CV > 35% se calcula como el promedio entre los percentiles 25 y 75, enfocándose en el rango central de los datos. De esta forma, se obtiene un precio más representativo y consistente para el análisis.
A4: FRUTAS | B4: Aguacate Hass | C4: Duitama (Boyacá), Mercaplaza | D4: 17 | E4: 6083 | F4: 6026.6 | G4: 6083 | H4: 4550 | I4: 7722 | J4: 5167 | K4: 6472 | L4: 985.6 | M4: 16.4 | N4: =IF(M4<=20,G4,IF(M4<=35,F4,(J4+K4)/2)) -> 6083 | O4: =(N4-E4)/E4 -> 0
A5: FRUTAS | B5: Aguacate Hass | C5: La Ceja (Antioquia) | D5: 24 | E5: 3897.5 | F5: 3936.8 | G5: 3897.5 | H5: 2690 | I5: 5420 | J5: 3357.2 | K5: 4298.2 | L5: 823.1 | M5: 20.9 | N5: =IF(M5<=20,G5,IF(M5<=35,F5,(J5+K5)/2)) -> 3936.8 | O5: =(N5-E5)/E5 -> 0.010083387
A6: FRUTAS | B6: Aguacate Hass | C6: Medellín, Central Mayorista de Antioquia | D6: 24 | E6: 4594.5 | F6: 4617.5 | G6: 4594.5 | H6: 3160 | I6: 6513 | J6: 3947.2 | K6: 5127.5 | L6: 890.1 | M6: 19.3 | N6: =IF(M6<=20,G6,IF(M6<=35,F6,(J6+K6)/2)) -> 4594.5 | O6: =(N6-E6)/E6 -> 0
A7: FRUTAS | B7: Aguacate Hass | C7: Rionegro (Antioquia) | D7: 24 | E7: 3915.5 | F7: 4052.4 | G7: 3915.5 | H7: 2656 | I7: 5764 | J7: 3343 | K7: 4705.2 | L7: 925.3 | M7: 22.8 | N7: =IF(M7<=20,G7,IF(M7<=35,F7,(J7+K7)/2)) -> 4052.4 | O7: =(N7-E7)/E7 -> 0.034963606
A8: FRUTAS | B8: Aguacate Hass | C8: San Gil (Santander) | D8: 23 | E8: 6726 | F8: 6960.6 | G8: 6726 | H8: 5750 | I8: 9203 | J8: 6000 | K8: 7926.5 | L8: 1141.5 | M8: 16.4 | N8: =IF(M8<=20,G8,IF(M8<=35,F8,(J8+K8)/2)) -> 6726 | O8: =(N8-E8)/E8 -> 0
A9: FRUTAS | B9: Aguacate Hass | C9: San Vicente (Antioquia) | D9: 10 | E9: 3237.5 | F9: 3405.6 | G9: 3237.5 | H9: 2463 | I9: 4825 | J9: 2617.5 | K9: 4016.2 | L9: 868.9 | M9: 25.5 | N9: =IF(M9<=20,G9,IF(M9<=35,F9,(J9+K9)/2)) -> 3405.6 | O9: =(N9-E9)/E9 -> 0.05192278
A10: FRUTAS | B10: Aguacate Hass | C10: San Vicente Ferrer (Antioquia) | D10: 14 | E10: 4116.5 | F10: 4282.1 | G10: 4116.5 | H10: 2860 | I10: 6030 | J10: 3671 | K10: 4856 | L10: 872.9 | M10: 20.4 | N10: =IF(M10<=20,G10,IF(M10<=35,F10,(J10+K10)/2)) -> 4282.1 | O10: =(N10-E10)/E10 -> 0.040228349
A11: FRUTAS | B11: Aguacate Hass | C11: Sonsón (Antioquia) | D11: 24 | E11: 4020 | F11: 4012.5 | G11: 4020 | H11: 2813 | I11: 5513 | J11: 3564 | K11: 4510.5 | L11: 707 | M11: 17.6 | N11: =IF(M11<=20,G11,IF(M11<=35,F11,(J11+K11)/2)) -> 4020 | O11: =(N11-E11)/E11 -> 0
A12: FRUTAS | B12: Aguacate Hass | C12: Tibasosa (Boyacá), Coomproriente | D12: 24 | E12: 6186 | F12: 6505.8 | G12: 6186 | H12: 4758 | I12: 8953 | J12: 5350.2 | K12: 7677.5 | L12: 1320.9 | M12: 20.3 | N12: =IF(M12<=20,G12,IF(M12<=35,F12,(J12+K12)/2)) -> 6505.8 | O12: =(N12-E12)/E12 -> 0.051697381
A13: FRUTAS | B13: Aguacate Hass | C13: Tunja, Complejo de Servicios del Sur | D13: 24 | E13: 5375 | F13: 5344.5 | G13: 5375 | H13: 4078 | I13: 6769 | J13: 4653.8 | K13: 5912.2 | L13: 821.8 | M13: 15.4 | N13: =IF(M13<=20,G13,IF(M13<=35,F13,(J13+K13)/2)) -> 5375 | O13: =(N13-E13)/E13 -> 0
A14: FRUTAS | B14: Limón Tahití | C14: Armenia, Mercar | D14: 24 | E14: 1872.5 | F14: 2286.8 | G14: 1872.5 | H14: 1053 | I14: 5678 | J14: 1257.2 | K14: 2767.8 | L14: 1316.5 | M14: 57.6 | N14: =IF(M14<=20,G14,IF(M14<=35,F14,(J14+K14)/2)) -> 2012.5 | O14: =(N14-E14)/E14 -> 0.074766355
A15: FRUTAS | B15: Limón Tahití | C15: Barranquilla, Barranquillita | D15: 24 | E15: 2190 | F15: 2576.5 | G15: 2190 | H15: 989 | I15: 5846 | J15: 1749 | K15: 3242 | L15: 1278.2 | M15: 49.6 | N15: =IF(M15<=20,G15,IF(M15<=35,F15,(J15+K15)/2)) -> 2495.5 | O15: =(N15-E15)/E15 -> 0.13949772
... A58: FRUTAS | B58: Limón común | C58: Ibagué, Plaza La 21 | D58: 24 | E58: 1868.5 | F58: 2117.1 | G58: 1868.5 | H58: 877 | I58: 4656 | J58: 1400.5 | K58: 2513.5 | L58: 1055.6 | M58: 49.9 | N58: =IF(M58<=20,G58,IF(M58<=35,F58,(J58+K58)/2)) -> 1957 | O58: =(N58-E58)/E58 -> 0.047364196
A59: FRUTAS | B59: Limón común | C59: La Unión (Nariño) | D59: 1 | E59: 2508 | F59: 2508 | G59: 2508 | H59: 2508 | I59: 2508 | J59: 2508 | K59: 2508 | N59: =IF(M59<=20,G59,IF(M59<=35,F59,(J59+K59)/2)) -> 2508 | O59: =(N59-E59)/E59 -> 0
A60: FRUTAS | B60: Limón común | C60: Medellín, Central Mayorista de Antioquia | D60: 23 | E60: 2055 | F60: 2051 | G60: 2055 | H60: 1167 | I60: 3651 | J60: 1476.5 | K60: 2427 | L60: 693.3 | M60: 33.8 | N60: =IF(M60<=20,G60,IF(M60<=35,F60,(J60+K60)/2)) -> 2051 | O60: =(N60-E60)/E60 -> -0.001946472
A61: FRUTAS | B61: Limón común | C61: Medellín, Plaza Minorista "José María Villa" | D61: 24 | E61: 2272 | F61: 2342.9 | G61: 2272 | H61: 1643 | I61: 3681 | J61: 1838.8 | K61: 2711 | L61: 551.6 | M61: 23.5 | N61: =IF(M61<=20,G61,IF(M61<=35,F61,(J61+K61)/2)) -> 2342.9 | O61: =(N61-E61)/E61 -> 0.031205986
A62: FRUTAS | B62: Limón común | C62: Montería, Mercado del Sur | D62: 24 | E62: 1999.5 | F62: 2212.5 | G62: 1999.5 | H62: 1266 | I62: 4214 | J62: 1705.2 | K62: 2677.2 | L62: 713.5 | M62: 32.2 | N62: =IF(M62<=20,G62,IF(M62<=35,F62,(J62+K62)/2)) -> 2212.5 | O62: =(N62-E62)/E62 -> 0.10652663
A63: FRUTAS | B63: Limón común | C63: Neiva, Surabastos | D63: 24 | E63: 1855.5 | F63: 2046 | G63: 1855.5 | H63: 939 | I63: 4385 | J63: 1316 | K63: 2342.5 | L63: 970.3 | M63: 47.4 | N63: =IF(M63<=20,G63,IF(M63<=35,F63,(J63+K63)/2)) -> 1829.25 | O63: =(N63-E63)/E63 -> -0.01414713
A64: FRUTAS | B64: Limón común | C64: Pamplona (Norte de Santander) | D64: 24 | E64: 4014.5 | F64: 4320.2 | G64: 4014.5 | H64: 2893 | I64: 6192 | J64: 3828 | K64: 5054 | L64: 949.7 | M64: 22 | N64: =IF(M64<=20,G64,IF(M64<=35,F64,(J64+K64)/2)) -> 4320.2 | O64: =(N64-E64)/E64 -> 0.07614896
A65: FRUTAS | B65: Limón común | C65: Pereira, La 41 | D65: 24 | E65: 3014.5 | F65: 3169.8 | G65: 3014.5 | H65: 2094 | I65: 4698 | J65: 2586.5 | K65: 3632.5 | L65: 754.6 | M65: 23.8 | N65: =IF(M65<=20,G65,IF(M65<=35,F65,(J65+K65)/2)) -> 3169.8 | O65: =(N65-E65)/E65 -> 0.051517665
A66: FRUTAS | B66: Limón común | C66: Pereira, Mercasa | D66: 24 | E66: 2973 | F66: 3163.5 | G66: 2973 | H66: 1845 | I66: 5123 | J66: 2572.5 | K66: 3671.8 | L66: 897.7 | M66: 28.4 | N66: =IF(M66<=20,G66,IF(M66<=35,F66,(J66+K66)/2)) -> 3163.5 | O66: =(N66-E66)/E66 -> 0.06407669
A67: FRUTAS | B67: Limón común | C67: San Gil (Santander) | D67: 24 | E67: 2148.5 | F67: 2446.8 | G67: 2148.5 | H67: 871 | I67: 4600 | J67: 1822.8 | K67: 3332.2 | L67: 1026.4 | M67: 41.9 | N67: =IF(M67<=20,G67,IF(M67<=35,F67,(J67+K67)/2)) -> 2577.5 | O67: =(N67-E67)/E67 -> 0.19967419
A68: FRUTAS | B68: Limón común | C68: Sincelejo, Nuevo Mercado | D68: 24 | E68: 2281 | F68: 2336.6 | G68: 2281 | H68: 1321 | I68: 4046 | J68: 1822.2 | K68: 2644.5 | L68: 685.7 | M68: 29.3 | N68: =IF(M68<=20,G68,IF(M68<=35,F68,(J68+K68)/2)) -> 2336.6 | O68: =(N68-E68)/E68 -> 0.024375274
A69: FRUTAS | B69: Limón común | C69: Socorro (Santander) | D69: 24 | E69: 2475 | F69: 2553.9 | G69: 2475 | H69: 757 | I69: 4700 | J69: 1806.8 | K69: 3393.5 | L69: 1100 | M69: 43.1 | N69: =IF(M69<=20,G69,IF(M69<=35,F69,(J69+K69)/2)) -> 2600.15 | O69: =(N69-E69)/E69 -> 0.050565657
A70: FRUTAS | B70: Limón común | C70: Valledupar, Mercabastos | D70: 24 | E70: 2804 | F70: 3153.3 | G70: 2804 | H70: 1945 | I70: 4904 | J70: 2425.2 | K70: 3938.8 | L70: 929.7 | M70: 29.5 | N70: =IF(M70<=20,G70,IF(M70<=35,F70,(J70+K70)/2)) -> 3153.3 | O70: =(N70-E70)/E70 -> 0.12457204
A71: FRUTAS | B71: Limón común | C71: Valledupar, Mercado Nuevo | D71: 24 | E71: 2233.5 | F71: 2461.5 | G71: 2233.5 | H71: 1494 | I71: 4140 | J71: 1827.8 | K71: 3070 | L71: 773 | M71: 31.4 | N71: =IF(M71<=20,G71,IF(M71<=35,F71,(J71+K71)/2)) -> 2461.5 | O71: =(N71-E71)/E71 -> 0.10208193
... A191: TUBERCULOS, RAICES Y PLATANOS | B191: Plátano dominico verde | C191: Sonsón (Antioquia) | D191: 12 | E191: 1670 | F191: 1599.2 | G191: 1670 | H191: 1056 | I191: 2200 | J191: 1278.5 | K191: 1816.8 | L191: 363 | M191: 22.7 | N191: =IF(M191<=20,G191,IF(M191<=35,F191,(J191+K191)/2)) -> 1599.2 | O191: =(N191-E191)/E191 -> -0.04239521
B192: Cacao criollo | C192: estandar | D192: 193 | E192: 14765.8 | F192: 17847.3 | G192: 14765.8 | H192: 7789.2 | I192: 38636.7 | J192: 11929.2 | K192: 28234.7 | L192: 8012.4 | M192: 0.449 | N192: =IF(M192<=20,G192,IF(M192<=35,F192,(J192+K192)/2)) -> 14765.8 | O192: =(N192-E192)/E192 -> 0
B193: Palma de aceite | C193: estandar | D193: 60 | E193: 708.05 | F193: 736.08 | G193: 708.05 | H193: 546 | I193: 1065 | J193: 656 | K193: 813 | L193: 126.5 | M193: 0.1719 | N193: =IF(M193<=20,G193,IF(M193<=35,F193,(J193+K193)/2)) -> 708.05 | O193: =(N193-E193)/E193 -> 0

Sheet Tabla_Costos_Insumos
A1: Departamento | B1: Grupo de Insumo | C1: Nombre del Insumo | D1: Presentación | E1: Precio Promedio Final | F1: Fuente del Precio | G1: PRECIO PERITO | H1: REGION | I1: PRECIO NUEVO | J1: PRECIO FINAL | L1: imputación jerárquica por región con anclaje a observaciones departamentales
A2: Antioquia | B2: Bioinsumos | C2: Rutinal | D2: 1 litro | E2: 46378.17 | F2: Nacional (Contingencia) | H2: =IF(OR(A2="Antioquia",A2="Bogotá, D.C.",A2="Boyacá",A2="Cundinamarca",A2="Caldas",A2="Risaralda",A2="Quindío",A2="Tolima",A2="Huila",A2="Santander",A2="Norte de Santander"),"ANDINA", IF(OR(A2="Atlántico",A2="Bolívar",A2="Cesar",A2="Córdoba",A2="Sucre",A2="Magdalena"),"CARIBE", IF(OR(A2="Valle del Cauca",A2="Cauca",A2="Nariño"),"PACIFICO", IF(OR(A2="Meta",A2="Casanare",A2="Arauca"),"ORINOQUIA", "AMAZONIA")))) -> ANDINA | I2: =IF(F2="Departamental",E2, AVERAGEIFS($E:$E,$H:$H,H2,$B:$B,B2,$C:$C,C2)) -> 46393.717 | J2: =IF(G2<>"",G2,I2) -> 46393.717 | L2: El ajuste de precios se realiza a partir de una estructura jerárquica por departamento y región, en la cual los valores clasificados como “Departamental” se mantienen sin modificación al representar observaciones directas del mercado, mientras que los registros identificados como “Nacional (Contingencia)” se recalculan utilizando un valor de referencia construido a nivel regional. Para ello, los departamentos se agrupan en regiones homogéneas (Andina, Caribe, Pacífica, Orinoquía y Amazonía), de modo que el precio final de los casos en contingencia se aproxima al comportamiento observado en su región correspondiente, garantizando coherencia espacial y reduciendo la asignación de valores únicos sin sustento territorial.
A3: Antioquia | B3: Fertilizantes Foliares | C3: Agrimins K Calcio Boro | D3: 1 litro | E3: 22086.61 | F3: Nacional (Contingencia) | H3: =IF(OR(A3="Antioquia",A3="Bogotá, D.C.",A3="Boyacá",A3="Cundinamarca",A3="Caldas",A3="Risaralda",A3="Quindío",A3="Tolima",A3="Huila",A3="Santander",A3="Norte de Santander"),"ANDINA", IF(OR(A3="Atlántico",A3="Bolívar",A3="Cesar",A3="Córdoba",A3="Sucre",A3="Magdalena"),"CARIBE", IF(OR(A3="Valle del Cauca",A3="Cauca",A3="Nariño"),"PACIFICO", IF(OR(A3="Meta",A3="Casanare",A3="Arauca"),"ORINOQUIA", "AMAZONIA")))) -> ANDINA | I3: =IF(F3="Departamental",E3, AVERAGEIFS($E:$E,$H:$H,H3,$B:$B,B3,$C:$C,C3)) -> 22820.238 | J3: =IF(G3<>"",G3,I3) -> 22820.238
A4: Antioquia | B4: Fertilizantes Foliares | C4: Klip - K Calcio-Boro | D4: 1 litro | E4: 21080.63 | F4: Departamental | H4: =IF(OR(A4="Antioquia",A4="Bogotá, D.C.",A4="Boyacá",A4="Cundinamarca",A4="Caldas",A4="Risaralda",A4="Quindío",A4="Tolima",A4="Huila",A4="Santander",A4="Norte de Santander"),"ANDINA", IF(OR(A4="Atlántico",A4="Bolívar",A4="Cesar",A4="Córdoba",A4="Sucre",A4="Magdalena"),"CARIBE", IF(OR(A4="Valle del Cauca",A4="Cauca",A4="Nariño"),"PACIFICO", IF(OR(A4="Meta",A4="Casanare",A4="Arauca"),"ORINOQUIA", "AMAZONIA")))) -> ANDINA | I4: =IF(F4="Departamental",E4, AVERAGEIFS($E:$E,$H:$H,H4,$B:$B,B4,$C:$C,C4)) -> 21080.63 | J4: =IF(G4<>"",G4,I4) -> 21080.63
A5: Antioquia | B5: Fertilizantes Foliares | C5: Nutrifoliar Completo | D5: 1 litro | E5: 28221.84 | F5: Departamental | H5: =IF(OR(A5="Antioquia",A5="Bogotá, D.C.",A5="Boyacá",A5="Cundinamarca",A5="Caldas",A5="Risaralda",A5="Quindío",A5="Tolima",A5="Huila",A5="Santander",A5="Norte de Santander"),"ANDINA", IF(OR(A5="Atlántico",A5="Bolívar",A5="Cesar",A5="Córdoba",A5="Sucre",A5="Magdalena"),"CARIBE", IF(OR(A5="Valle del Cauca",A5="Cauca",A5="Nariño"),"PACIFICO", IF(OR(A5="Meta",A5="Casanare",A5="Arauca"),"ORINOQUIA", "AMAZONIA")))) -> ANDINA | I5: =IF(F5="Departamental",E5, AVERAGEIFS($E:$E,$H:$H,H5,$B:$B,B5,$C:$C,C5)) -> 28221.84 | J5: =IF(G5<>"",G5,I5) -> 28221.84
A6: Antioquia | B6: Fertilizantes Foliares | C6: Wuxal Tapa Negra | D6: 1 litro | E6: 65385.32 | F6: Departamental | H6: =IF(OR(A6="Antioquia",A6="Bogotá, D.C.",A6="Boyacá",A6="Cundinamarca",A6="Caldas",A6="Risaralda",A6="Quindío",A6="Tolima",A6="Huila",A6="Santander",A6="Norte de Santander"),"ANDINA", IF(OR(A6="Atlántico",A6="Bolívar",A6="Cesar",A6="Córdoba",A6="Sucre",A6="Magdalena"),"CARIBE", IF(OR(A6="Valle del Cauca",A6="Cauca",A6="Nariño"),"PACIFICO", IF(OR(A6="Meta",A6="Casanare",A6="Arauca"),"ORINOQUIA", "AMAZONIA")))) -> ANDINA | I6: =IF(F6="Departamental",E6, AVERAGEIFS($E:$E,$H:$H,H6,$B:$B,B6,$C:$C,C6)) -> 65385.32 | J6: =IF(G6<>"",G6,I6) -> 65385.32
A7: Antioquia | B7: Fungicidas | C7: Amistar Top | D7: 1 litro | E7: 238388.71 | F7: Departamental | H7: =IF(OR(A7="Antioquia",A7="Bogotá, D.C.",A7="Boyacá",A7="Cundinamarca",A7="Caldas",A7="Risaralda",A7="Quindío",A7="Tolima",A7="Huila",A7="Santander",A7="Norte de Santander"),"ANDINA", IF(OR(A7="Atlántico",A7="Bolívar",A7="Cesar",A7="Córdoba",A7="Sucre",A7="Magdalena"),"CARIBE", IF(OR(A7="Valle del Cauca",A7="Cauca",A7="Nariño"),"PACIFICO", IF(OR(A7="Meta",A7="Casanare",A7="Arauca"),"ORINOQUIA", "AMAZONIA")))) -> ANDINA | I7: =IF(F7="Departamental",E7, AVERAGEIFS($E:$E,$H:$H,H7,$B:$B,B7,$C:$C,C7)) -> 238388.71 | J7: =IF(G7<>"",G7,I7) -> 238388.71
A8: Antioquia | B8: Fungicidas | C8: Azoxystrobin 250 Sc | D8: 1 litro | E8: 83813.89 | F8: Departamental | H8: =IF(OR(A8="Antioquia",A8="Bogotá, D.C.",A8="Boyacá",A8="Cundinamarca",A8="Caldas",A8="Risaralda",A8="Quindío",A8="Tolima",A8="Huila",A8="Santander",A8="Norte de Santander"),"ANDINA", IF(OR(A8="Atlántico",A8="Bolívar",A8="Cesar",A8="Córdoba",A8="Sucre",A8="Magdalena"),"CARIBE", IF(OR(A8="Valle del Cauca",A8="Cauca",A8="Nariño"),"PACIFICO", IF(OR(A8="Meta",A8="Casanare",A8="Arauca"),"ORINOQUIA", "AMAZONIA")))) -> ANDINA | I8: =IF(F8="Departamental",E8, AVERAGEIFS($E:$E,$H:$H,H8,$B:$B,B8,$C:$C,C8)) -> 83813.89 | J8: =IF(G8<>"",G8,I8) -> 83813.89
A9: Antioquia | B9: Fungicidas | C9: Azuco | D9: 1 litro | E9: 23149.93 | F9: Departamental | H9: =IF(OR(A9="Antioquia",A9="Bogotá, D.C.",A9="Boyacá",A9="Cundinamarca",A9="Caldas",A9="Risaralda",A9="Quindío",A9="Tolima",A9="Huila",A9="Santander",A9="Norte de Santander"),"ANDINA", IF(OR(A9="Atlántico",A9="Bolívar",A9="Cesar",A9="Córdoba",A9="Sucre",A9="Magdalena"),"CARIBE", IF(OR(A9="Valle del Cauca",A9="Cauca",A9="Nariño"),"PACIFICO", IF(OR(A9="Meta",A9="Casanare",A9="Arauca"),"ORINOQUIA", "AMAZONIA")))) -> ANDINA | I9: =IF(F9="Departamental",E9, AVERAGEIFS($E:$E,$H:$H,H9,$B:$B,B9,$C:$C,C9)) -> 23149.93 | J9: =IF(G9<>"",G9,I9) -> 23149.93
A10: Antioquia | B10: Fungicidas | C10: Benomyl 50 Wp | D10: 1 kilogramo | E10: 50900 | F10: Departamental | H10: =IF(OR(A10="Antioquia",A10="Bogotá, D.C.",A10="Boyacá",A10="Cundinamarca",A10="Caldas",A10="Risaralda",A10="Quindío",A10="Tolima",A10="Huila",A10="Santander",A10="Norte de Santander"),"ANDINA", IF(OR(A10="Atlántico",A10="Bolívar",A10="Cesar",A10="Córdoba",A10="Sucre",A10="Magdalena"),"CARIBE", IF(OR(A10="Valle del Cauca",A10="Cauca",A10="Nariño"),"PACIFICO", IF(OR(A10="Meta",A10="Casanare",A10="Arauca"),"ORINOQUIA", "AMAZONIA")))) -> ANDINA | I10: =IF(F10="Departamental",E10, AVERAGEIFS($E:$E,$H:$H,H10,$B:$B,B10,$C:$C,C10)) -> 50900 | J10: =IF(G10<>"",G10,I10) -> 50900
A11: Antioquia | B11: Fungicidas | C11: Carbendazim 500 Sc | D11: 1 litro | E11: 27047.36 | F11: Departamental | H11: =IF(OR(A11="Antioquia",A11="Bogotá, D.C.",A11="Boyacá",A11="Cundinamarca",A11="Caldas",A11="Risaralda",A11="Quindío",A11="Tolima",A11="Huila",A11="Santander",A11="Norte de Santander"),"ANDINA", IF(OR(A11="Atlántico",A11="Bolívar",A11="Cesar",A11="Córdoba",A11="Sucre",A11="Magdalena"),"CARIBE", IF(OR(A11="Valle del Cauca",A11="Cauca",A11="Nariño"),"PACIFICO", IF(OR(A11="Meta",A11="Casanare",A11="Arauca"),"ORINOQUIA", "AMAZONIA")))) -> ANDINA | I11: =IF(F11="Departamental",E11, AVERAGEIFS($E:$E,$H:$H,H11,$B:$B,B11,$C:$C,C11)) -> 27047.36 | J11: =IF(G11<>"",G11,I11) -> 27047.36
A12: Antioquia | B12: Fungicidas | C12: Daconil 720 Sc | D12: 1 litro | E12: 36738.19 | F12: Departamental | H12: =IF(OR(A12="Antioquia",A12="Bogotá, D.C.",A12="Boyacá",A12="Cundinamarca",A12="Caldas",A12="Risaralda",A12="Quindío",A12="Tolima",A12="Huila",A12="Santander",A12="Norte de Santander"),"ANDINA", IF(OR(A12="Atlántico",A12="Bolívar",A12="Cesar",A12="Córdoba",A12="Sucre",A12="Magdalena"),"CARIBE", IF(OR(A12="Valle del Cauca",A12="Cauca",A12="Nariño"),"PACIFICO", IF(OR(A12="Meta",A12="Casanare",A12="Arauca"),"ORINOQUIA", "AMAZONIA")))) -> ANDINA | I12: =IF(F12="Departamental",E12, AVERAGEIFS($E:$E,$H:$H,H12,$B:$B,B12,$C:$C,C12)) -> 36738.19 | J12: =IF(G12<>"",G12,I12) -> 36738.19
A13: Antioquia | B13: Fungicidas | C13: FURTIVO 250 SC | D13: 1 litro | E13: 112220.5 | F13: Departamental | H13: =IF(OR(A13="Antioquia",A13="Bogotá, D.C.",A13="Boyacá",A13="Cundinamarca",A13="Caldas",A13="Risaralda",A13="Quindío",A13="Tolima",A13="Huila",A13="Santander",A13="Norte de Santander"),"ANDINA", IF(OR(A13="Atlántico",A13="Bolívar",A13="Cesar",A13="Córdoba",A13="Sucre",A13="Magdalena"),"CARIBE", IF(OR(A13="Valle del Cauca",A13="Cauca",A13="Nariño"),"PACIFICO", IF(OR(A13="Meta",A13="Casanare",A13="Arauca"),"ORINOQUIA", "AMAZONIA")))) -> ANDINA | I13: =IF(F13="Departamental",E13, AVERAGEIFS($E:$E,$H:$H,H13,$B:$B,B13,$C:$C,C13)) -> 112220.5 | J13: =IF(G13<>"",G13,I13) -> 112220.5
A14: Antioquia | B14: Fungicidas | C14: Mancozeb 80 Wp | D14: 1 kilogramo | E14: 19786.38 | F14: Departamental | H14: =IF(OR(A14="Antioquia",A14="Bogotá, D.C.",A14="Boyacá",A14="Cundinamarca",A14="Caldas",A14="Risaralda",A14="Quindío",A14="Tolima",A14="Huila",A14="Santander",A14="Norte de Santander"),"ANDINA", IF(OR(A14="Atlántico",A14="Bolívar",A14="Cesar",A14="Córdoba",A14="Sucre",A14="Magdalena"),"CARIBE", IF(OR(A14="Valle del Cauca",A14="Cauca",A14="Nariño"),"PACIFICO", IF(OR(A14="Meta",A14="Casanare",A14="Arauca"),"ORINOQUIA", "AMAZONIA")))) -> ANDINA | I14: =IF(F14="Departamental",E14, AVERAGEIFS($E:$E,$H:$H,H14,$B:$B,B14,$C:$C,C14)) -> 19786.38 | J14: =IF(G14<>"",G14,I14) -> 19786.38
... A16: Antioquia | B16: Fungicidas | C16: Nativo Sc | D16: 1 litro | E16: 150429.77 | F16: Departamental | H16: =IF(OR(A16="Antioquia",A16="Bogotá, D.C.",A16="Boyacá",A16="Cundinamarca",A16="Caldas",A16="Risaralda",A16="Quindío",A16="Tolima",A16="Huila",A16="Santander",A16="Norte de Santander"),"ANDINA", IF(OR(A16="Atlántico",A16="Bolívar",A16="Cesar",A16="Córdoba",A16="Sucre",A16="Magdalena"),"CARIBE", IF(OR(A16="Valle del Cauca",A16="Cauca",A16="Nariño"),"PACIFICO", IF(OR(A16="Meta",A16="Casanare",A16="Arauca"),"ORINOQUIA", "AMAZONIA")))) -> ANDINA | I16: =IF(F16="Departamental",E16, AVERAGEIFS($E:$E,$H:$H,H16,$B:$B,B16,$C:$C,C16)) -> 150429.77 | J16: =IF(G16<>"",G16,I16) -> 150429.77
A17: Antioquia | B17: Fungicidas | C17: ORTHOCIDE 50 | D17: 1 kilogramo | E17: 37023.54 | F17: Departamental | H17: =IF(OR(A17="Antioquia",A17="Bogotá, D.C.",A17="Boyacá",A17="Cundinamarca",A17="Caldas",A17="Risaralda",A17="Quindío",A17="Tolima",A17="Huila",A17="Santander",A17="Norte de Santander"),"ANDINA", IF(OR(A17="Atlántico",A17="Bolívar",A17="Cesar",A17="Córdoba",A17="Sucre",A17="Magdalena"),"CARIBE", IF(OR(A17="Valle del Cauca",A17="Cauca",A17="Nariño"),"PACIFICO", IF(OR(A17="Meta",A17="Casanare",A17="Arauca"),"ORINOQUIA", "AMAZONIA")))) -> ANDINA | I17: =IF(F17="Departamental",E17, AVERAGEIFS($E:$E,$H:$H,H17,$B:$B,B17,$C:$C,C17)) -> 37023.54 | J17: =IF(G17<>"",G17,I17) -> 37023.54 | L17: Los precios nacionales en contingencia no se fijan de forma única, sino que se aproximan al comportamiento observado dentro de su región geográfica.”
A18: Antioquia | B18: Herbicidas | C18: Glifosato 480 Sl | D18: 1 litro | E18: 19100 | F18: Departamental | H18: =IF(OR(A18="Antioquia",A18="Bogotá, D.C.",A18="Boyacá",A18="Cundinamarca",A18="Caldas",A18="Risaralda",A18="Quindío",A18="Tolima",A18="Huila",A18="Santander",A18="Norte de Santander"),"ANDINA", IF(OR(A18="Atlántico",A18="Bolívar",A18="Cesar",A18="Córdoba",A18="Sucre",A18="Magdalena"),"CARIBE", IF(OR(A18="Valle del Cauca",A18="Cauca",A18="Nariño"),"PACIFICO", IF(OR(A18="Meta",A18="Casanare",A18="Arauca"),"ORINOQUIA", "AMAZONIA")))) -> ANDINA | I18: =IF(F18="Departamental",E18, AVERAGEIFS($E:$E,$H:$H,H18,$B:$B,B18,$C:$C,C18)) -> 19100 | J18: =IF(G18<>"",G18,I18) -> 19100
A19: Antioquia | B19: Herbicidas | C19: Gramoxone Sl | D19: 1 litro | E19: 24023.33 | F19: Nacional (Contingencia) | H19: =IF(OR(A19="Antioquia",A19="Bogotá, D.C.",A19="Boyacá",A19="Cundinamarca",A19="Caldas",A19="Risaralda",A19="Quindío",A19="Tolima",A19="Huila",A19="Santander",A19="Norte de Santander"),"ANDINA", IF(OR(A19="Atlántico",A19="Bolívar",A19="Cesar",A19="Córdoba",A19="Sucre",A19="Magdalena"),"CARIBE", IF(OR(A19="Valle del Cauca",A19="Cauca",A19="Nariño"),"PACIFICO", IF(OR(A19="Meta",A19="Casanare",A19="Arauca"),"ORINOQUIA", "AMAZONIA")))) -> ANDINA | I19: =IF(F19="Departamental",E19, AVERAGEIFS($E:$E,$H:$H,H19,$B:$B,B19,$C:$C,C19)) -> 25145.121 | J19: =IF(G19<>"",G19,I19) -> 25145.121
A20: Antioquia | B20: Herbicidas | C20: Panzer 480 Sl | D20: 1 litro | E20: 19388.04 | F20: Departamental | H20: =IF(OR(A20="Antioquia",A20="Bogotá, D.C.",A20="Boyacá",A20="Cundinamarca",A20="Caldas",A20="Risaralda",A20="Quindío",A20="Tolima",A20="Huila",A20="Santander",A20="Norte de Santander"),"ANDINA", IF(OR(A20="Atlántico",A20="Bolívar",A20="Cesar",A20="Córdoba",A20="Sucre",A20="Magdalena"),"CARIBE", IF(OR(A20="Valle del Cauca",A20="Cauca",A20="Nariño"),"PACIFICO", IF(OR(A20="Meta",A20="Casanare",A20="Arauca"),"ORINOQUIA", "AMAZONIA")))) -> ANDINA | I20: =IF(F20="Departamental",E20, AVERAGEIFS($E:$E,$H:$H,H20,$B:$B,B20,$C:$C,C20)) -> 19388.04 | J20: =IF(G20<>"",G20,I20) -> 19388.04
A21: Antioquia | B21: Herbicidas | C21: Roundup Activo | D21: 1 litro | E21: 23049.55 | F21: Departamental | H21: =IF(OR(A21="Antioquia",A21="Bogotá, D.C.",A21="Boyacá",A21="Cundinamarca",A21="Caldas",A21="Risaralda",A21="Quindío",A21="Tolima",A21="Huila",A21="Santander",A21="Norte de Santander"),"ANDINA", IF(OR(A21="Atlántico",A21="Bolívar",A21="Cesar",A21="Córdoba",A21="Sucre",A21="Magdalena"),"CARIBE", IF(OR(A21="Valle del Cauca",A21="Cauca",A21="Nariño"),"PACIFICO", IF(OR(A21="Meta",A21="Casanare",A21="Arauca"),"ORINOQUIA", "AMAZONIA")))) -> ANDINA | I21: =IF(F21="Departamental",E21, AVERAGEIFS($E:$E,$H:$H,H21,$B:$B,B21,$C:$C,C21)) -> 23049.55 | J21: =IF(G21<>"",G21,I21) -> 23049.55
A22: Antioquia | B22: Insecticidas_acaricidas_y_nematicidas | C22: Abamectina 1,8 Ec | D22: 1 litro | E22: 34056.25 | F22: Nacional (Contingencia) | H22: =IF(OR(A22="Antioquia",A22="Bogotá, D.C.",A22="Boyacá",A22="Cundinamarca",A22="Caldas",A22="Risaralda",A22="Quindío",A22="Tolima",A22="Huila",A22="Santander",A22="Norte de Santander"),"ANDINA", IF(OR(A22="Atlántico",A22="Bolívar",A22="Cesar",A22="Córdoba",A22="Sucre",A22="Magdalena"),"CARIBE", IF(OR(A22="Valle del Cauca",A22="Cauca",A22="Nariño"),"PACIFICO", IF(OR(A22="Meta",A22="Casanare",A22="Arauca"),"ORINOQUIA", "AMAZONIA")))) -> ANDINA | I22: =IF(F22="Departamental",E22, AVERAGEIFS($E:$E,$H:$H,H22,$B:$B,B22,$C:$C,C22)) -> 33820.265 | J22: =IF(G22<>"",G22,I22) -> 33820.265
A23: Antioquia | B23: Insecticidas_acaricidas_y_nematicidas | C23: Engeo | D23: 1 litro | E23: 188160.82 | F23: Departamental | H23: =IF(OR(A23="Antioquia",A23="Bogotá, D.C.",A23="Boyacá",A23="Cundinamarca",A23="Caldas",A23="Risaralda",A23="Quindío",A23="Tolima",A23="Huila",A23="Santander",A23="Norte de Santander"),"ANDINA", IF(OR(A23="Atlántico",A23="Bolívar",A23="Cesar",A23="Córdoba",A23="Sucre",A23="Magdalena"),"CARIBE", IF(OR(A23="Valle del Cauca",A23="Cauca",A23="Nariño"),"PACIFICO", IF(OR(A23="Meta",A23="Casanare",A23="Arauca"),"ORINOQUIA", "AMAZONIA")))) -> ANDINA | I23: =IF(F23="Departamental",E23, AVERAGEIFS($E:$E,$H:$H,H23,$B:$B,B23,$C:$C,C23)) -> 188160.82 | J23: =IF(G23<>"",G23,I23) -> 188160.82
A24: Antioquia | B24: Insecticidas_acaricidas_y_nematicidas | C24: Gruya | D24: 1 litro | E24: 90689.07 | F24: Nacional (Contingencia) | H24: =IF(OR(A24="Antioquia",A24="Bogotá, D.C.",A24="Boyacá",A24="Cundinamarca",A24="Caldas",A24="Risaralda",A24="Quindío",A24="Tolima",A24="Huila",A24="Santander",A24="Norte de Santander"),"ANDINA", IF(OR(A24="Atlántico",A24="Bolívar",A24="Cesar",A24="Córdoba",A24="Sucre",A24="Magdalena"),"CARIBE", IF(OR(A24="Valle del Cauca",A24="Cauca",A24="Nariño"),"PACIFICO", IF(OR(A24="Meta",A24="Casanare",A24="Arauca"),"ORINOQUIA", "AMAZONIA")))) -> ANDINA | I24: =IF(F24="Departamental",E24, AVERAGEIFS($E:$E,$H:$H,H24,$B:$B,B24,$C:$C,C24)) -> 88565.011 | J24: =IF(G24<>"",G24,I24) -> 88565.011
A25: Antioquia | B25: Insecticidas_acaricidas_y_nematicidas | C25: Inveprid 350 SC | D25: 1 litro | E25: 63931.02 | F25: Departamental | H25: =IF(OR(A25="Antioquia",A25="Bogotá, D.C.",A25="Boyacá",A25="Cundinamarca",A25="Caldas",A25="Risaralda",A25="Quindío",A25="Tolima",A25="Huila",A25="Santander",A25="Norte de Santander"),"ANDINA", IF(OR(A25="Atlántico",A25="Bolívar",A25="Cesar",A25="Córdoba",A25="Sucre",A25="Magdalena"),"CARIBE", IF(OR(A25="Valle del Cauca",A25="Cauca",A25="Nariño"),"PACIFICO", IF(OR(A25="Meta",A25="Casanare",A25="Arauca"),"ORINOQUIA", "AMAZONIA")))) -> ANDINA | I25: =IF(F25="Departamental",E25, AVERAGEIFS($E:$E,$H:$H,H25,$B:$B,B25,$C:$C,C25)) -> 63931.02 | J25: =IF(G25<>"",G25,I25) -> 63931.02
A26: Antioquia | B26: Insecticidas_acaricidas_y_nematicidas | C26: Invetrina 200 Ec | D26: 1 litro | E26: 28514.22 | F26: Departamental | H26: =IF(OR(A26="Antioquia",A26="Bogotá, D.C.",A26="Boyacá",A26="Cundinamarca",A26="Caldas",A26="Risaralda",A26="Quindío",A26="Tolima",A26="Huila",A26="Santander",A26="Norte de Santander"),"ANDINA", IF(OR(A26="Atlántico",A26="Bolívar",A26="Cesar",A26="Córdoba",A26="Sucre",A26="Magdalena"),"CARIBE", IF(OR(A26="Valle del Cauca",A26="Cauca",A26="Nariño"),"PACIFICO", IF(OR(A26="Meta",A26="Casanare",A26="Arauca"),"ORINOQUIA", "AMAZONIA")))) -> ANDINA | I26: =IF(F26="Departamental",E26, AVERAGEIFS($E:$E,$H:$H,H26,$B:$B,B26,$C:$C,C26)) -> 28514.22 | J26: =IF(G26<>"",G26,I26) -> 28514.22
A27: Antioquia | B27: Insecticidas_acaricidas_y_nematicidas | C27: Karate Zeon | D27: 1 litro | E27: 142727.61 | F27: Departamental | H27: =IF(OR(A27="Antioquia",A27="Bogotá, D.C.",A27="Boyacá",A27="Cundinamarca",A27="Caldas",A27="Risaralda",A27="Quindío",A27="Tolima",A27="Huila",A27="Santander",A27="Norte de Santander"),"ANDINA", IF(OR(A27="Atlántico",A27="Bolívar",A27="Cesar",A27="Córdoba",A27="Sucre",A27="Magdalena"),"CARIBE", IF(OR(A27="Valle del Cauca",A27="Cauca",A27="Nariño"),"PACIFICO", IF(OR(A27="Meta",A27="Casanare",A27="Arauca"),"ORINOQUIA", "AMAZONIA")))) -> ANDINA | I27: =IF(F27="Departamental",E27, AVERAGEIFS($E:$E,$H:$H,H27,$B:$B,B27,$C:$C,C27)) -> 142727.61 | J27: =IF(G27<>"",G27,I27) -> 142727.61
A28: Antioquia | B28: Insecticidas_acaricidas_y_nematicidas | C28: Kunfu 100 Ec | D28: 1 litro | E28: 70814.74 | F28: Departamental | H28: =IF(OR(A28="Antioquia",A28="Bogotá, D.C.",A28="Boyacá",A28="Cundinamarca",A28="Caldas",A28="Risaralda",A28="Quindío",A28="Tolima",A28="Huila",A28="Santander",A28="Norte de Santander"),"ANDINA", IF(OR(A28="Atlántico",A28="Bolívar",A28="Cesar",A28="Córdoba",A28="Sucre",A28="Magdalena"),"CARIBE", IF(OR(A28="Valle del Cauca",A28="Cauca",A28="Nariño"),"PACIFICO", IF(OR(A28="Meta",A28="Casanare",A28="Arauca"),"ORINOQUIA", "AMAZONIA")))) -> ANDINA | I28: =IF(F28="Departamental",E28, AVERAGEIFS($E:$E,$H:$H,H28,$B:$B,B28,$C:$C,C28)) -> 70814.74 | J28: =IF(G28<>"",G28,I28) -> 70814.74
A29: Antioquia | B29: Insecticidas_acaricidas_y_nematicidas | C29: Nilo 300 Sc | D29: 1 litro | E29: 148344.98 | F29: Departamental | H29: =IF(OR(A29="Antioquia",A29="Bogotá, D.C.",A29="Boyacá",A29="Cundinamarca",A29="Caldas",A29="Risaralda",A29="Quindío",A29="Tolima",A29="Huila",A29="Santander",A29="Norte de Santander"),"ANDINA", IF(OR(A29="Atlántico",A29="Bolívar",A29="Cesar",A29="Córdoba",A29="Sucre",A29="Magdalena"),"CARIBE", IF(OR(A29="Valle del Cauca",A29="Cauca",A29="Nariño"),"PACIFICO", IF(OR(A29="Meta",A29="Casanare",A29="Arauca"),"ORINOQUIA", "AMAZONIA")))) -> ANDINA | I29: =IF(F29="Departamental",E29, AVERAGEIFS($E:$E,$H:$H,H29,$B:$B,B29,$C:$C,C29)) -> 148344.98 | J29: =IF(G29<>"",G29,I29) -> 148344.98
... A1460: Total general | B1460: Herbicidas | C1460: Atrazina 80% Wp | D1460: 1 kilogramo | E1460: 28373.316 | F1460: Nacional (Contingencia) | H1460: =IF(OR(A1460="Antioquia",A1460="Bogotá, D.C.",A1460="Boyacá",A1460="Cundinamarca",A1460="Caldas",A1460="Risaralda",A1460="Quindío",A1460="Tolima",A1460="Huila",A1460="Santander",A1460="Norte de Santander"),"ANDINA", IF(OR(A1460="Atlántico",A1460="Bolívar",A1460="Cesar",A1460="Córdoba",A1460="Sucre",A1460="Magdalena"),"CARIBE", IF(OR(A1460="Valle del Cauca",A1460="Cauca",A1460="Nariño"),"PACIFICO", IF(OR(A1460="Meta",A1460="Casanare",A1460="Arauca"),"ORINOQUIA", "AMAZONIA")))) -> AMAZONIA | I1460: =IF(F1460="Departamental",E1460, AVERAGEIFS($E:$E,$H:$H,H1460,$B:$B,B1460,$C:$C,C1460)) -> 28373.316 | J1460: =IF(G1460<>"",G1460,I1460) -> 28373.316
A1461: Amazonas | B1461: Bioinsumos | C1461: Rutinal | D1461: 1 litro | E1461: 46387.828 | F1461: Nacional (Contingencia)
A1462: Amazonas | B1462: Fertilizantes Foliares | C1462: Agrimins K Calcio Boro | D1462: 1 litro | E1462: 22409.406 | F1462: Nacional (Contingencia)
A1463: Amazonas | B1463: Fertilizantes Foliares | C1463: Klip - K Calcio-Boro | D1463: 1 litro | E1463: 22007.387 | F1463: Nacional (Contingencia)
A1464: Amazonas | B1464: Fertilizantes Foliares | C1464: Nutrifoliar Completo | D1464: 1 litro | E1464: 29374.792 | F1464: Nacional (Contingencia)
A1465: Amazonas | B1465: Fertilizantes Foliares | C1465: Wuxal Tapa Negra | D1465: 1 litro | E1465: 64582.943 | F1465: Nacional (Contingencia)
A1466: Amazonas | B1466: Fungicidas | C1466: Amistar Top | D1466: 1 litro | E1466: 285555.82 | F1466: Nacional (Contingencia)
A1467: Amazonas | B1467: Fungicidas | C1467: Azoxystrobin 250 Sc | D1467: 1 litro | E1467: 83725.822 | F1467: Nacional (Contingencia)
A1468: Amazonas | B1468: Fungicidas | C1468: Azuco | D1468: 1 litro | E1468: 23874.192 | F1468: Nacional (Contingencia)
A1469: Amazonas | B1469: Fungicidas | C1469: Benomyl 50 Wp | D1469: 1 kilogramo | E1469: 61429.978 | F1469: Nacional (Contingencia)
A1470: Amazonas | B1470: Fungicidas | C1470: Carbendazim 500 Sc | D1470: 1 litro | E1470: 29745.087 | F1470: Nacional (Contingencia)
A1471: Amazonas | B1471: Fungicidas | C1471: Daconil 720 Sc | D1471: 1 litro | E1471: 41426.64 | F1471: Nacional (Contingencia)
A1472: Amazonas | B1472: Fungicidas | C1472: FURTIVO 250 SC | D1472: 1 litro | E1472: 116939.8 | F1472: Nacional (Contingencia)
... A2512: Bolívar | B2512: Herbicidas | C2512: Atrazina 80% Wp | D2512: 1 kilogramo | E2512: 28603.382 | F2512: Nacional (Contingencia)
A2513: Amazonas | B2513: Varios | C2513: Administración del cultivo
A2514: Amazonas | B2514: Varios | C2514: Asistencia Técnica | D2514: Visita | E2514: 120000 | F2514: Contingencia nacional
A2515: Amazonas | B2515: Varios | C2515: Analisis completo de suelos | D2515: héctarea | E2515: 175000 | F2515: Agrosavia
A2516: Antioquia | B2516: Varios | C2516: Administración del cultivo | D2516: unidad
A2517: Antioquia | B2517: Varios | C2517: Asistencia Técnica | D2517: Visita | E2517: 120000 | F2517: Contingencia nacional
A2518: Antioquia | B2518: Varios | C2518: Analisis completo de suelos | D2518: héctarea | E2518: 175000 | F2518: Agrosavia
A2519: Arauca | B2519: Varios | C2519: Administración del cultivo | D2519: unidad
A2520: Arauca | B2520: Varios | C2520: Asistencia Técnica | D2520: Visita | E2520: 120000 | F2520: Contingencia nacional
A2521: Arauca | B2521: Varios | C2521: Analisis completo de suelos | D2521: héctarea | E2521: 175000 | F2521: Agrosavia
A2522: Atlántico | B2522: Varios | C2522: Administración del cultivo | D2522: unidad
A2523: Atlántico | B2523: Varios | C2523: Asistencia Técnica | D2523: Visita | E2523: 120000 | F2523: Contingencia nacional
A2524: Atlántico | B2524: Varios | C2524: Analisis completo de suelos | D2524: héctarea | E2524: 175000 | F2524: Agrosavia
A2525: Bogotá, D.C. | B2525: Varios | C2525: Administración del cultivo | D2525: unidad
A2526: Bogotá, D.C. | B2526: Varios | C2526: Asistencia Técnica | D2526: Visita | E2526: 120000 | F2526: Contingencia nacional
A2527: Bogotá, D.C. | B2527: Varios | C2527: Analisis completo de suelos | D2527: héctarea | E2527: 175000 | F2527: Agrosavia
A2528: Bolívar | B2528: Varios | C2528: Administración del cultivo | D2528: unidad
A2529: Bolívar | B2529: Varios | C2529: Asistencia Técnica | D2529: Visita | E2529: 120000 | F2529: Contingencia nacional
A2530: Bolívar | B2530: Varios | C2530: Analisis completo de suelos | D2530: héctarea | E2530: 175000 | F2530: Agrosavia
A2531: Boyacá | B2531: Varios | C2531: Administración del cultivo | D2531: unidad
A2532: Boyacá | B2532: Varios | C2532: Asistencia Técnica | D2532: Visita | E2532: 120000 | F2532: Contingencia nacional
A2533: Boyacá | B2533: Varios | C2533: Analisis completo de suelos | D2533: héctarea | E2533: 175000 | F2533: Agrosavia
A2534: Caldas | B2534: Varios | C2534: Administración del cultivo | D2534: unidad
A2535: Caldas | B2535: Varios | C2535: Asistencia Técnica | D2535: Visita | E2535: 120000 | F2535: Contingencia nacional
A2536: Caldas | B2536: Varios | C2536: Analisis completo de suelos | D2536: héctarea | E2536: 175000 | F2536: Agrosavia
A2537: Caquetá | B2537: Varios | C2537: Administración del cultivo | D2537: unidad
A2538: Caquetá | B2538: Varios | C2538: Asistencia Técnica | D2538: Visita | E2538: 120000 | F2538: Contingencia nacional
A2539: Caquetá | B2539: Varios | C2539: Analisis completo de suelos | D2539: héctarea | E2539: 175000 | F2539: Agrosavia
A2540: Casanare | B2540: Varios | C2540: Administración del cultivo | D2540: unidad
A2541: Casanare | B2541: Varios | C2541: Asistencia Técnica | D2541: Visita | E2541: 120000 | F2541: Contingencia nacional
A2542: Casanare | B2542: Varios | C2542: Analisis completo de suelos | D2542: héctarea | E2542: 175000 | F2542: Agrosavia
A2543: Cauca | B2543: Varios | C2543: Administración del cultivo | D2543: unidad
A2544: Cauca | B2544: Varios | C2544: Asistencia Técnica | D2544: Visita | E2544: 120000 | F2544: Contingencia nacional
A2545: Cauca | B2545: Varios | C2545: Analisis completo de suelos | D2545: héctarea | E2545: 175000 | F2545: Agrosavia
A2546: Cesar | B2546: Varios | C2546: Administración del cultivo | D2546: unidad
A2547: Cesar | B2547: Varios | C2547: Asistencia Técnica | D2547: Visita | E2547: 120000 | F2547: Contingencia nacional
A2548: Cesar | B2548: Varios | C2548: Analisis completo de suelos | D2548: héctarea | E2548: 175000 | F2548: Agrosavia
A2549: Chocó | B2549: Varios | C2549: Administración del cultivo | D2549: unidad
A2550: Chocó | B2550: Varios | C2550: Asistencia Técnica | D2550: Visita | E2550: 120000 | F2550: Contingencia nacional
A2551: Chocó | B2551: Varios | C2551: Analisis completo de suelos | D2551: héctarea | E2551: 175000 | F2551: Agrosavia
A2552: Cundinamarca | B2552: Varios | C2552: Administración del cultivo | D2552: unidad
A2553: Cundinamarca | B2553: Varios | C2553: Asistencia Técnica | D2553: Visita | E2553: 120000 | F2553: Contingencia nacional
A2554: Cundinamarca | B2554: Varios | C2554: Analisis completo de suelos | D2554: héctarea | E2554: 175000 | F2554: Agrosavia
A2555: Córdoba | B2555: Varios | C2555: Administración del cultivo | D2555: unidad
A2556: Córdoba | B2556: Varios | C2556: Asistencia Técnica | D2556: Visita | E2556: 120000 | F2556: Contingencia nacional
A2557: Córdoba | B2557: Varios | C2557: Analisis completo de suelos | D2557: héctarea | E2557: 175000 | F2557: Agrosavia
A2558: Guainía | B2558: Varios | C2558: Administración del cultivo | D2558: unidad
A2559: Guainía | B2559: Varios | C2559: Asistencia Técnica | D2559: Visita | E2559: 120000 | F2559: Contingencia nacional
A2560: Guainía | B2560: Varios | C2560: Analisis completo de suelos | D2560: héctarea | E2560: 175000 | F2560: Agrosavia
A2561: Guaviare | B2561: Varios | C2561: Administración del cultivo | D2561: unidad
A2562: Guaviare | B2562: Varios | C2562: Asistencia Técnica | D2562: Visita | E2562: 120000 | F2562: Contingencia nacional
A2563: Guaviare | B2563: Varios | C2563: Analisis completo de suelos | D2563: héctarea | E2563: 175000 | F2563: Agrosavia
A2564: Huila | B2564: Varios | C2564: Administración del cultivo | D2564: unidad
A2565: Huila | B2565: Varios | C2565: Asistencia Técnica | D2565: Visita | E2565: 120000 | F2565: Contingencia nacional
A2566: Huila | B2566: Varios | C2566: Analisis completo de suelos | D2566: héctarea | E2566: 175000 | F2566: Agrosavia
A2567: La Guajira | B2567: Varios | C2567: Administración del cultivo | D2567: unidad
A2568: La Guajira | B2568: Varios | C2568: Asistencia Técnica | D2568: Visita | E2568: 120000 | F2568: Contingencia nacional
A2569: La Guajira | B2569: Varios | C2569: Analisis completo de suelos | D2569: héctarea | E2569: 175000 | F2569: Agrosavia
A2570: Magdalena | B2570: Varios | C2570: Administración del cultivo | D2570: unidad
...

Sheet departamento
A1: Nombre Departamento | B1: Nombre Municipio | C1: Tipo: Municipio / Isla / Área no municipalizada | D1: longitud | E1: Latitud | G1: DEPARTAMENTOS_VÁLIDOS
A2: ANTIOQUIA | B2: MEDELLÍN | C2: Municipio | D2: -75,581775 | E2: 6,246631 | F2: AMAZONAS | G2: AMAZONAS | H2: ARAUCA | I2: ATLÁNTICO | J2: BOLÍVAR | K2: BOYACÁ | L2: CALDAS | M2: CAQUETÁ | N2: CASANARE | O2: CAUCA | P2: CESAR | Q2: CHOCÓ | R2: CÓRDOBA | S2: CUNDINAMARCA | T2: GUAINÍA | U2: GUAVIARE | V2: HUILA | W2: LA GUAJIRA | X2: MAGDALENA | Y2: META | Z2: NARIÑO | AA2: NORTE DE SANTANDER | AB2: PUTUMAYO | AC2: QUINDÍO | AD2: RISARALDA | AE2: SANTANDER | AF2: SUCRE | AG2: TOLIMA | AH2: VALLE DEL CAUCA | AI2: VAUPÉS | AJ2: VICHADA
A3: ANTIOQUIA | B3: ABEJORRAL | C3: Municipio | D3: -75,428739 | E3: 5,789315 | F3: LETICIA | G3: ANTIOQUIA | H3: ARAUCA | I3: BARRANQUILLA | J3: CARTAGENA DE INDIAS | K3: TUNJA | L3: MANIZALES | M3: FLORENCIA | N3: YOPAL | O3: POPAYÁN | P3: VALLEDUPAR | Q3: QUIBDÓ | R3: MONTERÍA | S3: AGUA DE DIOS | T3: INÍRIDA | U3: SAN JOSÉ DEL GUAVIARE | V3: NEIVA | W3: RIOHACHA | X3: SANTA MARTA | Y3: VILLAVICENCIO | Z3: PASTO | AA3: SAN JOSÉ DE CÚCUTA | AB3: MOCOA | AC3: ARMENIA | AD3: PEREIRA | AE3: BUCARAMANGA | AF3: SINCELEJO | AG3: IBAGUÉ | AH3: SANTIAGO DE CALI | AI3: MITÚ | AJ3: PUERTO CARREÑO
A4: ANTIOQUIA | B4: ABRIAQUÍ | C4: Municipio | D4: -76,064304 | E4: 6,632282 | F4: EL ENCANTO | G4: ARAUCA | H4: ARAUQUITA | I4: BARANOA | J4: ACHÍ | K4: ALMEIDA | L4: AGUADAS | M4: ALBANIA | N4: AGUAZUL | O4: ALMAGUER | P4: AGUACHICA | Q4: ACANDÍ | R4: AYAPEL | S4: ALBÁN | T4: BARRANCOMINAS | U4: CALAMAR | V4: ACEVEDO | W4: ALBANIA | X4: ALGARROBO | Y4: ACACÍAS | Z4: ALBÁN | AA4: ÁBREGO | AB4: COLÓN | AC4: BUENAVISTA | AD4: APÍA | AE4: AGUADA | AF4: BUENAVISTA | AG4: ALPUJARRA | AH4: ALCALÁ | AI4: CARURÚ | AJ4: LA PRIMAVERA
A5: ANTIOQUIA | B5: ALEJANDRÍA | C5: Municipio | D5: -75,141346 | E5: 6,376061 | F5: LA CHORRERA | G5: ATLÁNTICO | H5: CRAVO NORTE | I5: CAMPO DE LA CRUZ | J5: ALTOS DEL ROSARIO | K5: AQUITANIA | L5: ANSERMA | M5: BELÉN DE LOS ANDAQUÍES | N5: CHÁMEZA | O5: ARGELIA | P5: AGUSTÍN CODAZZI | Q5: ALTO BAUDÓ | R5: BUENAVISTA | S5: ANAPOIMA | T5: SAN FELIPE | U5: EL RETORNO | V5: AGRADO | W5: BARRANCAS | X5: ARACATACA | Y5: BARRANCA DE UPÍA | Z5: ALDANA | AA5: ARBOLEDAS | AB5: ORITO | AC5: CALARCÁ | AD5: BALBOA | AE5: ALBANIA | AF5: CAIMITO | AG5: ALVARADO | AH5: ANDALUCÍA | AI5: PACOA | AJ5: SANTA ROSALÍA
A6: ANTIOQUIA | B6: AMAGÁ | C6: Municipio | D6: -75,702188 | E6: 6,038708 | F6: LA PEDRERA | G6: BOGOTÁ, D.C. | H6: FORTUL | I6: CANDELARIA | J6: ARENAL | K6: ARCABUCO | L6: ARANZAZU | M6: CARTAGENA DEL CHAIRÁ | N6: HATO COROZAL | O6: BALBOA | P6: ASTREA | Q6: ATRATO | R6: CANALETE | S6: ANOLAIMA | T6: PUERTO COLOMBIA | U6: MIRAFLORES | V6: AIPE | W6: DIBULLA | X6: ARIGUANÍ | Y6: CABUYARO | Z6: ANCUYA | AA6: BOCHALEMA | AB6: PUERTO ASÍS | AC6: CIRCASIA | AD6: BELÉN DE UMBRÍA | AE6: ARATOCA | AF6: COLOSÓ | AG6: AMBALEMA | AH6: ANSERMANUEVO | AI6: TARAIRA | AJ6: CUMARIBO
A7: ANTIOQUIA | B7: AMALFI | C7: Municipio | D7: -75,077501 | E7: 6,909655 | F7: LA VICTORIA | G7: BOLÍVAR | H7: PUERTO RONDÓN | I7: GALAPA | J7: ARJONA | K7: BELÉN | L7: BELALCÁZAR | M7: CURILLO | N7: LA SALINA | O7: BOLÍVAR | P7: BECERRIL | Q7: BAGADÓ | R7: CERETÉ | S7: ARBELÁEZ | T7: LA GUADALUPE | V7: ALGECIRAS | W7: DISTRACCIÓN | X7: CERRO DE SAN ANTONIO | Y7: CASTILLA LA NUEVA | Z7: ARBOLEDA | AA7: BUCARASICA | AB7: PUERTO CAICEDO | AC7: CÓRDOBA | AD7: DOSQUEBRADAS | AE7: BARBOSA | AF7: COROZAL | AG7: ANZOÁTEGUI | AH7: ARGELIA | AI7: PAPUNAHUA
A8: ANTIOQUIA | B8: ANDES | C8: Municipio | D8: -75,878828 | E8: 5,657194 | F8: MIRITÍ - PARANÁ | G8: BOYACÁ | H8: SARAVENA | I8: JUAN DE ACOSTA | J8: ARROYOHONDO | K8: BERBEO | L8: CHINCHINÁ | M8: EL DONCELLO | N8: MANÍ | O8: BUENOS AIRES | P8: BOSCONIA | Q8: BAHÍA SOLANO | R8: CHIMÁ | S8: BELTRÁN | T8: CACAHUAL | V8: ALTAMIRA | W8: EL MOLINO | X8: CHIVOLO | Y8: CUBARRAL | Z8: BARBACOAS | AA8: CÁCOTA | AB8: PUERTO GUZMÁN | AC8: FILANDIA | AD8: GUÁTICA | AE8: BARICHARA | AF8: COVEÑAS | AG8: ARMERO | AH8: BOLÍVAR | AI8: YAVARATÉ
A9: ANTIOQUIA | B9: ANGELÓPOLIS | C9: Municipio | D9: -75,711389 | E9: 6,109719 | F9: PUERTO ALEGRÍA | G9: CALDAS | H9: TAME | I9: LURUACO | J9: BARRANCO DE LOBA | K9: BETÉITIVA | L9: FILADELFIA | M9: EL PAUJÍL | N9: MONTERREY | O9: CAJIBÍO | P9: CHIMICHAGUA | Q9: BAJO BAUDÓ | R9: CHINÚ | S9: BITUIMA | T9: PANA PANA | V9: BARAYA | W9: FONSECA | X9: CIÉNAGA | Y9: CUMARAL | Z9: BELÉN | AA9: CÁCHIRA | AB9: PUERTO LEGUÍZAMO | AC9: GÉNOVA | AD9: LA CELIA | AE9: BARRANCABERMEJA | AF9: CHALÁN | AG9: ATACO | AH9: BUENAVENTURA
A10: ANTIOQUIA | B10: ANGOSTURA | C10: Municipio | D10: -75,335116 | E10: 6,885175 | F10: PUERTO ARICA | G10: CAQUETÁ | I10: MALAMBO | J10: CALAMAR | K10: BOAVITA | L10: LA DORADA | M10: LA MONTAÑITA | N10: NUNCHÍA | O10: CALDONO | P10: CHIRIGUANÁ | Q10: BOJAYÁ | R10: CIÉNAGA DE ORO | S10: BOJACÁ | T10: MORICHAL | V10: CAMPOALEGRE | W10: HATONUEVO | X10: CONCORDIA | Y10: EL CALVARIO | Z10: BUESACO | AA10: CHINÁCOTA | AB10: SIBUNDOY | AC10: LA TEBAIDA | AD10: LA VIRGINIA | AE10: BETULIA | AF10: EL ROBLE | AG10: CAJAMARCA | AH10: GUADALAJARA DE BUGA
A11: ANTIOQUIA | B11: ANORÍ | C11: Municipio | D11: -75,148355 | E11: 7,074703 | F11: PUERTO NARIÑO | G11: CASANARE | I11: MANATÍ | J11: CANTAGALLO | K11: BOYACÁ | L11: LA MERCED | M11: MILÁN | N11: OROCUÉ | O11: CALOTO | P11: CURUMANÍ | Q11: EL CANTÓN DEL SAN PABLO | R11: COTORRA | S11: CABRERA | V11: COLOMBIA | W11: LA JAGUA DEL PILAR | X11: EL BANCO | Y11: EL CASTILLO | Z11: COLÓN | AA11: CHITAGÁ | AB11: SAN FRANCISCO | AC11: MONTENEGRO | AD11: MARSELLA | AE11: BOLÍVAR | AF11: GALERAS | AG11: CARMEN DE APICALÁ | AH11: BUGALAGRANDE
A12: ANTIOQUIA | B12: SANTA FÉ DE ANTIOQUIA | C12: Municipio | D12: -75,826648 | E12: 6,556484 | F12: PUERTO SANTANDER | G12: CAUCA | I12: PALMAR DE VARELA | J12: CICUCO | K12: BRICEÑO | L12: MANZANARES | M12: MORELIA | N12: PAZ DE ARIPORO | O12: CORINTO | P12: EL COPEY | Q12: CARMEN DEL DARIÉN | R12: LA APARTADA | S12: CACHIPAY | V12: ELÍAS | W12: MAICAO | X12: EL PIÑÓN | Y12: EL DORADO | Z12: CONSACÁ | AA12: CONVENCIÓN | AB12: SAN MIGUEL | AC12: PIJAO | AD12: MISTRATÓ | AE12: CABRERA | AF12: GUARANDA | AG12: CASABIANCA | AH12: CAICEDONIA
A13: ANTIOQUIA | B13: ANZÁ | C13: Municipio | D13: -75,854442 | E13: 6,302641 | F13: TARAPACÁ | G13: CESAR | I13: PIOJÓ | J13: CÓRDOBA | K13: BUENAVISTA | L13: MARMATO | M13: PUERTO RICO | N13: PORE | O13: EL TAMBO | P13: EL PASO | Q13: CÉRTEGUI | R13: LORICA | S13: CAJICÁ | V13: GARZÓN | W13: MANAURE | X13: EL RETÉN | Y13: FUENTE DE ORO | Z13: CONTADERO | AA13: CUCUTILLA | AB13: SANTIAGO | AC13: QUIMBAYA | AD13: PUEBLO RICO | AE13: CALIFORNIA | AF13: LA UNIÓN | AG13: CHAPARRAL | AH13: CALIMA
A14: ANTIOQUIA | B14: APARTADÓ | C14: Municipio | D14: -76,625279 | E14: 7,882968 | G14: CHOCÓ | I14: POLONUEVO | J14: CLEMENCIA | K14: BUSBANZÁ | L14: MARQUETALIA | M14: SAN JOSÉ DEL FRAGUA | N14: RECETOR | O14: FLORENCIA | P14: GAMARRA | Q14: CONDOTO | R14: LOS CÓRDOBAS | S14: CAPARRAPÍ | V14: GIGANTE | W14: SAN JUAN DEL CESAR | X14: FUNDACIÓN | Y14: GRANADA | Z14: CÓRDOBA | AA14: DURANIA | AB14: VALLE DEL GUAMUEZ | AC14: SALENTO | AD14: QUINCHÍA | AE14: CAPITANEJO | AF14: LOS PALMITOS | AG14: COELLO | AH14: CANDELARIA
A15: ANTIOQUIA | B15: ARBOLETES | C15: Municipio | D15: -76,426708 | E15: 8,849317 | G15: CUNDINAMARCA | I15: PONEDERA | J15: EL CARMEN DE BOLÍVAR | K15: CALDAS | L15: MARULANDA | M15: SAN VICENTE DEL CAGUÁN | N15: SABANALARGA | O15: GUACHENÉ | P15: GONZÁLEZ | Q15: EL CARMEN DE ATRATO | R15: MOMIL | S15: CÁQUEZA | V15: GUADALUPE | W15: URIBIA | X15: GUAMAL | Y15: GUAMAL | Z15: CUASPUD CARLOSAMA | AA15: EL CARMEN | AB15: VILLAGARZÓN | AD15: SANTA ROSA DE CABAL | AE15: CARCASÍ | AF15: MAJAGUAL | AG15: COYAIMA | AH15: CARTAGO
A16: ANTIOQUIA | B16: ARGELIA | C16: Municipio | D16: -75,14107 | E16: 5,731474 | G16: CÓRDOBA | I16: PUERTO COLOMBIA | J16: EL GUAMO | K16: CAMPOHERMOSO | L16: NEIRA | M16: SOLANO | N16: SÁCAMA | O16: GUAPI | P16: LA GLORIA | Q16: EL LITORAL DEL SAN JUAN | R16: MONTELÍBANO | S16: CARMEN DE CARUPA | V16: HOBO | W16: URUMITA | X16: NUEVA GRANADA | Y16: MAPIRIPÁN | Z16: CUMBAL | AA16: EL TARRA | AD16: SANTUARIO | AE16: CEPITÁ | AF16: MORROA | AG16: CUNDAY | AH16: DAGUA
A17: ANTIOQUIA | B17: ARMENIA | C17: Municipio | D17: -75,786647 | E17: 6,155667 | G17: GUAINÍA | I17: REPELÓN | J17: EL PEÑÓN | K17: CERINZA | L17: NORCASIA | M17: SOLITA | N17: SAN LUIS DE PALENQUE | O17: INZÁ | P17: LA JAGUA DE IBIRICO | Q17: ISTMINA | R17: MOÑITOS | S17: CHAGUANÍ | V17: ÍQUIRA | W17: VILLANUEVA | X17: PEDRAZA | Y17: MESETAS | Z17: CUMBITARA | AA17: EL ZULIA | AE17: CERRITO | AF17: OVEJAS | AG17: DOLORES | AH17: EL ÁGUILA
A18: ANTIOQUIA | B18: BARBOSA | C18: Municipio | D18: -75,331627 | E18: 6,439195 | G18: GUAVIARE | I18: SABANAGRANDE | J18: HATILLO DE LOBA | K18: CHINAVITA | L18: PÁCORA | M18: VALPARAÍSO | N18: TÁMARA | O18: JAMBALÓ | P18: MANAURE BALCÓN DEL CESAR | Q18: JURADÓ | R18: PLANETA RICA | S18: CHÍA | V18: ISNOS | X18: PIJIÑO DEL CARMEN | Y18: LA MACARENA | Z18: CHACHAGÜÍ | AA18: GRAMALOTE | AE18: CHARALÁ | AF18: PALMITO | AG18: ESPINAL | AH18: EL CAIRO
A19: ANTIOQUIA | B19: BELMIRA | C19: Municipio | D19: -75,667779 | E19: 6,606319 | G19: HUILA | I19: SABANALARGA | J19: MAGANGUÉ | K19: CHIQUINQUIRÁ | L19: PALESTINA | N19: TAURAMENA | O19: LA SIERRA | P19: PAILITAS | Q19: LLORÓ | R19: PUEBLO NUEVO | S19: CHIPAQUE | V19: LA ARGENTINA | X19: PIVIJAY | Y19: URIBE | Z19: EL CHARCO | AA19: HACARÍ | AE19: CHARTA | AF19: SAMPUÉS | AG19: FALAN | AH19: EL CERRITO
A20: ANTIOQUIA | B20: BELLO | C20: Municipio | D20: -75,555245 | E20: 6,333587 | G20: LA GUAJIRA | I20: SANTA LUCÍA | J20: MAHATES | K20: CHISCAS | L20: PENSILVANIA | N20: TRINIDAD | O20: LA VEGA | P20: PELAYA | Q20: MEDIO ATRATO | R20: PUERTO ESCONDIDO | S20: CHOACHÍ | V20: LA PLATA | X20: PLATO | Y20: LEJANÍAS | Z20: EL PEÑOL | AA20: HERRÁN | AE20: CHIMA | AF20: SAN BENITO ABAD | AG20: FLANDES | AH20: EL DOVIO
A21: ANTIOQUIA | B21: BETANIA | C21: Municipio | D21: -75,97679 | E21: 5,74615 | G21: MAGDALENA | I21: SANTO TOMÁS | J21: MARGARITA | K21: CHITA | L21: RIOSUCIO | N21: VILLANUEVA | O21: LÓPEZ DE MICAY | P21: PUEBLO BELLO | Q21: MEDIO BAUDÓ | R21: PUERTO LIBERTADOR | S21: CHOCONTÁ | V21: NÁTAGA | X21: PUEBLOVIEJO | Y21: PUERTO CONCORDIA | Z21: EL ROSARIO | AA21: LABATECA | AE21: CHIPATÁ | AF21: SAN JUAN DE BETULIA | AG21: FRESNO | AH21: FLORIDA
A22: ANTIOQUIA | B22: BETULIA | C22: Municipio | D22: -75,984452 | E22: 6,115208 | G22: META | I22: SOLEDAD | J22: MARÍA LA BAJA | K22: CHITARAQUE | L22: RISARALDA | O22: MERCADERES | P22: RÍO DE ORO | Q22: MEDIO SAN JUAN | R22: PURÍSIMA DE LA CONCEPCIÓN | S22: COGUA | V22: OPORAPA | X22: REMOLINO | Y22: PUERTO GAITÁN | Z22: EL TABLÓN DE GÓMEZ | AA22: LA ESPERANZA | AE22: CIMITARRA | AF22: SAN MARCOS | AG22: GUAMO | AH22: GINEBRA
A23: ANTIOQUIA | B23: CIUDAD BOLÍVAR | C23: Municipio | D23: -76,021509 | E23: 5,850273 | G23: NARIÑO | I23: SUAN | J23: MONTECRISTO | K23: CHIVATÁ | L23: SALAMINA | O23: MIRANDA | P23: LA PAZ | Q23: NÓVITA | R23: SAHAGÚN | S23: COTA | V23: PAICOL | X23: SABANAS DE SAN ÁNGEL | Y23: PUERTO LÓPEZ | Z23: EL TAMBO | AA23: LA PLAYA | AE23: CONCEPCIÓN | AF23: SAN ONOFRE | AG23: HERVEO | AH23: GUACARÍ
A24: ANTIOQUIA | B24: BRICEÑO | C24: Municipio | D24: -75,55036 | E24: 7,112803 | G24: NORTE DE SANTANDER | I24: TUBARÁ | J24: SANTA CRUZ DE MOMPOX | K24: CIÉNEGA | L24: SAMANÁ | O24: MORALES | P24: SAN ALBERTO | Q24: NUEVO BELÉN DE BAJIRÁ | R24: SAN ANDRÉS DE SOTAVENTO | S24: CUCUNUBÁ | V24: PALERMO | X24: SALAMINA | Y24: PUERTO LLERAS | Z24: FUNES | AA24: LOS PATIOS | AE24: CONFINES | AF24: SAN PEDRO | AG24: HONDA | AH24: JAMUNDÍ
A25: ANTIOQUIA | B25: BURITICÁ | C25: Municipio | D25: -75,907 | E25: 6,720759 | G25: PUTUMAYO | I25: USIACURÍ | J25: MORALES | K25: CÓMBITA | L25: SAN JOSÉ | O25: PADILLA | P25: SAN DIEGO | Q25: NUQUÍ | R25: SAN ANTERO | S25: EL COLEGIO | V25: PALESTINA | X25: SAN SEBASTIÁN DE BUENAVISTA | Y25: PUERTO RICO | Z25: GUACHUCAL | AA25: LOURDES | AE25: CONTRATACIÓN | AF25: SAN LUIS DE SINCÉ | AG25: ICONONZO | AH25: LA CUMBRE
A26: ANTIOQUIA | B26: CÁCERES | C26: Municipio | D26: -75,35205 | E26: 7,578366 | G26: QUINDÍO | J26: NOROSÍ | K26: COPER | L26: SUPÍA | O26: PÁEZ | P26: SAN MARTÍN | Q26: RÍO IRÓ | R26: SAN BERNARDO DEL VIENTO | S26: EL PEÑÓN | V26: PITAL | X26: SAN ZENÓN | Y26: RESTREPO | Z26: GUAITARILLA | AA26: MUTISCUA | AE26: COROMORO | AF26: SUCRE | AG26: LÉRIDA | AH26: LA UNIÓN
A27: ANTIOQUIA | B27: CAICEDO | C27: Municipio | D27: -75,98293 | E27: 6,405607 | G27: RISARALDA | J27: PINILLOS | K27: CORRALES | L27: VICTORIA | O27: PATÍA | P27: TAMALAMEQUE | Q27: RÍO QUITO | R27: SAN CARLOS | S27: EL ROSAL | V27: PITALITO | X27: SANTA ANA | Y27: SAN CARLOS DE GUAROA | Z27: GUALMATÁN | AA27: OCAÑA | AE27: CURITÍ | AF27: SANTIAGO DE TOLÚ | AG27: LÍBANO | AH27: LA VICTORIA
A28: ANTIOQUIA | B28: CALDAS | C28: Municipio | D28: -75,633673 | E28: 6,091077 | G28: SANTANDER | J28: REGIDOR | K28: COVARACHÍA | L28: VILLAMARÍA | O28: PIAMONTE | Q28: RIOSUCIO | R28: SAN JOSÉ DE URÉ | S28: FACATATIVÁ | V28: RIVERA | X28: SANTA BÁRBARA DE PINTO | Y28: SAN JUAN DE ARAMA | Z28: ILES | AA28: PAMPLONA | AE28: EL CARMEN DE CHUCURÍ | AF28: SAN JOSÉ DE TOLUVIEJO | AG28: SAN SEBASTIÁN DE MARIQUITA | AH28: OBANDO
A29: ANTIOQUIA | B29: CAMPAMENTO | C29: Municipio | D29: -75,298091 | E29: 6,979771 | G29: SUCRE | J29: RÍO VIEJO | K29: CUBARÁ | L29: VITERBO | O29: PIENDAMÓ - TUNÍA | Q29: SAN JOSÉ DEL PALMAR | R29: SAN PELAYO | S29: FÓMEQUE | V29: SALADOBLANCO | X29: SITIONUEVO | Y29: SAN JUANITO | Z29: IMUÉS | AA29: PAMPLONITA | AE29: EL GUACAMAYO | AG29: MELGAR | AH29: PALMIRA
A30: ANTIOQUIA | B30: CAÑASGORDAS | C30: Municipio | D30: -76,028228 | E30: 6,753859 | G30: TOLIMA | J30: SAN CRISTÓBAL | K30: CUCAITA | O30: PUERTO TEJADA | Q30: SIPÍ | R30: TIERRALTA | S30: FOSCA | V30: SAN AGUSTÍN | X30: TENERIFE | Y30: SAN MARTÍN | Z30: IPIALES | AA30: PUERTO SANTANDER | AE30: EL PEÑÓN | AG30: MURILLO | AH30: PRADERA
A31: ANTIOQUIA | B31: CARACOLÍ | C31: Municipio | D31: -74,757421 | E31: 6,409829 | G31: VALLE DEL CAUCA | J31: SAN ESTANISLAO | K31: CUÍTIVA | O31: PURACÉ | Q31: TADÓ | R31: TUCHÍN | S31: FUNZA | V31: SANTA MARÍA | X31: ZAPAYÁN | Y31: VISTAHERMOSA | Z31: LA CRUZ | AA31: RAGONVALIA | AE31: EL PLAYÓN | AG31: NATAGAIMA | AH31: RESTREPO
A32: ANTIOQUIA | B32: CARAMANTA | C32: Municipio | D32: -75,643868 | E32: 5,54853 | G32: VAUPÉS | J32: SAN FERNANDO | K32: CHÍQUIZA | O32: ROSAS | Q32: UNGUÍA | R32: VALENCIA | S32: FÚQUENE | V32: SUAZA | X32: ZONA BANANERA | Z32: LA FLORIDA | AA32: SALAZAR | AE32: ENCINO | AG32: ORTEGA | AH32: RIOFRÍO
A33: ANTIOQUIA | B33: CAREPA | C33: Municipio | D33: -76,652652 | E33: 7,755148 | G33: VICHADA | J33: SAN JACINTO | K33: CHIVOR | O33: SAN SEBASTIÁN | Q33: UNIÓN PANAMERICANA | S33: FUSAGASUGÁ | V33: TARQUI | Z33: LA LLANADA | AA33: SAN CALIXTO | AE33: ENCISO | AG33: PALOCABILDO | AH33: ROLDANILLO
A34: ANTIOQUIA | B34: EL CARMEN DE VIBORAL | C34: Municipio | D34: -75,333901 | E34: 6,082885 | G34: CAREPA | J34: SAN JACINTO DEL CAUCA | K34: DUITAMA | O34: SANTANDER DE QUILICHAO | S34: GACHALÁ | V34: TESALIA | Z34: LA TOLA | AA34: SAN CAYETANO | AE34: FLORIÁN | AG34: PIEDRAS | AH34: SAN PEDRO
A35: ANTIOQUIA | B35: CAROLINA | C35: Municipio | D35: -75,283192 | E35: 6,725995 | G35: EL CARMEN DE VIBORAL | J35: SAN JUAN NEPOMUCENO | K35: EL COCUY | O35: SANTA ROSA | S35: GACHANCIPÁ | V35: TELLO | Z35: LA UNIÓN | AA35: SANTIAGO | AE35: FLORIDABLANCA | AG35: PLANADAS | AH35: SEVILLA
A36: ANTIOQUIA | B36: CAUCASIA | C36: Municipio | D36: -75,197996 | E36: 7,977278 | G36: CAROLINA | J36: SAN MARTÍN DE LOBA | K36: EL ESPINO | O36: SILVIA | S36: GACHETÁ | V36: TERUEL | Z36: LEIVA | AA36: SARDINATA | AE36: GALÁN | AG36: PRADO | AH36: TORO
A37: ANTIOQUIA | B37: CHIGORODÓ | C37: Municipio | D37: -76,681531 | E37: 7,666147 | G37: CAUCASIA | J37: SAN PABLO | K37: FIRAVITOBA | O37: SOTARÁ - PAISPAMBA | S37: GAMA | V37: TIMANÁ | Z37: LINARES | AA37: SILOS | AE37: GÁMBITA | AG37: PURIFICACIÓN | AH37: TRUJILLO
A38: ANTIOQUIA | B38: CISNEROS | C38: Municipio | D38: -75,087047 | E38: 6,537829 | G38: CHIGORODÓ | J38: SANTA CATALINA | K38: FLORESTA | O38: SUÁREZ | S38: GIRARDOT | V38: VILLAVIEJA | Z38: LOS ANDES | AA38: TEORAMA | AE38: GIRÓN | AG38: RIOBLANCO | AH38: TULUÁ
A39: ANTIOQUIA | B39: COCORNÁ | C39: Municipio | D39: -75,185483 | E39: 6,058295 | G39: CISNEROS | J39: SANTA ROSA | K39: GACHANTIVÁ | O39: SUCRE | S39: GRANADA | V39: YAGUARÁ | Z39: MAGÜÍ | AA39: TIBÚ | AE39: GUACA | AG39: RONCESVALLES | AH39: ULLOA
A40: ANTIOQUIA | B40: CONCEPCIÓN | C40: Municipio | D40: -75,257587 | E40: 6,394348 | G40: COCORNÁ | J40: SANTA ROSA DEL SUR | K40: GÁMEZA | O40: TIMBÍO | S40: GUACHETÁ | Z40: MALLAMA | AA40: TOLEDO | AE40: GUADALUPE | AG40: ROVIRA | AH40: VERSALLES
A41: ANTIOQUIA | B41: CONCORDIA | C41: Municipio | D41: -75,908448 | E41: 6,045738 | G41: CONCEPCIÓN | J41: SIMITÍ | K41: GARAGOA | O41: TIMBIQUÍ | S41: GUADUAS | Z41: MOSQUERA | AA41: VILLA CARO | AE41: GUAPOTÁ | AG41: SALDAÑA | AH41: VIJES
A42: ANTIOQUIA | B42: COPACABANA | C42: Municipio | D42: -75,509384 | E42: 6,348557 | G42: CONCORDIA | J42: SOPLAVIENTO | K42: GUACAMAYAS | O42: TORIBÍO | S42: GUASCA | Z42: NARIÑO | AA42: VILLA DEL ROSARIO | AE42: GUAVATÁ | AG42: SAN ANTONIO | AH42: YOTOCO
A43: ANTIOQUIA | B43: DABEIBA | C43: Municipio | D43: -76,261614 | E43: 6,998112 | G43: COPACABANA | J43: TALAIGUA NUEVO | K43: GUATEQUE | O43: TOTORÓ | S43: GUATAQUÍ | Z43: OLAYA HERRERA | AE43: GÜEPSA | AG43: SAN LUIS | AH43: YUMBO
A44: ANTIOQUIA | B44: DONMATÍAS | C44: Municipio | D44: -75,39263 | E44: 6,485603 | G44: DABEIBA | J44: TIQUISIO | K44: GUAYATÁ | O44: VILLA RICA | S44: GUATAVITA | Z44: OSPINA | AE44: HATO | AG44: SANTA ISABEL | AH44: ZARZAL
A45: ANTIOQUIA | B45: EBÉJICO | C45: Municipio | D45: -75,766413 | E45: 6,325615 | G45: DONMATÍAS | J45: TURBACO | K45: GÜICÁN DE LA SIERRA | S45: GUAYABAL DE SÍQUIMA | Z45: FRANCISCO PIZARRO | AE45: JESÚS MARÍA | AG45: SUÁREZ
A46: ANTIOQUIA | B46: EL BAGRE | C46: Municipio | D46: -74,799097 | E46: 7,5975 | G46: EBÉJICO | J46: TURBANÁ | K46: IZA | S46: GUAYABETAL | Z46: POLICARPA | AE46: JORDÁN | AG46: VALLE DE SAN JUAN
A47: ANTIOQUIA | B47: ENTRERRÍOS | C47: Municipio | D47: -75,517685 | E47: 6,566273 | G47: EL BAGRE | J47: VILLANUEVA | K47: JENESANO | S47: GUTIÉRREZ | Z47: POTOSÍ | AE47: LA BELLEZA | AG47: VENADILLO
A48: ANTIOQUIA | B48: ENVIGADO | C48: Municipio | D48: -75,582192 | E48: 6,166695 | G48: ENTRERRÍOS | J48: ZAMBRANO | K48: JERICÓ | S48: JERUSALÉN | Z48: PROVIDENCIA | AE48: LANDÁZURI | AG48: VILLAHERMOSA
A49: ANTIOQUIA | B49: FREDONIA | C49: Municipio | D49: -75,675072 | E49: 5,928039 | G49: ENVIGADO | K49: LABRANZAGRANDE | S49: JUNÍN | Z49: PUERRES | AE49: LA PAZ | AG49: VILLARRICA
A50: ANTIOQUIA | B50: FRONTINO | C50: Municipio | D50: -76,130765 | E50: 6,776066 | G50: FREDONIA | K50: LA CAPILLA | S50: LA CALERA | Z50: PUPIALES | AE50: LEBRIJA
A51: ANTIOQUIA | B51: GIRALDO | C51: Municipio | D51: -75,952158 | E51: 6,680808 | G51: FRONTINO | K51: LA VICTORIA | S51: LA MESA | Z51: RICAURTE | AE51: LOS SANTOS
A52: ANTIOQUIA | B52: GIRARDOTA | C52: Municipio | D52: -75,444238 | E52: 6,379472 | G52: GIRALDO | K52: LA UVITA | S52: LA PALMA | Z52: ROBERTO PAYÁN | AE52: MACARAVITA
A53: ANTIOQUIA | B53: GÓMEZ PLATA | C53: Municipio | D53: -75,220018 | E53: 6,683269 | G53: GIRARDOTA | K53: VILLA DE LEYVA | S53: LA PEÑA | Z53: SAMANIEGO | AE53: MÁLAGA
A54: ANTIOQUIA | B54: GRANADA | C54: Municipio | D54: -75,184446 | E54: 6,142892 | G54: GÓMEZ PLATA | K54: MACANAL | S54: LA VEGA | Z54: SANDONÁ | AE54: MATANZA
A55: ANTIOQUIA | B55: GUADALUPE | C55: Municipio | D55: -75,239862 | E55: 6,815069 | G55: GRANADA | K55: MARIPÍ | S55: LENGUAZAQUE | Z55: SAN BERNARDO | AE55: MOGOTES
A56: ANTIOQUIA | B56: GUARNE | C56: Municipio | D56: -75,441612 | E56: 6,27787 | G56: GUADALUPE | K56: MIRAFLORES | S56: MACHETÁ | Z56: SAN LORENZO | AE56: MOLAGAVITA
A57: ANTIOQUIA | B57: GUATAPÉ | C57: Municipio | D57: -75,160041 | E57: 6,232461 | G57: GUARNE | K57: MONGUA | S57: MADRID | Z57: SAN PABLO | AE57: OCAMONTE
A58: ANTIOQUIA | B58: HELICONIA | C58: Municipio | D58: -75,734322 | E58: 6,206757 | G58: GUATAPÉ | K58: MONGUÍ | S58: MANTA | Z58: SAN PEDRO DE CARTAGO | AE58: OIBA
A59: ANTIOQUIA | B59: HISPANIA | C59: Municipio | D59: -75,906587 | E59: 5,799461 | G59: HELICONIA | K59: MONIQUIRÁ | S59: MEDINA | Z59: SANTA BÁRBARA | AE59: ONZAGA
A60: ANTIOQUIA | B60: ITAGÜÍ | C60: Municipio | D60: -75,612056 | E60: 6,175079 | G60: HISPANIA | K60: MOTAVITA | S60: MOSQUERA | Z60: SANTACRUZ | AE60: PALMAR
A61: ANTIOQUIA | B61: ITUANGO | C61: Municipio | D61: -75,764673 | E61: 7,171629 | G61: ITAGÜÍ | K61: MUZO | S61: NARIÑO | Z61: SAPUYES | AE61: PALMAS DEL SOCORRO
... A66: ANTIOQUIA | B66: LA PINTADA | C66: Municipio | D66: -75,60781 | E66: 5,743808 | G66: LA ESTRELLA | K66: PACHAVITA | S66: VENECIA | Z66: YACUANQUER | AE66: PUERTO PARRA
A67: ANTIOQUIA | B67: LA UNIÓN | C67: Municipio | D67: -75,360874 | E67: 5,973845 | G67: LA PINTADA | K67: PÁEZ | S67: PACHO | AE67: PUERTO WILCHES
A68: ANTIOQUIA | B68: LIBORINA | C68: Municipio | D68: -75,812838 | E68: 6,677316 | G68: LA UNIÓN | K68: PAIPA | S68: PAIME | AE68: RIONEGRO
A69: ANTIOQUIA | B69: MACEO | C69: Municipio | D69: -74,78716 | E69: 6,552116 | G69: LIBORINA | K69: PAJARITO | S69: PANDI | AE69: SABANA DE TORRES
A70: ANTIOQUIA | B70: MARINILLA | C70: Municipio | D70: -75,339345 | E70: 6,173995 | G70: MACEO | K70: PANQUEBA | S70: PARATEBUENO | AE70: SAN ANDRÉS
A71: ANTIOQUIA | B71: MONTEBELLO | C71: Municipio | D71: -75,523455 | E71: 5,946313 | G71: MARINILLA | K71: PAUNA | S71: PASCA | AE71: SAN BENITO
A72: ANTIOQUIA | B72: MURINDÓ | C72: Municipio | D72: -76,817485 | E72: 6,97771 | G72: MONTEBELLO | K72: PAYA | S72: PUERTO SALGAR | AE72: SAN GIL
A73: ANTIOQUIA | B73: MUTATÁ | C73: Municipio | D73: -76,435875 | E73: 7,242875 | G73: MURINDÓ | K73: PAZ DE RÍO | S73: PULÍ | AE73: SAN JOAQUÍN
A74: ANTIOQUIA | B74: NARIÑO | C74: Municipio | D74: -75,176262 | E74: 5,610777 | G74: MUTATÁ | K74: PESCA | S74: QUEBRADANEGRA | AE74: SAN JOSÉ DE MIRANDA
A75: ANTIOQUIA | B75: NECOCLÍ | C75: Municipio | D75: -76,787271 | E75: 8,434526 | G75: NARIÑO | K75: PISBA | S75: QUETAME | AE75: SAN MIGUEL
A76: ANTIOQUIA | B76: NECHÍ | C76: Municipio | D76: -74,77647 | E76: 8,094129 | G76: NECOCLÍ | K76: PUERTO BOYACÁ | S76: QUIPILE | AE76: SAN VICENTE DE CHUCURÍ
A77: ANTIOQUIA | B77: OLAYA | C77: Municipio | D77: -75,811773 | E77: 6,626492 | G77: NECHÍ | K77: QUÍPAMA | S77: APULO | AE77: SANTA BÁRBARA
A78: ANTIOQUIA | B78: PEÑOL | C78: Municipio | D78: -75,242693 | E78: 6,219349 | G78: OLAYA | K78: RAMIRIQUÍ | S78: RICAURTE | AE78: SANTA HELENA DEL OPÓN
... A89: ANTIOQUIA | B89: SALGAR | C89: Municipio | D89: -75,976807 | E89: 5,964198 | G89: SABANETA | K89: SAN PABLO DE BORBUR | S89: SOACHA | AE89: ZAPATOCA
A90: ANTIOQUIA | B90: SAN ANDRÉS DE CUERQUÍA | C90: Municipio | D90: -75,674564 | E90: 6,916676 | G90: SALGAR | K90: SANTANA | S90: SOPÓ
A91: ANTIOQUIA | B91: SAN CARLOS | C91: Municipio | D91: -74,988097 | E91: 6,187746 | G91: SAN ANDRÉS DE CUERQUÍA | K91: SANTA MARÍA | S91: SUBACHOQUE
A92: ANTIOQUIA | B92: SAN FRANCISCO | C92: Municipio | D92: -75,101562 | E92: 5,963476 | G92: SAN CARLOS | K92: SANTA ROSA DE VITERBO | S92: SUESCA
A93: ANTIOQUIA | B93: SAN JERÓNIMO | C93: Municipio | D93: -75,726975 | E93: 6,44809 | G93: SAN FRANCISCO | K93: SANTA SOFÍA | S93: SUPATÁ
A94: ANTIOQUIA | B94: SAN JOSÉ DE LA MONTAÑA | C94: Municipio | D94: -75,683352 | E94: 6,85009 | G94: SAN JERÓNIMO | K94: SATIVANORTE | S94: SUSA
A95: ANTIOQUIA | B95: SAN JUAN DE URABÁ | C95: Municipio | D95: -76,52857 | E95: 8,758964 | G95: SAN JOSÉ DE LA MONTAÑA | K95: SATIVASUR | S95: SUTATAUSA
A96: ANTIOQUIA | B96: SAN LUIS | C96: Municipio | D96: -74,993619 | E96: 6,043017 | G96: SAN JUAN DE URABÁ | K96: SIACHOQUE | S96: TABIO
A97: ANTIOQUIA | B97: SAN PEDRO DE LOS MILAGROS | C97: Municipio | D97: -75,556743 | E97: 6,46012 | G97: SAN LUIS | K97: SOATÁ | S97: TAUSA
A98: ANTIOQUIA | B98: SAN PEDRO DE URABÁ | C98: Municipio | D98: -76,380567 | E98: 8,276884 | G98: SAN PEDRO DE LOS MILAGROS | K98: SOCOTÁ | S98: TENA
A99: ANTIOQUIA | B99: SAN RAFAEL | C99: Municipio | D99: -75,02849 | E99: 6,293759 | G99: SAN PEDRO DE URABÁ | K99: SOCHA | S99: TENJO
A100: ANTIOQUIA | B100: SAN ROQUE | C100: Municipio | D100: -75,019109 | E100: 6,485939 | G100: SAN RAFAEL | K100: SOGAMOSO | S100: TIBACUY
A101: ANTIOQUIA | B101: SAN VICENTE FERRER | C101: Municipio | D101: -75,332616 | E101: 6,282164 | G101: SAN ROQUE | K101: SOMONDOCO | S101: TIBIRITA
... A118: ANTIOQUIA | B118: VALPARAÍSO | C118: Municipio | D118: -75,624452 | E118: 5,614555 | G118: VALDIVIA | K118: TUNUNGUÁ | S118: ZIPAQUIRÁ
A119: ANTIOQUIA | B119: VEGACHÍ | C119: Municipio | D119: -74,798714 | E119: 6,773525 | G119: VALPARAÍSO | K119: TURMEQUÉ
A120: ANTIOQUIA | B120: VENECIA | C120: Municipio | D120: -75,735544 | E120: 5,964693 | G120: VEGACHÍ | K120: TUTA
A121: ANTIOQUIA | B121: VIGÍA DEL FUERTE | C121: Municipio | D121: -76,896004 | E121: 6,588164 | G121: VENECIA | K121: TUTAZÁ
A122: ANTIOQUIA | B122: YALÍ | C122: Municipio | D122: -74,840059 | E122: 6,676554 | G122: VIGÍA DEL FUERTE | K122: ÚMBITA
A123: ANTIOQUIA | B123: YARUMAL | C123: Municipio | D123: -75,418828 | E123: 6,963832 | G123: YALÍ | K123: VENTAQUEMADA
A124: ANTIOQUIA | B124: YOLOMBÓ | C124: Municipio | D124: -75,013385 | E124: 6,594511 | G124: YARUMAL | K124: VIRACACHÁ
A125: ANTIOQUIA | B125: YONDÓ | C125: Municipio | D125: -73,912445 | E125: 7,00396 | G125: YOLOMBÓ | K125: ZETAQUIRA
A126: ANTIOQUIA | B126: ZARAGOZA | C126: Municipio | D126: -74,867075 | E126: 7,488583 | G126: YONDÓ
A127: ATLÁNTICO | B127: BARRANQUILLA | C127: Municipio | D127: -74,815546 | E127: 10,977961 | G127: ZARAGOZA
A128: ATLÁNTICO | B128: BARANOA | C128: Municipio | D128: -74,916077 | E128: 10,79445
A129: ATLÁNTICO | B129: CAMPO DE LA CRUZ | C129: Municipio | D129: -74,880847 | E129: 10,378291
A130: ATLÁNTICO | B130: CANDELARIA | C130: Municipio | D130: -74,879717 | E130: 10,461903
...

Sheet Base_datActividades_priorFIN
A2: CULTIVO | B2: VARIEDAD | C2: TIPO CULTIVO | D2: SISTEMA PRODUCTIVO | E2: EDAD (AÑOS) | F2: CONDICION FITOSANITARIA | G2: DISTANCIA PLANTA (m) | H2: DISTANCIA SURCO (m) | I2: DENSIDAD DE SIEMBRA (plantas/ha) | J2: AREA DE CULTIVO (ha) | K2: RENDIMIENTO PRODUCTO EN FRESCO (kg/ha) | M2: Area Referencia | N2: {=IF(TRIM(K2)="Mano de Obra",IF(Formulario!$L$23<>"",Formulario!$L$23,IFERROR(VLOOKUP(TRIM($M$4),Jornalesdeppto!A:C,3,0),"")),_xlfn.XLOOKUP(1,(Tabla_Costos_Insumos!$A$2:$A$2928=TRIM($M$4))*(Tabla_Costos_Insumos!$C$2:$C$2928=TRIM(K2)),Tabla_Costos_Insumos!$E$2:$E$2928,"",0))}
A3: =Formulario!$A$22 -> Plátano | B3: =Formulario!$B$22 -> Domínico hartón | C3: =Formulario!C$22 -> Permanente | D3: =Formulario!D$22 -> Convencional | E3: =Formulario!E$22 -> 6 | F3: =Formulario!F$22 -> BUENO | G3: =Formulario!G$22 -> 3 | H3: =Formulario!H$22 -> 2.5 | I3: =Formulario!I$22 -> 1540 | J3: =Formulario!J$22 -> 1 | K3: =Formulario!K$22 -> 0 | M3: =CONCATENATE(A3," ",B3) -> Plátano Domínico hartón | N3: {=IF(TRIM(K3)="Mano de Obra",IF(Formulario!$L$23<>"",Formulario!$L$23,IFERROR(VLOOKUP(TRIM($M$4),Jornalesdeppto!A:C,3,0),"")),_xlfn.XLOOKUP(1,(Tabla_Costos_Insumos!$A$2:$A$2928=TRIM($M$4))*(Tabla_Costos_Insumos!$C$2:$C$2928=TRIM(K3)),Tabla_Costos_Insumos!$E$2:$E$2928,"",0))}
A4: Condición hídrica del predio | B4: =Formulario!B$23 -> Con disponibilidad de agua permanente | C4: =Formulario!C$23 -> Regimen de lluvias | D4: =Formulario!D$23 -> Bimodal | E4: =Formulario!E$23 -> Precipitacion anual (mm/año) | F4: =Formulario!F$23 -> 1200 | G4: =Formulario!G$23 -> MARCO DE PLANTACIÓN | H4: =Formulario!H$23 -> tres bolillo | I4: =Formulario!I$23 -> COSTO DE ARRIENDO Ha/AÑO | J4: =Formulario!$J$23 -> 500000 | M4: =Formulario!B7 -> CAUCA | P4: =IF(H23="aguacate hass", (G22 * H22) / 480, "")
A5: Costo del jornal | B5: =Formulario!$L$23 -> 0 | C5: pendiente | D5: =Formulario!G17 -> 25
A7: 4. COSTOS DE PRODUCCIÓN ($/ha)
A9: Cultivo | B9: =A3 -> Plátano | C9: Variedad | D9: =B3 -> Domínico hartón | E9: Año | F9: Establecimiento | H9: Vida remanente | J9: Precio comercializacón (Kg)
A16: CULTIVO | B16: VARIEDAD | C16: AÑO | D16: COD_RUBRO | E16: NOM_RUBRO | F16: COD_SUBRUB | G16: NOM_SUBRUB | H16: COD_ACTV | I16: NOM_ACTV | J16: TIPO_INSUMO | K16: NOM_INSUMO | L16: PRESEN_INSUM | M16: CANTID_INSUM | N16: PREC_UNI | O16: PRECIO_T | P16: CULTIVO_VARIEDAD | Q16: TIPO DE MEDICIÓN | R16: TIEMPO DE EJECUCIÓN ACTIVIDAD (minutos) | S16: JORNAL DE REFERENCIA | T16: FACTOR DE AJUSTE | U16: JORNALES POR ACTIVIDAD | V16: FRECUENCIA (REPETICIONES_AÑO) | W16: TOTAL JORNALES AÑO | X16: jornal base correccion
A17: Aguacate | B17: Hass | C17: Mantenimiento | D17: 1. | E17: Labores | F17: 1.3. | G17: Preparacion de Tierras | H17: 1.3.5. | I17: Fertilización, correctivos y riego | J17: Varios | K17: Mano de Obra | L17: Jornal | M17: =IF(W17<>"", W17, ROUNDUP(X17*T17, 0)) -> 7 | N17: {=IF(TRIM(K17)="Mano de Obra",IF(Formulario!$L$23<>"",Formulario!$L$23,IFERROR(VLOOKUP(TRIM($M$4),Jornalesdeppto!A:C,3,0),"")),_xlfn.XLOOKUP(1,(Tabla_Costos_Insumos!$A$2:$A$3199=TRIM($M$4))*(Tabla_Costos_Insumos!$C$2:$C$3199=TRIM(K17)),Tabla_Costos_Insumos!$E$2:$E$3199,"",0))} -> 46666.667 | O17: =IF(OR(N17=0,N17=""),"",N17*M17) -> 326666.67 | P17: =CONCATENATE(A17," ",B17) -> Aguacate Hass | Q17: Individuo | R17: 5 | S17: =IF($M$3="Aguacate Hass",($I$3*R17) / 480,"") | T17: {=_xlfn.IFS($D$5<=7, 1.1, $D$5<=12,1.2, $D$5<=25, 1.3, $D$5>25,1.4)} -> 1.3 | U17: =IFERROR(S17*T17,"") | V17: 1 | W17: =IFERROR(ROUNDUP(V17*U17,0),"") | X17: 5
A18: Aguacate | B18: Hass | C18: Mantenimiento | D18: 1. | E18: Labores | F18: 1.4. | G18: Siembra y Sostenimiento | H18: 1.4.4. | I18: Deschuponada | J18: Varios | K18: Mano de Obra | L18: Jornal | M18: =IF(W18<>"", W18, ROUNDUP(X18*T18, 0)) -> 13 | N18: {=IF(TRIM(K18)="Mano de Obra",IF(Formulario!$L$23<>"",Formulario!$L$23,IFERROR(VLOOKUP(TRIM($M$4),Jornalesdeppto!A:C,3,0),"")),_xlfn.XLOOKUP(1,(Tabla_Costos_Insumos!$A$2:$A$3199=TRIM($M$4))*(Tabla_Costos_Insumos!$C$2:$C$3199=TRIM(K18)),Tabla_Costos_Insumos!$E$2:$E$3199,"",0))} -> 46666.667 | O18: =IF(OR(N18=0,N18=""),"",N18*M18) -> 606666.67 | P18: =CONCATENATE(A18," ",B18) -> Aguacate Hass | Q18: Individuo | R18: 0.4 | S18: =IF($M$3="Aguacate Hass",($I$3*R18) / 480,"") | T18: {=_xlfn.IFS($D$5<=7, 1.1, $D$5<=12,1.2, $D$5<=25, 1.3, $D$5>25,1.4)} -> 1.3 | U18: =IFERROR(S18*T18,"") | V18: 2 | W18: =IFERROR(ROUNDUP(V18*U18,0),"") | X18: 10
A19: Aguacate | B19: Hass | C19: Mantenimiento | D19: 1. | E19: Labores | F19: 1.5. | G19: Labores Culturales | H19: 1.5.3. | I19: Colgada Poda y Cicatrizacion | J19: Varios | K19: Mano de Obra | L19: Jornal | M19: =IF(W19<>"", W19, ROUNDUP(X19*T19, 0)) -> 13 | N19: {=IF(TRIM(K19)="Mano de Obra",IF(Formulario!$L$23<>"",Formulario!$L$23,IFERROR(VLOOKUP(TRIM($M$4),Jornalesdeppto!A:C,3,0),"")),_xlfn.XLOOKUP(1,(Tabla_Costos_Insumos!$A$2:$A$3199=TRIM($M$4))*(Tabla_Costos_Insumos!$C$2:$C$3199=TRIM(K19)),Tabla_Costos_Insumos!$E$2:$E$3199,"",0))} -> 46666.667 | O19: =IF(OR(N19=0,N19=""),"",N19*M19) -> 606666.67 | P19: =CONCATENATE(A19," ",B19) -> Aguacate Hass | Q19: Individuo | R19: 3 | S19: =IF($M$3="Aguacate Hass",($I$3*R19) / 480,"") | T19: {=_xlfn.IFS($D$5<=7, 1.1, $D$5<=12,1.2, $D$5<=25, 1.3, $D$5>25,1.4)} -> 1.3 | U19: =IFERROR(S19*T19,"") | V19: 2 | W19: =IFERROR(ROUNDUP(V19*U19,0),"") | X19: 10
A20: Aguacate | B20: Hass | C20: Mantenimiento | D20: 1. | E20: Labores | F20: 1.6. | G20: Control Sanitario | H20: 1.6.1. | I20: Aplicación de Fungicidas | J20: Varios | K20: Mano de Obra | L20: Jornal | M20: =IF(W20<>"", W20, ROUNDUP(X20*T20, 0)) -> 11 | N20: {=IF(TRIM(K20)="Mano de Obra",IF(Formulario!$L$23<>"",Formulario!$L$23,IFERROR(VLOOKUP(TRIM($M$4),Jornalesdeppto!A:C,3,0),"")),_xlfn.XLOOKUP(1,(Tabla_Costos_Insumos!$A$2:$A$3199=TRIM($M$4))*(Tabla_Costos_Insumos!$C$2:$C$3199=TRIM(K20)),Tabla_Costos_Insumos!$E$2:$E$3199,"",0))} -> 46666.667 | O20: =IF(OR(N20=0,N20=""),"",N20*M20) -> 513333.33 | P20: =CONCATENATE(A20," ",B20) -> Aguacate Hass | Q20: Individuo | R20: 3 | S20: =IF($M$3="Aguacate Hass",($I$3*R20) / 480,"") | T20: {=_xlfn.IFS($D$5<=7, 1.1, $D$5<=12,1.2, $D$5<=25, 1.3, $D$5>25,1.4)} -> 1.3 | U20: =IFERROR(S20*T20,"") | V20: 9 | W20: =IFERROR(ROUNDUP(V20*U20,0),"") | X20: 8
A21: Aguacate | B21: Hass | C21: Mantenimiento | D21: 1. | E21: Labores | F21: 1.6. | G21: Control Sanitario | H21: 1.6.2. | I21: Aplicación de Insecticidas | J21: Varios | K21: Mano de Obra | L21: Jornal | M21: =IF(W21<>"", W21, ROUNDUP(X21*T21, 0)) -> 11 | N21: {=IF(TRIM(K21)="Mano de Obra",IF(Formulario!$L$23<>"",Formulario!$L$23,IFERROR(VLOOKUP(TRIM($M$4),Jornalesdeppto!A:C,3,0),"")),_xlfn.XLOOKUP(1,(Tabla_Costos_Insumos!$A$2:$A$3199=TRIM($M$4))*(Tabla_Costos_Insumos!$C$2:$C$3199=TRIM(K21)),Tabla_Costos_Insumos!$E$2:$E$3199,"",0))} -> 46666.667 | O21: =IF(OR(N21=0,N21=""),"",N21*M21) -> 513333.33 | P21: =CONCATENATE(A21," ",B21) -> Aguacate Hass | Q21: Individuo | R21: 3 | S21: =IF($M$3="Aguacate Hass",($I$3*R21) / 480,"") | T21: {=_xlfn.IFS($D$5<=7, 1.1, $D$5<=12,1.2, $D$5<=25, 1.3, $D$5>25,1.4)} -> 1.3 | U21: =IFERROR(S21*T21,"") | V21: 9 | W21: =IFERROR(ROUNDUP(V21*U21,0),"") | X21: 8
A22: Aguacate | B22: Hass | C22: Mantenimiento | D22: 1. | E22: Labores | F22: 1.7. | G22: Control de Malezas | H22: 1.7.1. | I22: Aplicación de Herbicidas Preemergentes | J22: Varios | K22: Mano de Obra | L22: Jornal | M22: =IF(W22<>"", W22, ROUNDUP(X22*T22, 0)) -> 7 | N22: {=IF(TRIM(K22)="Mano de Obra",IF(Formulario!$L$23<>"",Formulario!$L$23,IFERROR(VLOOKUP(TRIM($M$4),Jornalesdeppto!A:C,3,0),"")),_xlfn.XLOOKUP(1,(Tabla_Costos_Insumos!$A$2:$A$3199=TRIM($M$4))*(Tabla_Costos_Insumos!$C$2:$C$3199=TRIM(K22)),Tabla_Costos_Insumos!$E$2:$E$3199,"",0))} -> 46666.667 | O22: =IF(OR(N22=0,N22=""),"",N22*M22) -> 326666.67 | P22: =CONCATENATE(A22," ",B22) -> Aguacate Hass | Q22: Area | R22: 0.09 | S22: =10000*R22/480 -> 1.875 | T22: {=_xlfn.IFS($D$5<=7, 1.1, $D$5<=12,1.2, $D$5<=25, 1.3, $D$5>25,1.4)} -> 1.3 | U22: =IFERROR(S22*T22,"") -> 2.4375 | V22: 2 | X22: 5
A23: Aguacate | B23: Hass | C23: Mantenimiento | D23: 1. | E23: Labores | F23: 1.7. | G23: Control de Malezas | H23: 1.7.3. | I23: Desyerbas - Postemergente | J23: Varios | K23: Mano de Obra | L23: Jornal | M23: =IF(W23<>"", W23, ROUNDUP(X23*T23, 0)) -> 7 | N23: {=IF(TRIM(K23)="Mano de Obra",IF(Formulario!$L$23<>"",Formulario!$L$23,IFERROR(VLOOKUP(TRIM($M$4),Jornalesdeppto!A:C,3,0),"")),_xlfn.XLOOKUP(1,(Tabla_Costos_Insumos!$A$2:$A$3199=TRIM($M$4))*(Tabla_Costos_Insumos!$C$2:$C$3199=TRIM(K23)),Tabla_Costos_Insumos!$E$2:$E$3199,"",0))} -> 46666.667 | O23: =IF(OR(N23=0,N23=""),"",N23*M23) -> 326666.67 | P23: =CONCATENATE(A23," ",B23) -> Aguacate Hass | Q23: Area | R23: 0.8 | S23: =10000*R23/480 -> 16.666667 | T23: {=_xlfn.IFS($D$5<=7, 1.1, $D$5<=12,1.2, $D$5<=25, 1.3, $D$5>25,1.4)} -> 1.3 | U23: =IFERROR(S23*T23,"") -> 21.666667 | V23: 2 | X23: 5
A24: Aguacate | B24: Hass | C24: Mantenimiento | D24: 1. | E24: Labores | F24: 1.8. | G24: Fertilizacion | H24: 1.8.1. | I24: Fertilizante Compuesto | J24: Varios | K24: Mano de Obra | L24: Jornal | M24: =IF(W24<>"", W24, ROUNDUP(X24*T24, 0)) -> 10 | N24: {=IF(TRIM(K24)="Mano de Obra",IF(Formulario!$L$23<>"",Formulario!$L$23,IFERROR(VLOOKUP(TRIM($M$4),Jornalesdeppto!A:C,3,0),"")),_xlfn.XLOOKUP(1,(Tabla_Costos_Insumos!$A$2:$A$3199=TRIM($M$4))*(Tabla_Costos_Insumos!$C$2:$C$3199=TRIM(K24)),Tabla_Costos_Insumos!$E$2:$E$3199,"",0))} -> 46666.667 | O24: =IF(OR(N24=0,N24=""),"",N24*M24) -> 466666.67 | P24: =CONCATENATE(A24," ",B24) -> Aguacate Hass | Q24: Individuo | R24: 0.8 | S24: =IF($M$3="Aguacate Hass",($I$3*R24) / 480,"") | T24: {=_xlfn.IFS($D$5<=7, 1.1, $D$5<=12,1.2, $D$5<=25, 1.3, $D$5>25,1.4)} -> 1.3 | U24: =IFERROR(S24*T24,"") | V24: 4 | W24: =IFERROR(ROUNDUP(V24*U24,0),"") | X24: 7
A25: Aguacate | B25: Hass | C25: Mantenimiento | D25: 1. | E25: Labores | F25: 1.8. | G25: Fertilizacion | H25: 1.8.2. | I25: Fertilizante Simple | J25: Varios | K25: Mano de Obra | L25: Jornal | M25: =IF(W25<>"", W25, ROUNDUP(X25*T25, 0)) -> 6 | N25: {=IF(TRIM(K25)="Mano de Obra",IF(Formulario!$L$23<>"",Formulario!$L$23,IFERROR(VLOOKUP(TRIM($M$4),Jornalesdeppto!A:C,3,0),"")),_xlfn.XLOOKUP(1,(Tabla_Costos_Insumos!$A$2:$A$3199=TRIM($M$4))*(Tabla_Costos_Insumos!$C$2:$C$3199=TRIM(K25)),Tabla_Costos_Insumos!$E$2:$E$3199,"",0))} -> 46666.667 | O25: =IF(OR(N25=0,N25=""),"",N25*M25) -> 280000 | P25: =CONCATENATE(A25," ",B25) -> Aguacate Hass | Q25: Individuo | R25: 0.5 | S25: =IF($M$3="Aguacate Hass",($I$3*R25) / 480,"") | T25: {=_xlfn.IFS($D$5<=7, 1.1, $D$5<=12,1.2, $D$5<=25, 1.3, $D$5>25,1.4)} -> 1.3 | U25: =IFERROR(S25*T25,"") | V25: 4 | W25: =IFERROR(ROUNDUP(V25*U25,0),"") | X25: 4
A26: Aguacate | B26: Hass | C26: Mantenimiento | D26: 1. | E26: Labores | F26: 1.8. | G26: Fertilizacion | H26: 1.8.3. | I26: Fertilizantes Foliares | J26: Varios | K26: Mano de Obra | L26: Jornal | M26: =IF(W26<>"", W26, ROUNDUP(X26*T26, 0)) -> 6 | N26: {=IF(TRIM(K26)="Mano de Obra",IF(Formulario!$L$23<>"",Formulario!$L$23,IFERROR(VLOOKUP(TRIM($M$4),Jornalesdeppto!A:C,3,0),"")),_xlfn.XLOOKUP(1,(Tabla_Costos_Insumos!$A$2:$A$3199=TRIM($M$4))*(Tabla_Costos_Insumos!$C$2:$C$3199=TRIM(K26)),Tabla_Costos_Insumos!$E$2:$E$3199,"",0))} -> 46666.667 | O26: =IF(OR(N26=0,N26=""),"",N26*M26) -> 280000 | P26: =CONCATENATE(A26," ",B26) -> Aguacate Hass | Q26: Individuo | R26: 4 | S26: =IF($M$3="Aguacate Hass",($I$3*R26) / 480,"") | T26: {=_xlfn.IFS($D$5<=7, 1.1, $D$5<=12,1.2, $D$5<=25, 1.3, $D$5>25,1.4)} -> 1.3 | U26: =IFERROR(S26*T26,"") | V26: 4 | W26: =IFERROR(ROUNDUP(V26*U26,0),"") | X26: 4
A27: Aguacate | B27: Hass | C27: Mantenimiento | D27: 1. | E27: Labores | F27: 1.9. | G27: Cosecha y Beneficio | H27: 1.9.6. | I27: Pesada Limpieza y Secamiento | J27: Varios | K27: Mano de Obra | L27: Jornal | M27: =IF(W27<>"", W27, ROUNDUP(X27*T27, 0)) -> 33 | N27: {=IF(TRIM(K27)="Mano de Obra",IF(Formulario!$L$23<>"",Formulario!$L$23,IFERROR(VLOOKUP(TRIM($M$4),Jornalesdeppto!A:C,3,0),"")),_xlfn.XLOOKUP(1,(Tabla_Costos_Insumos!$A$2:$A$3199=TRIM($M$4))*(Tabla_Costos_Insumos!$C$2:$C$3199=TRIM(K27)),Tabla_Costos_Insumos!$E$2:$E$3199,"",0))} -> 46666.667 | O27: =IF(OR(N27=0,N27=""),"",N27*M27) -> 1540000 | P27: =CONCATENATE(A27," ",B27) -> Aguacate Hass | T27: {=_xlfn.IFS($D$5<=7, 1.1, $D$5<=12,1.2, $D$5<=25, 1.3, $D$5>25,1.4)} -> 1.3 | X27: 25
A28: Aguacate | B28: Hass | C28: Mantenimiento | D28: 1. | E28: Labores | F28: 1.9. | G28: Cosecha y Beneficio | H28: 1.9.7. | I28: Recolección | J28: Varios | K28: Mano de Obra | L28: Jornal | M28: =IF(W28<>"", W28, ROUNDUP(X28*T28, 0)) -> 39 | N28: {=IF(TRIM(K28)="Mano de Obra",IF(Formulario!$L$23<>"",Formulario!$L$23,IFERROR(VLOOKUP(TRIM($M$4),Jornalesdeppto!A:C,3,0),"")),_xlfn.XLOOKUP(1,(Tabla_Costos_Insumos!$A$2:$A$3199=TRIM($M$4))*(Tabla_Costos_Insumos!$C$2:$C$3199=TRIM(K28)),Tabla_Costos_Insumos!$E$2:$E$3199,"",0))} -> 46666.667 | O28: =IF(OR(N28=0,N28=""),"",N28*M28) -> 1820000 | P28: =CONCATENATE(A28," ",B28) -> Aguacate Hass | T28: {=_xlfn.IFS($D$5<=7, 1.1, $D$5<=12,1.2, $D$5<=25, 1.3, $D$5>25,1.4)} -> 1.3 | X28: 30
A29: Aguacate | B29: Hass | C29: Mantenimiento | D29: 2. | E29: Insumos | F29: 2.2. | G29: Fertilizacion | H29: 2.2.2. | I29: compuestos | J29: Fertilizantes_enmiendas_y_acondicionadores_de_suelo | K29: Fosfato Diamónico (DAP) 18-46-0 | L29: 50 kilogramos | M29: 2 | N29: {=IF(TRIM(K29)="Mano de Obra",IF(Formulario!$L$23<>"",Formulario!$L$23,IFERROR(VLOOKUP(TRIM($M$4),Jornalesdeppto!A:C,3,0),"")),_xlfn.XLOOKUP(1,(Tabla_Costos_Insumos!$A$2:$A$3199=TRIM($M$4))*(Tabla_Costos_Insumos!$C$2:$C$3199=TRIM(K29)),Tabla_Costos_Insumos!$E$2:$E$3199,"",0))} -> 198055.68 | O29: =IF(OR(N29=0,N29=""),"",N29*M29) -> 396111.37 | P29: =CONCATENATE(A29," ",B29) -> Aguacate Hass | T29: {=_xlfn.IFS($D$5<=7, 1.1, $D$5<=12,1.2, $D$5<=25, 1.3, $D$5>25,1.4)} -> 1.3
A30: Aguacate | B30: Hass | C30: Mantenimiento | D30: 2. | E30: Insumos | F30: 2.2. | G30: Fertilizacion | H30: 2.2.3. | I30: Simples | J30: Fertilizantes_enmiendas_y_acondicionadores_de_suelo | K30: Urea 46% | L30: 50 kilogramos | M30: 8 | N30: {=IF(TRIM(K30)="Mano de Obra",IF(Formulario!$L$23<>"",Formulario!$L$23,IFERROR(VLOOKUP(TRIM($M$4),Jornalesdeppto!A:C,3,0),"")),_xlfn.XLOOKUP(1,(Tabla_Costos_Insumos!$A$2:$A$3199=TRIM($M$4))*(Tabla_Costos_Insumos!$C$2:$C$3199=TRIM(K30)),Tabla_Costos_Insumos!$E$2:$E$3199,"",0))} -> 125849.24 | O30: =IF(OR(N30=0,N30=""),"",N30*M30) -> 1006793.9 | P30: =CONCATENATE(A30," ",B30) -> Aguacate Hass
A31: Aguacate | B31: Hass | C31: Mantenimiento | D31: 2. | E31: Insumos | F31: 2.2. | G31: Fertilizacion | H31: 2.2.4. | I31: Correctivos | J31: Fertilizantes_enmiendas_y_acondicionadores_de_suelo | K31: Cal dolomita | L31: 50 kilogramos | M31: 2 | N31: {=IF(TRIM(K31)="Mano de Obra",IF(Formulario!$L$23<>"",Formulario!$L$23,IFERROR(VLOOKUP(TRIM($M$4),Jornalesdeppto!A:C,3,0),"")),_xlfn.XLOOKUP(1,(Tabla_Costos_Insumos!$A$2:$A$3199=TRIM($M$4))*(Tabla_Costos_Insumos!$C$2:$C$3199=TRIM(K31)),Tabla_Costos_Insumos!$E$2:$E$3199,"",0))} -> 17212.5 | O31: =IF(OR(N31=0,N31=""),"",N31*M31) -> 34425 | P31: =CONCATENATE(A31," ",B31) -> Aguacate Hass
A32: Aguacate | B32: Hass | C32: Mantenimiento | D32: 2. | E32: Insumos | F32: 2.2. | G32: Fertilizacion | H32: 2.2.6. | I32: Foliares | J32: Fertilizantes_enmiendas_y_acondicionadores_de_suelo | K32: Crecer 500 | L32: 0,9 kilogramos | M32: 7 | N32: {=IF(TRIM(K32)="Mano de Obra",IF(Formulario!$L$23<>"",Formulario!$L$23,IFERROR(VLOOKUP(TRIM($M$4),Jornalesdeppto!A:C,3,0),"")),_xlfn.XLOOKUP(1,(Tabla_Costos_Insumos!$A$2:$A$3199=TRIM($M$4))*(Tabla_Costos_Insumos!$C$2:$C$3199=TRIM(K32)),Tabla_Costos_Insumos!$E$2:$E$3199,"",0))} -> 11619.376 | O32: =IF(OR(N32=0,N32=""),"",N32*M32) -> 81335.631 | P32: =CONCATENATE(A32," ",B32) -> Aguacate Hass
A33: Aguacate | B33: Hass | C33: Mantenimiento | D33: 2. | E33: Insumos | F33: 2.2. | G33: Fertilizacion | H33: 2.2.7. | I33: Menores | J33: Fertilizantes_enmiendas_y_acondicionadores_de_suelo | K33: Agrimins 8-5-0-6 | L33: 46 kilogramos | M33: 2 | N33: {=IF(TRIM(K33)="Mano de Obra",IF(Formulario!$L$23<>"",Formulario!$L$23,IFERROR(VLOOKUP(TRIM($M$4),Jornalesdeppto!A:C,3,0),"")),_xlfn.XLOOKUP(1,(Tabla_Costos_Insumos!$A$2:$A$3199=TRIM($M$4))*(Tabla_Costos_Insumos!$C$2:$C$3199=TRIM(K33)),Tabla_Costos_Insumos!$E$2:$E$3199,"",0))} -> 128084.44 | O33: =IF(OR(N33=0,N33=""),"",N33*M33) -> 256168.89 | P33: =CONCATENATE(A33," ",B33) -> Aguacate Hass
A34: Aguacate | B34: Hass | C34: Mantenimiento | D34: 2. | E34: Insumos | F34: 2.2. | G34: Fertilizacion | H34: 2.2.8. | I34: Simples | J34: Fertilizantes_enmiendas_y_acondicionadores_de_suelo | K34: Cloruro de Potasio 0-0-60 | L34: 50 kilogramos | M34: 8 | N34: {=IF(TRIM(K34)="Mano de Obra",IF(Formulario!$L$23<>"",Formulario!$L$23,IFERROR(VLOOKUP(TRIM($M$4),Jornalesdeppto!A:C,3,0),"")),_xlfn.XLOOKUP(1,(Tabla_Costos_Insumos!$A$2:$A$3199=TRIM($M$4))*(Tabla_Costos_Insumos!$C$2:$C$3199=TRIM(K34)),Tabla_Costos_Insumos!$E$2:$E$3199,"",0))} -> 110000 | O34: =IF(OR(N34=0,N34=""),"",N34*M34) -> 880000 | P34: =CONCATENATE(A34," ",B34) -> Aguacate Hass
A35: Aguacate | B35: Hass | C35: Mantenimiento | D35: 2. | E35: Insumos | F35: 2.3. | G35: Control Sanitario | H35: 2.3.3. | I35: Fungicida | J35: Fungicidas | K35: FURTIVO 250 SC | L35: 1 litro | M35: 14 | N35: {=IF(TRIM(K35)="Mano de Obra",IF(Formulario!$L$23<>"",Formulario!$L$23,IFERROR(VLOOKUP(TRIM($M$4),Jornalesdeppto!A:C,3,0),"")),_xlfn.XLOOKUP(1,(Tabla_Costos_Insumos!$A$2:$A$3199=TRIM($M$4))*(Tabla_Costos_Insumos!$C$2:$C$3199=TRIM(K35)),Tabla_Costos_Insumos!$E$2:$E$3199,"",0))} -> 115879.72 | O35: =IF(OR(N35=0,N35=""),"",N35*M35) -> 1622316.1 | P35: =CONCATENATE(A35," ",B35) -> Aguacate Hass
A36: Aguacate | B36: Hass | C36: Mantenimiento | D36: 2. | E36: Insumos | F36: 2.3. | G36: Control Sanitario | H36: 2.3.3. | I36: Fungicida | J36: Fungicidas | K36: NATIVO SC | L36: 1 litro | M36: 11 | N36: {=IF(TRIM(K36)="Mano de Obra",IF(Formulario!$L$23<>"",Formulario!$L$23,IFERROR(VLOOKUP(TRIM($M$4),Jornalesdeppto!A:C,3,0),"")),_xlfn.XLOOKUP(1,(Tabla_Costos_Insumos!$A$2:$A$3199=TRIM($M$4))*(Tabla_Costos_Insumos!$C$2:$C$3199=TRIM(K36)),Tabla_Costos_Insumos!$E$2:$E$3199,"",0))} -> 153430.65 | O36: =IF(OR(N36=0,N36=""),"",N36*M36) -> 1687737.1 | P36: =CONCATENATE(A36," ",B36) -> Aguacate Hass
A37: Aguacate | B37: Hass | C37: Mantenimiento | D37: 2. | E37: Insumos | F37: 2.3. | G37: Control Sanitario | H37: 2.3.4. | I37: Herbicida | J37: Herbicidas | K37: Panzer 480 Sl | L37: 1 litro | M37: 14 | N37: {=IF(TRIM(K37)="Mano de Obra",IF(Formulario!$L$23<>"",Formulario!$L$23,IFERROR(VLOOKUP(TRIM($M$4),Jornalesdeppto!A:C,3,0),"")),_xlfn.XLOOKUP(1,(Tabla_Costos_Insumos!$A$2:$A$3199=TRIM($M$4))*(Tabla_Costos_Insumos!$C$2:$C$3199=TRIM(K37)),Tabla_Costos_Insumos!$E$2:$E$3199,"",0))} -> 20153.83 | O37: =IF(OR(N37=0,N37=""),"",N37*M37) -> 282153.62 | P37: =CONCATENATE(A37," ",B37) -> Aguacate Hass
A38: Aguacate | B38: Hass | C38: Mantenimiento | D38: 2. | E38: Insumos | F38: 2.3. | G38: Control Sanitario | H38: 2.3.5. | I38: Insecticida | J38: Insecticidas_acaricidas_y_nematicidas | K38: Abamectina 1,8 Ec | L38: 1 litro | M38: 4 | N38: {=IF(TRIM(K38)="Mano de Obra",IF(Formulario!$L$23<>"",Formulario!$L$23,IFERROR(VLOOKUP(TRIM($M$4),Jornalesdeppto!A:C,3,0),"")),_xlfn.XLOOKUP(1,(Tabla_Costos_Insumos!$A$2:$A$3199=TRIM($M$4))*(Tabla_Costos_Insumos!$C$2:$C$3199=TRIM(K38)),Tabla_Costos_Insumos!$E$2:$E$3199,"",0))} -> 34056.25 | O38: =IF(OR(N38=0,N38=""),"",N38*M38) -> 136225 | P38: =CONCATENATE(A38," ",B38) -> Aguacate Hass
A39: Aguacate | B39: Hass | C39: Mantenimiento | D39: 2. | E39: Insumos | F39: 2.3. | G39: Control Sanitario | H39: 2.3.5. | I39: Insecticida | J39: Insecticidas_acaricidas_y_nematicidas | K39: Proteus 170 Od | L39: 1 litro | M39: 14 | N39: {=IF(TRIM(K39)="Mano de Obra",IF(Formulario!$L$23<>"",Formulario!$L$23,IFERROR(VLOOKUP(TRIM($M$4),Jornalesdeppto!A:C,3,0),"")),_xlfn.XLOOKUP(1,(Tabla_Costos_Insumos!$A$2:$A$3199=TRIM($M$4))*(Tabla_Costos_Insumos!$C$2:$C$3199=TRIM(K39)),Tabla_Costos_Insumos!$E$2:$E$3199,"",0))} -> 151029.59 | O39: =IF(OR(N39=0,N39=""),"",N39*M39) -> 2114414.3 | P39: =CONCATENATE(A39," ",B39) -> Aguacate Hass
A40: Aguacate | B40: Hass | C40: Mantenimiento | D40: 2. | E40: Insumos | F40: 2.7. | G40: Analisis Laboratorio | H40: 2.7.2. | I40: Analisis de Suelos | J40: Varios | K40: Analisis completo de suelos | L40: héctarea | M40: 0.1 | N40: {=IF(TRIM(K40)="Mano de Obra",IF(Formulario!$L$23<>"",Formulario!$L$23,IFERROR(VLOOKUP(TRIM($M$4),Jornalesdeppto!A:C,3,0),"")),_xlfn.XLOOKUP(1,(Tabla_Costos_Insumos!$A$2:$A$3199=TRIM($M$4))*(Tabla_Costos_Insumos!$C$2:$C$3199=TRIM(K40)),Tabla_Costos_Insumos!$E$2:$E$3199,"",0))} -> 175000 | O40: =IF(OR(N40=0,N40=""),"",N40*M40) -> 17500 | P40: =CONCATENATE(A40," ",B40) -> Aguacate Hass
A41: Aguacate | B41: Hass | C41: Mantenimiento | D41: 3. | E41: Otros Costos | F41: 3.1. | G41: Administracion | H41: 3.1.1. | I41: Administración | J41: Otros costos directos | K41: Administración del cultivo | L41: unidad | M41: 1 | N41: =IFERROR(SUM(O17:$O$40)*0.08,0) -> 1289747.8 | O41: =IF(OR(N41=0,N41=""),"",N41*M41) -> 1289747.8 | P41: =CONCATENATE(A41," ",B41) -> Aguacate Hass
A42: Aguacate | B42: Hass | C42: Mantenimiento | D42: 3. | E42: Otros Costos | F42: 3.2. | G42: Asistencia Tecnica | H42: 3.2.1. | I42: Visitas | J42: Varios | K42: Asistencia Técnica | L42: Visita | M42: 1 | N42: {=IF(TRIM(K42)="Mano de Obra",IF(Formulario!$L$23<>"",Formulario!$L$23,IFERROR(VLOOKUP(TRIM($M$4),Jornalesdeppto!A:C,3,0),"")),_xlfn.XLOOKUP(1,(Tabla_Costos_Insumos!$A$2:$A$3199=TRIM($M$4))*(Tabla_Costos_Insumos!$C$2:$C$3199=TRIM(K42)),Tabla_Costos_Insumos!$E$2:$E$3199,"",0))} -> 120000 | O42: =IF(OR(N42=0,N42=""),"",N42*M42) -> 120000 | P42: =CONCATENATE(A42," ",B42) -> Aguacate Hass
A43: Aguacate | B43: Hass | C43: Mantenimiento | D43: 3. | E43: Otros Costos | F43: 3.3. | G43: Arrendamiento | H43: 3.3.1. | I43: Canon | J43: Arrendamiento_de_tierras | K43: Hectárea anual. | L43: unidad | M43: 1 | N43: =$J$4 -> 500000 | O43: =IF(OR(N43=0,N43=""),"",N43*M43) -> 500000 | P43: =CONCATENATE(A43," ",B43) -> Aguacate Hass
A44: Aguacate | B44: Hass | C44: Establecimiento | D44: 1. | E44: Labores | F44: 1.3. | G44: Preparacion de Tierras | H44: 1.3.4. | I44: Construcción Drenajes | J44: Varios | K44: Mano de Obra | L44: Jornal | M44: =IF(W44<>"", W44, ROUNDUP(X44*T44, 0)) -> 4 | N44: {=IF(TRIM(K44)="Mano de Obra",IF(Formulario!$L$23<>"",Formulario!$L$23,IFERROR(VLOOKUP(TRIM($M$4),Jornalesdeppto!A:C,3,0),"")),_xlfn.XLOOKUP(1,(Tabla_Costos_Insumos!$A$2:$A$3199=TRIM($M$4))*(Tabla_Costos_Insumos!$C$2:$C$3199=TRIM(K44)),Tabla_Costos_Insumos!$E$2:$E$3199,"",0))} -> 46666.667 | O44: =IF(OR(N44=0,N44=""),"",N44*M44) -> 186666.67 | P44: =CONCATENATE(A44," ",B44) -> Aguacate Hass | Q44: Distancia | R44: 5 | S44: 0 | T44: {=_xlfn.IFS($D$5<=7, 1.1, $D$5<=12,1.2, $D$5<=25, 1.3, $D$5>25,1.4)} -> 1.3 | V44: 1 | X44: 3
A45: Aguacate | B45: Hass | C45: Establecimiento | D45: 1. | E45: Labores | F45: 1.3. | G45: Preparacion de Tierras | H45: 1.3.5. | I45: Fertilización, correctivos y riego | J45: Varios | K45: Mano de Obra | L45: Jornal | M45: =IF(W45<>"", W45, ROUNDUP(X45*T45, 0)) -> 21 | N45: {=IF(TRIM(K45)="Mano de Obra",IF(Formulario!$L$23<>"",Formulario!$L$23,IFERROR(VLOOKUP(TRIM($M$4),Jornalesdeppto!A:C,3,0),"")),_xlfn.XLOOKUP(1,(Tabla_Costos_Insumos!$A$2:$A$3199=TRIM($M$4))*(Tabla_Costos_Insumos!$C$2:$C$3199=TRIM(K45)),Tabla_Costos_Insumos!$E$2:$E$3199,"",0))} -> 46666.667 | O45: =IF(OR(N45=0,N45=""),"",N45*M45) -> 980000 | P45: =CONCATENATE(A45," ",B45) -> Aguacate Hass | Q45: Individuo | R45: 7 | S45: =IF($M$3="Aguacate Hass",($I$3*R45) / 480,"") | T45: {=_xlfn.IFS($D$5<=7, 1.1, $D$5<=12,1.2, $D$5<=25, 1.3, $D$5>25,1.4)} -> 1.3 | U45: =IFERROR(S45*T45,"") | V45: 1 | W45: =IFERROR(ROUNDUP(V45*U45,0),"") | X45: 16
A46: Aguacate | B46: Hass | C46: Establecimiento | D46: 1. | E46: Labores | F46: 1.3. | G46: Preparacion de Tierras | H46: 1.3.10. | I46: Trazado y Hoyado | J46: Varios | K46: Mano de Obra | L46: Jornal | M46: =IF(W46<>"", W46, ROUNDUP(X46*T46, 0)) -> 10 | N46: {=IF(TRIM(K46)="Mano de Obra",IF(Formulario!$L$23<>"",Formulario!$L$23,IFERROR(VLOOKUP(TRIM($M$4),Jornalesdeppto!A:C,3,0),"")),_xlfn.XLOOKUP(1,(Tabla_Costos_Insumos!$A$2:$A$3199=TRIM($M$4))*(Tabla_Costos_Insumos!$C$2:$C$3199=TRIM(K46)),Tabla_Costos_Insumos!$E$2:$E$3199,"",0))} -> 46666.667 | O46: =IF(OR(N46=0,N46=""),"",N46*M46) -> 466666.67 | P46: =CONCATENATE(A46," ",B46) -> Aguacate Hass | Q46: Individuo | R46: 14 | S46: =IF($M$3="Aguacate Hass",($I$3*R46) / 480,"") | T46: {=_xlfn.IFS($D$5<=7, 1.1, $D$5<=12,1.2, $D$5<=25, 1.3, $D$5>25,1.4)} -> 1.3 | U46: =IFERROR(S46*T46,"") | V46: 1 | W46: =IFERROR(ROUNDUP(V46*U46,0),"") | X46: 7
A47: Aguacate | B47: Hass | C47: Establecimiento | D47: 1. | E47: Labores | F47: 1.3. | G47: Preparacion de Tierras | H47: 1.3.12. | I47: Otras | J47: Varios | K47: Mano de Obra | L47: Jornal | M47: =IF(W47<>"", W47, ROUNDUP(X47*T47, 0)) -> 8 | N47: {=IF(TRIM(K47)="Mano de Obra",IF(Formulario!$L$23<>"",Formulario!$L$23,IFERROR(VLOOKUP(TRIM($M$4),Jornalesdeppto!A:C,3,0),"")),_xlfn.XLOOKUP(1,(Tabla_Costos_Insumos!$A$2:$A$3199=TRIM($M$4))*(Tabla_Costos_Insumos!$C$2:$C$3199=TRIM(K47)),Tabla_Costos_Insumos!$E$2:$E$3199,"",0))} -> 46666.667 | O47: =IF(OR(N47=0,N47=""),"",N47*M47) -> 373333.33 | P47: =CONCATENATE(A47," ",B47) -> Aguacate Hass | Q47: Individuo | R47: 0.2 | S47: =IF($M$3="Aguacate Hass",($I$3*R47) / 480,"") | T47: {=_xlfn.IFS($D$5<=7, 1.1, $D$5<=12,1.2, $D$5<=25, 1.3, $D$5>25,1.4)} -> 1.3 | U47: =IFERROR(S47*T47,"") | V47: 1 | W47: =IFERROR(ROUNDUP(V47*U47,0),"") | X47: 6
A48: Aguacate | B48: Hass | C48: Establecimiento | D48: 1. | E48: Labores | F48: 1.4. | G48: Siembra y Sostenimiento | H48: 1.4.4. | I48: Deschuponada | J48: Varios | K48: Mano de Obra | L48: Jornal | M48: =IF(W48<>"", W48, ROUNDUP(X48*T48, 0)) -> 6 | N48: {=IF(TRIM(K48)="Mano de Obra",IF(Formulario!$L$23<>"",Formulario!$L$23,IFERROR(VLOOKUP(TRIM($M$4),Jornalesdeppto!A:C,3,0),"")),_xlfn.XLOOKUP(1,(Tabla_Costos_Insumos!$A$2:$A$3199=TRIM($M$4))*(Tabla_Costos_Insumos!$C$2:$C$3199=TRIM(K48)),Tabla_Costos_Insumos!$E$2:$E$3199,"",0))} -> 46666.667 | O48: =IF(OR(N48=0,N48=""),"",N48*M48) -> 280000 | P48: =CONCATENATE(A48," ",B48) -> Aguacate Hass | Q48: Individuo | R48: 0.4 | S48: =IF($M$3="Aguacate Hass",($I$3*R48) / 480,"") | T48: {=_xlfn.IFS($D$5<=7, 1.1, $D$5<=12,1.2, $D$5<=25, 1.3, $D$5>25,1.4)} -> 1.3 | U48: =IFERROR(S48*T48,"") | V48: 2 | W48: =IFERROR(ROUNDUP(V48*U48,0),"") | X48: 4
A49: Aguacate | B49: Hass | C49: Establecimiento | D49: 1. | E49: Labores | F49: 1.4. | G49: Siembra y Sostenimiento | H49: 1.4.7. | I49: Resiembra | J49: Varios | K49: Mano de Obra | L49: Jornal | M49: =IF(W49<>"", W49, ROUNDUP(X49*T49, 0)) -> 3 | N49: {=IF(TRIM(K49)="Mano de Obra",IF(Formulario!$L$23<>"",Formulario!$L$23,IFERROR(VLOOKUP(TRIM($M$4),Jornalesdeppto!A:C,3,0),"")),_xlfn.XLOOKUP(1,(Tabla_Costos_Insumos!$A$2:$A$3199=TRIM($M$4))*(Tabla_Costos_Insumos!$C$2:$C$3199=TRIM(K49)),Tabla_Costos_Insumos!$E$2:$E$3199,"",0))} -> 46666.667 | O49: =IF(OR(N49=0,N49=""),"",N49*M49) -> 140000 | P49: =CONCATENATE(A49," ",B49) -> Aguacate Hass | Q49: Individuo | R49: 15 | S49: =IF($M$3="Aguacate Hass",($I$3*R49) / 480,"") | T49: {=_xlfn.IFS($D$5<=7, 1.1, $D$5<=12,1.2, $D$5<=25, 1.3, $D$5>25,1.4)} -> 1.3 | U49: =IFERROR(S49*T49,"") | V49: 1 | W49: =IFERROR(ROUNDUP(V49*U49,0),"") | X49: 2
A50: Aguacate | B50: Hass | C50: Establecimiento | D50: 1. | E50: Labores | F50: 1.4. | G50: Siembra y Sostenimiento | H50: 1.4.8. | I50: Siembra Abonamiento y Tapada | J50: Varios | K50: Mano de Obra | L50: Jornal | M50: =IF(W50<>"", W50, ROUNDUP(X50*T50, 0)) -> 6 | N50: {=IF(TRIM(K50)="Mano de Obra",IF(Formulario!$L$23<>"",Formulario!$L$23,IFERROR(VLOOKUP(TRIM($M$4),Jornalesdeppto!A:C,3,0),"")),_xlfn.XLOOKUP(1,(Tabla_Costos_Insumos!$A$2:$A$3199=TRIM($M$4))*(Tabla_Costos_Insumos!$C$2:$C$3199=TRIM(K50)),Tabla_Costos_Insumos!$E$2:$E$3199,"",0))} -> 46666.667 | O50: =IF(OR(N50=0,N50=""),"",N50*M50) -> 280000 | P50: =CONCATENATE(A50," ",B50) -> Aguacate Hass | Q50: Individuo | R50: 16 | S50: =IF($M$3="Aguacate Hass",($I$3*R50) / 480,"") | T50: {=_xlfn.IFS($D$5<=7, 1.1, $D$5<=12,1.2, $D$5<=25, 1.3, $D$5>25,1.4)} -> 1.3 | U50: =IFERROR(S50*T50,"") | V50: 1 | W50: =IFERROR(ROUNDUP(V50*U50,0),"") | X50: 4
A51: Aguacate | B51: Hass | C51: Establecimiento | D51: 1. | E51: Labores | F51: 1.5. | G51: Labores Culturales | H51: 1.5.3. | I51: Colgada Poda y Cicatrizacion | J51: Varios | K51: Mano de Obra | L51: Jornal | M51: =IF(W51<>"", W51, ROUNDUP(X51*T51, 0)) -> 8 | N51: {=IF(TRIM(K51)="Mano de Obra",IF(Formulario!$L$23<>"",Formulario!$L$23,IFERROR(VLOOKUP(TRIM($M$4),Jornalesdeppto!A:C,3,0),"")),_xlfn.XLOOKUP(1,(Tabla_Costos_Insumos!$A$2:$A$3199=TRIM($M$4))*(Tabla_Costos_Insumos!$C$2:$C$3199=TRIM(K51)),Tabla_Costos_Insumos!$E$2:$E$3199,"",0))} -> 46666.667 | O51: =IF(OR(N51=0,N51=""),"",N51*M51) -> 373333.33 | P51: =CONCATENATE(A51," ",B51) -> Aguacate Hass | Q51: Individuo | R51: 3 | S51: =IF($M$3="Aguacate Hass",($I$3*R51) / 480,"") | T51: {=_xlfn.IFS($D$5<=7, 1.1, $D$5<=12,1.2, $D$5<=25, 1.3, $D$5>25,1.4)} -> 1.3 | U51: =IFERROR(S51*T51,"") | V51: 2 | W51: =IFERROR(ROUNDUP(V51*U51,0),"") | X51: 6
A52: Aguacate | B52: Hass | C52: Establecimiento | D52: 1. | E52: Labores | F52: 1.6. | G52: Control Sanitario | H52: 1.6.1. | I52: Aplicación de Fungicidas | J52: Varios | K52: Mano de Obra | L52: Jornal | M52: =IF(W52<>"", W52, ROUNDUP(X52*T52, 0)) -> 10 | N52: {=IF(TRIM(K52)="Mano de Obra",IF(Formulario!$L$23<>"",Formulario!$L$23,IFERROR(VLOOKUP(TRIM($M$4),Jornalesdeppto!A:C,3,0),"")),_xlfn.XLOOKUP(1,(Tabla_Costos_Insumos!$A$2:$A$3199=TRIM($M$4))*(Tabla_Costos_Insumos!$C$2:$C$3199=TRIM(K52)),Tabla_Costos_Insumos!$E$2:$E$3199,"",0))} -> 46666.667 | O52: =IF(OR(N52=0,N52=""),"",N52*M52) -> 466666.67 | P52: =CONCATENATE(A52," ",B52) -> Aguacate Hass | Q52: Individuo | R52: 4 | S52: =IF($M$3="Aguacate Hass",($I$3*R52) / 480,"") | T52: {=_xlfn.IFS($D$5<=7, 1.1, $D$5<=12,1.2, $D$5<=25, 1.3, $D$5>25,1.4)} -> 1.3 | U52: =IFERROR(S52*T52,"") | V52: 9 | W52: =IFERROR(ROUNDUP(V52*U52,0),"") | X52: 7
A53: Aguacate | B53: Hass | C53: Establecimiento | D53: 1. | E53: Labores | F53: 1.6. | G53: Control Sanitario | H53: 1.6.2. | I53: Aplicación de Insecticidas | J53: Varios | K53: Mano de Obra | L53: Jornal | M53: =IF(W53<>"", W53, ROUNDUP(X53*T53, 0)) -> 10 | N53: {=IF(TRIM(K53)="Mano de Obra",IF(Formulario!$L$23<>"",Formulario!$L$23,IFERROR(VLOOKUP(TRIM($M$4),Jornalesdeppto!A:C,3,0),"")),_xlfn.XLOOKUP(1,(Tabla_Costos_Insumos!$A$2:$A$3199=TRIM($M$4))*(Tabla_Costos_Insumos!$C$2:$C$3199=TRIM(K53)),Tabla_Costos_Insumos!$E$2:$E$3199,"",0))} -> 46666.667 | O53: =IF(OR(N53=0,N53=""),"",N53*M53) -> 466666.67 | P53: =CONCATENATE(A53," ",B53) -> Aguacate Hass | Q53: Individuo | R53: 4 | S53: =IF($M$3="Aguacate Hass",($I$3*R53) / 480,"") | T53: {=_xlfn.IFS($D$5<=7, 1.1, $D$5<=12,1.2, $D$5<=25, 1.3, $D$5>25,1.4)} -> 1.3 | U53: =IFERROR(S53*T53,"") | V53: 9 | W53: =IFERROR(ROUNDUP(V53*U53,0),"") | X53: 7
A54: Aguacate | B54: Hass | C54: Establecimiento | D54: 1. | E54: Labores | F54: 1.7. | G54: Control de Malezas | H54: 1.7.1. | I54: Aplicación de Herbicidas Preemergentes | J54: Varios | K54: Mano de Obra | L54: Jornal | M54: =IF(W54<>"", W54, ROUNDUP(X54*T54, 0)) -> 7 | N54: {=IF(TRIM(K54)="Mano de Obra",IF(Formulario!$L$23<>"",Formulario!$L$23,IFERROR(VLOOKUP(TRIM($M$4),Jornalesdeppto!A:C,3,0),"")),_xlfn.XLOOKUP(1,(Tabla_Costos_Insumos!$A$2:$A$3199=TRIM($M$4))*(Tabla_Costos_Insumos!$C$2:$C$3199=TRIM(K54)),Tabla_Costos_Insumos!$E$2:$E$3199,"",0))} -> 46666.667 | O54: =IF(OR(N54=0,N54=""),"",N54*M54) -> 326666.67 | P54: =CONCATENATE(A54," ",B54) -> Aguacate Hass | Q54: Area | R54: 0.09 | S54: =10000*R54/480 -> 1.875 | T54: {=_xlfn.IFS($D$5<=7, 1.1, $D$5<=12,1.2, $D$5<=25, 1.3, $D$5>25,1.4)} -> 1.3 | U54: =IFERROR(S54*T54,"") -> 2.4375 | V54: 2 | X54: 5
A55: Aguacate | B55: Hass | C55: Establecimiento | D55: 1. | E55: Labores | F55: 1.7. | G55: Control de Malezas | H55: 1.7.3. | I55: Desyerbas - Postemergente | J55: Varios | K55: Mano de Obra | L55: Jornal | M55: =IF(W55<>"", W55, ROUNDUP(X55*T55, 0)) -> 39 | N55: {=IF(TRIM(K55)="Mano de Obra",IF(Formulario!$L$23<>"",Formulario!$L$23,IFERROR(VLOOKUP(TRIM($M$4),Jornalesdeppto!A:C,3,0),"")),_xlfn.XLOOKUP(1,(Tabla_Costos_Insumos!$A$2:$A$3199=TRIM($M$4))*(Tabla_Costos_Insumos!$C$2:$C$3199=TRIM(K55)),Tabla_Costos_Insumos!$E$2:$E$3199,"",0))} -> 46666.667 | O55: =IF(OR(N55=0,N55=""),"",N55*M55) -> 1820000 | P55: =CONCATENATE(A55," ",B55) -> Aguacate Hass | Q55: Area | R55: 0.09 | S55: =10000*R55/480 -> 1.875 | T55: {=_xlfn.IFS($D$5<=7, 1.1, $D$5<=12,1.2, $D$5<=25, 1.3, $D$5>25,1.4)} -> 1.3 | U55: =IFERROR(S55*T55,"") -> 2.4375 | V55: 2 | X55: 30
A56: Aguacate | B56: Hass | C56: Establecimiento | D56: 1. | E56: Labores | F56: 1.8. | G56: Fertilizacion | H56: 1.8.1. | I56: Fertilizante Compuesto | J56: Varios | K56: Mano de Obra | L56: Jornal | M56: =IF(W56<>"", W56, ROUNDUP(X56*T56, 0)) -> 10 | N56: {=IF(TRIM(K56)="Mano de Obra",IF(Formulario!$L$23<>"",Formulario!$L$23,IFERROR(VLOOKUP(TRIM($M$4),Jornalesdeppto!A:C,3,0),"")),_xlfn.XLOOKUP(1,(Tabla_Costos_Insumos!$A$2:$A$3199=TRIM($M$4))*(Tabla_Costos_Insumos!$C$2:$C$3199=TRIM(K56)),Tabla_Costos_Insumos!$E$2:$E$3199,"",0))} -> 46666.667 | O56: =IF(OR(N56=0,N56=""),"",N56*M56) -> 466666.67 | P56: =CONCATENATE(A56," ",B56) -> Aguacate Hass | Q56: Individuo | R56: 1.5 | S56: =IF($M$3="Aguacate Hass",($I$3*R56) / 480,"") | T56: {=_xlfn.IFS($D$5<=7, 1.1, $D$5<=12,1.2, $D$5<=25, 1.3, $D$5>25,1.4)} -> 1.3 | U56: =IFERROR(S56*T56,"") | V56: 4 | W56: =IFERROR(ROUNDUP(V56*U56,0),"") | X56: 7
A57: Aguacate | B57: Hass | C57: Establecimiento | D57: 1. | E57: Labores | F57: 1.8. | G57: Fertilizacion | H57: 1.8.2. | I57: Fertilizante Simple | J57: Varios | K57: Mano de Obra | L57: Jornal | M57: =IF(W57<>"", W57, ROUNDUP(X57*T57, 0)) -> 4 | N57: {=IF(TRIM(K57)="Mano de Obra",IF(Formulario!$L$23<>"",Formulario!$L$23,IFERROR(VLOOKUP(TRIM($M$4),Jornalesdeppto!A:C,3,0),"")),_xlfn.XLOOKUP(1,(Tabla_Costos_Insumos!$A$2:$A$3199=TRIM($M$4))*(Tabla_Costos_Insumos!$C$2:$C$3199=TRIM(K57)),Tabla_Costos_Insumos!$E$2:$E$3199,"",0))} -> 46666.667 | O57: =IF(OR(N57=0,N57=""),"",N57*M57) -> 186666.67 | P57: =CONCATENATE(A57," ",B57) -> Aguacate Hass | Q57: Individuo | R57: 1.5 | S57: =IF($M$3="Aguacate Hass",($I$3*R57) / 480,"") | T57: {=_xlfn.IFS($D$5<=7, 1.1, $D$5<=12,1.2, $D$5<=25, 1.3, $D$5>25,1.4)} -> 1.3 | U57: =IFERROR(S57*T57,"") | V57: 4 | W57: =IFERROR(ROUNDUP(V57*U57,0),"") | X57: 3
A58: Aguacate | B58: Hass | C58: Establecimiento | D58: 1. | E58: Labores | F58: 1.8. | G58: Fertilizacion | H58: 1.8.3. | I58: Fertilizantes Foliares | J58: Varios | K58: Mano de Obra | L58: Jornal | M58: =IF(W58<>"", W58, ROUNDUP(X58*T58, 0)) -> 6 | N58: {=IF(TRIM(K58)="Mano de Obra",IF(Formulario!$L$23<>"",Formulario!$L$23,IFERROR(VLOOKUP(TRIM($M$4),Jornalesdeppto!A:C,3,0),"")),_xlfn.XLOOKUP(1,(Tabla_Costos_Insumos!$A$2:$A$3199=TRIM($M$4))*(Tabla_Costos_Insumos!$C$2:$C$3199=TRIM(K58)),Tabla_Costos_Insumos!$E$2:$E$3199,"",0))} -> 46666.667 | O58: =IF(OR(N58=0,N58=""),"",N58*M58) -> 280000 | P58: =CONCATENATE(A58," ",B58) -> Aguacate Hass | Q58: Individuo | R58: 4 | S58: =IF($M$3="Aguacate Hass",($I$3*R58) / 480,"") | T58: {=_xlfn.IFS($D$5<=7, 1.1, $D$5<=12,1.2, $D$5<=25, 1.3, $D$5>25,1.4)} -> 1.3 | U58: =IFERROR(S58*T58,"") | V58: 4 | W58: =IFERROR(ROUNDUP(V58*U58,0),"") | X58: 4
A59: Aguacate | B59: Hass | C59: Establecimiento | D59: 2. | E59: Insumos | F59: 2.1. | G59: Material Vegetal | H59: 2.1.1. | I59: Semillas o Plantulas | J59: Material_de_propagación | K59: Aguacate Hass (4-6 meses, 30 cm) | L59: unidad | M59: 260 | N59: 16000 | O59: =IF(OR(N59=0,N59=""),"",N59*M59) -> 4160000 | P59: =CONCATENATE(A59," ",B59) -> Aguacate Hass | X59: 260
A60: Aguacate | B60: Hass | C60: Establecimiento | D60: 2. | E60: Insumos | F60: 2.2. | G60: Fertilizacion | H60: 2.2.2. | I60: compuestos | J60: Fertilizantes_enmiendas_y_acondicionadores_de_suelo | K60: Fosfato Diamónico (DAP) 18-46-0 | L60: 50 kilogramos | M60: 1 | N60: {=IF(TRIM(K60)="Mano de Obra",IF(Formulario!$L$23<>"",Formulario!$L$23,IFERROR(VLOOKUP(TRIM($M$4),Jornalesdeppto!A:C,3,0),"")),_xlfn.XLOOKUP(1,(Tabla_Costos_Insumos!$A$2:$A$3199=TRIM($M$4))*(Tabla_Costos_Insumos!$C$2:$C$3199=TRIM(K60)),Tabla_Costos_Insumos!$E$2:$E$3199,"",0))} -> 198055.68 | O60: =IF(OR(N60=0,N60=""),"",N60*M60) -> 198055.68 | P60: =CONCATENATE(A60," ",B60) -> Aguacate Hass | X60: 1
A61: Aguacate | B61: Hass | C61: Establecimiento | D61: 2. | E61: Insumos | F61: 2.2. | G61: Fertilizacion | H61: 2.2.3. | I61: Simples | J61: Fertilizantes_enmiendas_y_acondicionadores_de_suelo | K61: Cloruro de Potasio 0-0-60 | L61: 50 kilogramos | M61: 3 | N61: {=IF(TRIM(K61)="Mano de Obra",IF(Formulario!$L$23<>"",Formulario!$L$23,IFERROR(VLOOKUP(TRIM($M$4),Jornalesdeppto!A:C,3,0),"")),_xlfn.XLOOKUP(1,(Tabla_Costos_Insumos!$A$2:$A$3199=TRIM($M$4))*(Tabla_Costos_Insumos!$C$2:$C$3199=TRIM(K61)),Tabla_Costos_Insumos!$E$2:$E$3199,"",0))} -> 110000 | O61: =IF(OR(N61=0,N61=""),"",N61*M61) -> 330000 | P61: =CONCATENATE(A61," ",B61) -> Aguacate Hass | X61: 3
A62: Aguacate | B62: Hass | C62: Establecimiento | D62: 2. | E62: Insumos | F62: 2.2. | G62: Fertilizacion | H62: 2.2.4. | I62: Correctivos | J62: Fertilizantes_enmiendas_y_acondicionadores_de_suelo | K62: Cal dolomita | L62: 50 kilogramos | M62: 5 | N62: {=IF(TRIM(K62)="Mano de Obra",IF(Formulario!$L$23<>"",Formulario!$L$23,IFERROR(VLOOKUP(TRIM($M$4),Jornalesdeppto!A:C,3,0),"")),_xlfn.XLOOKUP(1,(Tabla_Costos_Insumos!$A$2:$A$3199=TRIM($M$4))*(Tabla_Costos_Insumos!$C$2:$C$3199=TRIM(K62)),Tabla_Costos_Insumos!$E$2:$E$3199,"",0))} -> 17212.5 | O62: =IF(OR(N62=0,N62=""),"",N62*M62) -> 86062.5 | P62: =CONCATENATE(A62," ",B62) -> Aguacate Hass | X62: 5
A63: Aguacate | B63: Hass | C63: Establecimiento | D63: 2. | E63: Insumos | F63: 2.2. | G63: Fertilizacion | H63: 2.2.6. | I63: Foliares | J63: Fertilizantes_enmiendas_y_acondicionadores_de_suelo | K63: Crecer 500 | L63: 900 gramos | M63: 7 | N63: {=IF(TRIM(K63)="Mano de Obra",IF(Formulario!$L$23<>"",Formulario!$L$23,IFERROR(VLOOKUP(TRIM($M$4),Jornalesdeppto!A:C,3,0),"")),_xlfn.XLOOKUP(1,(Tabla_Costos_Insumos!$A$2:$A$3199=TRIM($M$4))*(Tabla_Costos_Insumos!$C$2:$C$3199=TRIM(K63)),Tabla_Costos_Insumos!$E$2:$E$3199,"",0))} -> 11619.376 | O63: =IF(OR(N63=0,N63=""),"",N63*M63) -> 81335.631 | P63: =CONCATENATE(A63," ",B63) -> Aguacate Hass | X63: 7
